Workbook

Sheet RESUMEN
A1: AUTORIDAD NACIONAL DE INFRAESTRUCTURA - ANIN
A2: DIRECCIÓN DE INTERVENCIONES MULTISECTORIALES Y DE EMERGENCIA - DIME
A3: SUBDIRECCIÓN DE ESTUDIOS DE INVERSIÓN
A4: PROYECTO IN PIURA – CUI 2669244 · Motor de costos paramétrico – RESUMEN (versión piloto v1)
A5: Generado el 18-oct-2026. Todas las cifras se recalculan desde PARAMETROS, PAQUETES y BLOQUES. Celdas amarillas = supuestos por calibrar.
A7: Indicador | B7: Piloto (5 bloques) | C7: Cartera (117 bloques) | D7: Unidad
A8: Bloques | B8: =COUNTIF(B_PIL,"Sí") -> 5 | C8: =COUNTA(B_ID) -> 117 | D8: n°
A9: Superficie de bloques | B9: =C_HA_P -> 538.323 | C9: =C_HA_T -> 12270.235 | D9: ha
A10: Plantación activa R1 (MSAVI DN 1–2) | B10: =C_R1_P -> 216.151 | C10: =C_R1_T -> 5503.444 | D10: ha
A11: Enriquecimiento R2 (MSAVI DN 3) | B11: =C_R2_P -> 94.297 | C11: =C_R2_T -> 2838.422 | D11: ha
A12: Plantas a instalar | B12: =C_PL_P -> 172906.33 | C12: =C_PL_T -> 4508650.6 | D12: und
A13: Zanjas de infiltración | B13: =C_KZ_P -> 871.50623 | C13: =C_KZ_T -> 17971.711 | D13: km
A14: Terrazas de formación lenta | B14: =C_KT_P -> 28.272113 | C14: =C_KT_T -> 705.49002 | D14: km
A15: Cerco perimétrico | B15: =C_CE_P -> 26234.8 | C15: =C_CE_T -> 577845.6 | D15: m
A16: Cárcavas (diques) | B16: =C_KC_P -> 0 | C16: =C_KC_T -> 0 | D16: km
A17: Costo directo | B17: =C_CD_P -> 13344299 | C17: =C_CD_T -> 2.9810789e+08 | D17: S/
A18: Inversión total (CD + GG + sup. + ET) | B18: =C_INV_P -> 15356266 | C18: =C_INV_T -> 3.4305467e+08 | D18: S/
A19: · infraestructura verde | B19: =C_VER_P -> 2788611.8 | C19: =C_VER_T -> 71180513 | D19: S/
A20: · infraestructura marrón | B20: =C_MAR_P -> 12567654 | C20: =C_MAR_T -> 2.7187415e+08 | D20: S/
A21: Inversión por ha de bloque | B21: =C_INV_P/C_HA_P -> 28526.119 | C21: =C_INV_T/C_HA_T -> 27958.28 | D21: S/ / ha
A22: O&M – primer año de operación | B22: =OYM!K21 -> 1911221.6 | C22: =OYM!J21 -> 46347297 | D22: S/ / año
A23: O&M – 15 años (sin descontar) | B23: =SUM(FLUJO!C26:V26) -> 12826725 | C23: =SUM(FLUJO!C13:V13) -> 2.8167704e+08 | D23: S/
A24: Inversión + O&M 15 años (sin descontar) | B24: =B18+B23 -> 28182991 | C24: =C18+C23 -> 6.2473171e+08 | D24: S/
A25: Referencia: techo del proyecto (incluye preinversión y ET) | C25: =P_TECHO -> 372442809 | D25: S/
A26: Cartera / techo | C26: =C24/P_TECHO -> 1.6773896 | D26: %
A27: VAC social (TSD 8 %) | B27: =FLUJO!B54 -> 9511139.7 | C27: =FLUJO!B47 -> 2.1364061e+08 | D27: S/
A28: Costo-efectividad (VAC social / ha plantada) | B28: =FLUJO!B58 -> 30636.821 | C28: =FLUJO!B51 -> 25610.65 | D28: S/ / ha
A29: VANS | B29: =FLUJO!B56 -> Pendiente de beneficios | C29: =FLUJO!B49 -> Pendiente de beneficios | D29: S/
A31: Bloque piloto | B31: Tipología | C31: Área (ha) | D31: R1 + R2 (ha) | E31: Plantas | F31: Zanjas / terrazas (km) | G31: Inversión (S/) | H31: S/ por ha | I31: Dist. media acarreo (m) | J31: Grupo · degradación
A32: 21 | B32: =INDEX(CALCULO!$B$7:$B$123,MATCH("21",CALCULO!$A$7:$A$123,0)) -> T6 | C32: =INDEX(CALCULO!$D$7:$D$123,MATCH("21",CALCULO!$A$7:$A$123,0)) -> 84.227 | D32: =INDEX(CALCULO!$E$7:$E$123,MATCH("21",CALCULO!$A$7:$A$123,0))+INDEX(CALCULO!$F$7:$F$123,MATCH("21",CALCULO!$A$7:$A$123,0)) -> 4.357 | E32: =INDEX(CALCULO!$J$7:$J$123,MATCH("21",CALCULO!$A$7:$A$123,0)) -> 1419.275 | F32: =INDEX(CALCULO!$K$7:$K$123,MATCH("21",CALCULO!$A$7:$A$123,0))+INDEX(CALCULO!$L$7:$L$123,MATCH("21",CALCULO!$A$7:$A$123,0)) -> 5.1768207 | G32: =INDEX(CALCULO!$AA$7:$AA$123,MATCH("21",CALCULO!$A$7:$A$123,0)) -> 646128.48 | H32: =INDEX(CALCULO!$AB$7:$AB$123,MATCH("21",CALCULO!$A$7:$A$123,0)) -> 7671.275 | I32: =INDEX(BLOQUES!$AB$7:$AB$123,MATCH("21",CALCULO!$A$7:$A$123,0)) -> 579 | J32: =INDEX(BLOQUES!$AG$7:$AG$123,MATCH("21",CALCULO!$A$7:$A$123,0))&" · "&INDEX(BLOQUES!$AH$7:$AH$123,MATCH("21",CALCULO!$A$7:$A$123,0)) -> MOSAICO · Moderada
A33: 66 | B33: =INDEX(CALCULO!$B$7:$B$123,MATCH("66",CALCULO!$A$7:$A$123,0)) -> T6 | C33: =INDEX(CALCULO!$D$7:$D$123,MATCH("66",CALCULO!$A$7:$A$123,0)) -> 102.335 | D33: =INDEX(CALCULO!$E$7:$E$123,MATCH("66",CALCULO!$A$7:$A$123,0))+INDEX(CALCULO!$F$7:$F$123,MATCH("66",CALCULO!$A$7:$A$123,0)) -> 9.047 | E33: =INDEX(CALCULO!$J$7:$J$123,MATCH("66",CALCULO!$A$7:$A$123,0)) -> 3119.025 | F33: =INDEX(CALCULO!$K$7:$K$123,MATCH("66",CALCULO!$A$7:$A$123,0))+INDEX(CALCULO!$L$7:$L$123,MATCH("66",CALCULO!$A$7:$A$123,0)) -> 10.759243 | G33: =INDEX(CALCULO!$AA$7:$AA$123,MATCH("66",CALCULO!$A$7:$A$123,0)) -> 1284667.1 | H33: =INDEX(CALCULO!$AB$7:$AB$123,MATCH("66",CALCULO!$A$7:$A$123,0)) -> 12553.546 | I33: =INDEX(BLOQUES!$AB$7:$AB$123,MATCH("66",CALCULO!$A$7:$A$123,0)) -> 663 | J33: =INDEX(BLOQUES!$AG$7:$AG$123,MATCH("66",CALCULO!$A$7:$A$123,0))&" · "&INDEX(BLOQUES!$AH$7:$AH$123,MATCH("66",CALCULO!$A$7:$A$123,0)) -> MOSAICO · Moderada
A34: 73 | B34: =INDEX(CALCULO!$B$7:$B$123,MATCH("73",CALCULO!$A$7:$A$123,0)) -> T6 | C34: =INDEX(CALCULO!$D$7:$D$123,MATCH("73",CALCULO!$A$7:$A$123,0)) -> 54.29 | D34: =INDEX(CALCULO!$E$7:$E$123,MATCH("73",CALCULO!$A$7:$A$123,0))+INDEX(CALCULO!$F$7:$F$123,MATCH("73",CALCULO!$A$7:$A$123,0)) -> 10.28 | E34: =INDEX(CALCULO!$J$7:$J$123,MATCH("73",CALCULO!$A$7:$A$123,0)) -> 3653.65 | F34: =INDEX(CALCULO!$K$7:$K$123,MATCH("73",CALCULO!$A$7:$A$123,0))+INDEX(CALCULO!$L$7:$L$123,MATCH("73",CALCULO!$A$7:$A$123,0)) -> 12.336049 | G34: =INDEX(CALCULO!$AA$7:$AA$123,MATCH("73",CALCULO!$A$7:$A$123,0)) -> 1408810.3 | H34: =INDEX(CALCULO!$AB$7:$AB$123,MATCH("73",CALCULO!$A$7:$A$123,0)) -> 25949.72 | I34: =INDEX(BLOQUES!$AB$7:$AB$123,MATCH("73",CALCULO!$A$7:$A$123,0)) -> 598 | J34: =INDEX(BLOQUES!$AG$7:$AG$123,MATCH("73",CALCULO!$A$7:$A$123,0))&" · "&INDEX(BLOQUES!$AH$7:$AH$123,MATCH("73",CALCULO!$A$7:$A$123,0)) -> MOSAICO · Moderada
A35: 31 | B35: =INDEX(CALCULO!$B$7:$B$123,MATCH("31",CALCULO!$A$7:$A$123,0)) -> T3 | C35: =INDEX(CALCULO!$D$7:$D$123,MATCH("31",CALCULO!$A$7:$A$123,0)) -> 47.581 | D35: =INDEX(CALCULO!$E$7:$E$123,MATCH("31",CALCULO!$A$7:$A$123,0))+INDEX(CALCULO!$F$7:$F$123,MATCH("31",CALCULO!$A$7:$A$123,0)) -> 37.311 | E35: =INDEX(CALCULO!$J$7:$J$123,MATCH("31",CALCULO!$A$7:$A$123,0)) -> 17665.535 | F35: =INDEX(CALCULO!$K$7:$K$123,MATCH("31",CALCULO!$A$7:$A$123,0))+INDEX(CALCULO!$L$7:$L$123,MATCH("31",CALCULO!$A$7:$A$123,0)) -> 129.54856 | G35: =INDEX(CALCULO!$AA$7:$AA$123,MATCH("31",CALCULO!$A$7:$A$123,0)) -> 1799213.7 | H35: =INDEX(CALCULO!$AB$7:$AB$123,MATCH("31",CALCULO!$A$7:$A$123,0)) -> 37813.701 | I35: =INDEX(BLOQUES!$AB$7:$AB$123,MATCH("31",CALCULO!$A$7:$A$123,0)) -> 774 | J35: =INDEX(BLOQUES!$AG$7:$AG$123,MATCH("31",CALCULO!$A$7:$A$123,0))&" · "&INDEX(BLOQUES!$AH$7:$AH$123,MATCH("31",CALCULO!$A$7:$A$123,0)) -> ANDINO · Alta
A36: M6B10 | B36: =INDEX(CALCULO!$B$7:$B$123,MATCH("M6B10",CALCULO!$A$7:$A$123,0)) -> T1 | C36: =INDEX(CALCULO!$D$7:$D$123,MATCH("M6B10",CALCULO!$A$7:$A$123,0)) -> 249.89 | D36: =INDEX(CALCULO!$E$7:$E$123,MATCH("M6B10",CALCULO!$A$7:$A$123,0))+INDEX(CALCULO!$F$7:$F$123,MATCH("M6B10",CALCULO!$A$7:$A$123,0)) -> 249.453 | E36: =INDEX(CALCULO!$J$7:$J$123,MATCH("M6B10",CALCULO!$A$7:$A$123,0)) -> 147048.85 | F36: =INDEX(CALCULO!$K$7:$K$123,MATCH("M6B10",CALCULO!$A$7:$A$123,0))+INDEX(CALCULO!$L$7:$L$123,MATCH("M6B10",CALCULO!$A$7:$A$123,0)) -> 741.95766 | G36: =INDEX(CALCULO!$AA$7:$AA$123,MATCH("M6B10",CALCULO!$A$7:$A$123,0)) -> 10217446 | H36: =INDEX(CALCULO!$AB$7:$AB$123,MATCH("M6B10",CALCULO!$A$7:$A$123,0)) -> 40887.775 | I36: =INDEX(BLOQUES!$AB$7:$AB$123,MATCH("M6B10",CALCULO!$A$7:$A$123,0)) -> 1200 | J36: =INDEX(BLOQUES!$AG$7:$AG$123,MATCH("M6B10",CALCULO!$A$7:$A$123,0))&" · "&INDEX(BLOQUES!$AH$7:$AH$123,MATCH("M6B10",CALCULO!$A$7:$A$123,0)) -> BES · Alta
A38: Tipología | B38: Descripción | C38: N° bloques | D38: Área (ha) | E38: Inversión (S/) | F38: S/ por ha
A39: T1 | B39: =INDEX(PAQUETES!$C$7:$C$12,1)&" · "&INDEX(PAQUETES!$D$7:$D$12,1) -> Bosque estacionalmente seco de colina y montaña · Alta | C39: =COUNTIF(B_TIP,"T1") -> 47 | D39: =SUMIFS(B_AREA,B_TIP,"T1") -> 7645.154 | E39: =SUMIFS(CALCULO!$AA$7:$AA$123,CALCULO!$B$7:$B$123,"T1") -> 2.4559308e+08 | F39: =IF(D39=0,0,E39/D39) -> 32124.02
A40: T2 | B40: =INDEX(PAQUETES!$C$7:$C$12,2)&" · "&INDEX(PAQUETES!$D$7:$D$12,2) -> Bosque estacionalmente seco de colina y montaña · Moderada | C40: =COUNTIF(B_TIP,"T2") -> 7 | D40: =SUMIFS(B_AREA,B_TIP,"T2") -> 596.926 | E40: =SUMIFS(CALCULO!$AA$7:$AA$123,CALCULO!$B$7:$B$123,"T2") -> 6054815.5 | F40: =IF(D40=0,0,E40/D40) -> 10143.327
A41: T3 | B41: =INDEX(PAQUETES!$C$7:$C$12,3)&" · "&INDEX(PAQUETES!$D$7:$D$12,3) -> Andino (matorral andino + páramo + relicto montano) · Alta | C41: =COUNTIF(B_TIP,"T3") -> 3 | D41: =SUMIFS(B_AREA,B_TIP,"T3") -> 95.24 | E41: =SUMIFS(CALCULO!$AA$7:$AA$123,CALCULO!$B$7:$B$123,"T3") -> 3188724.4 | F41: =IF(D41=0,0,E41/D41) -> 33480.936
A42: T4 | B42: =INDEX(PAQUETES!$C$7:$C$12,4)&" · "&INDEX(PAQUETES!$D$7:$D$12,4) -> Andino (matorral andino + páramo + relicto montano) · Moderada | C42: =COUNTIF(B_TIP,"T4") -> 20 | D42: =SUMIFS(B_AREA,B_TIP,"T4") -> 1000.648 | E42: =SUMIFS(CALCULO!$AA$7:$AA$123,CALCULO!$B$7:$B$123,"T4") -> 8146657.6 | F42: =IF(D42=0,0,E42/D42) -> 8141.382
A43: T5 | B43: =INDEX(PAQUETES!$C$7:$C$12,5)&" · "&INDEX(PAQUETES!$D$7:$D$12,5) -> Mosaico agroforestal (zona agrícola MINAM) · Alta | C43: =COUNTIF(B_TIP,"T5") -> 3 | D43: =SUMIFS(B_AREA,B_TIP,"T5") -> 106.884 | E43: =SUMIFS(CALCULO!$AA$7:$AA$123,CALCULO!$B$7:$B$123,"T5") -> 8982524.4 | F43: =IF(D43=0,0,E43/D43) -> 84039.934
A44: T6 | B44: =INDEX(PAQUETES!$C$7:$C$12,6)&" · "&INDEX(PAQUETES!$D$7:$D$12,6) -> Mosaico agroforestal (zona agrícola MINAM) · Moderada | C44: =COUNTIF(B_TIP,"T6") -> 37 | D44: =SUMIFS(B_AREA,B_TIP,"T6") -> 2825.383 | E44: =SUMIFS(CALCULO!$AA$7:$AA$123,CALCULO!$B$7:$B$123,"T6") -> 71088861 | F44: =IF(D44=0,0,E44/D44) -> 25160.787
A46: LECTURA RÁPIDA
A47: 1. Calcula los 117 bloques (12 270.235 ha) con los mismos coeficientes; el piloto (21, 66, 73, 31, M6B10) es el que se calibra primero.
A48: 2. Coeficientes críticos por calibrar (hoja PAQUETES): densidades R1/R2 y espaciamiento de zanjas y terrazas. Las fichas ANIN de zanjas (2.78 m) y terrazas (8.33 m) son referenciales.
A49: 3. Cárcavas: ingresar metros lineales por bloque en BLOQUES!AD a partir del inventario por dron o imagen de alta resolución.
A50: 4. O&M: los "años de aplicación" (OYM!G) son un supuesto inicial; las fichas ANIN son anuales para todas las actividades.
A51: 5. Costo-beneficio: completar FLUJO!B38–B43. Mientras estén vacías, el VANS se muestra como "Pendiente de beneficios".
A52: 6. GG (15.08 %) es la referencia ANIN; supervisión y expediente técnico están en 0 % hasta que se definan (PARAMETROS).

Sheet LEEME
A1: AUTORIDAD NACIONAL DE INFRAESTRUCTURA - ANIN
A2: DIRECCIÓN DE INTERVENCIONES MULTISECTORIALES Y DE EMERGENCIA - DIME
A3: SUBDIRECCIÓN DE ESTUDIOS DE INVERSIÓN
A4: PROYECTO IN PIURA – CUI 2669244 · Guía de uso y fuentes
A5: Motor de costos paramétrico para el Estudio de Perfil (Invierte.pe).
A7: PROPÓSITO | B7: Pasar de la tipología de cada bloque a metas físicas, costos de inversión, O&M y flujos a precios privados y sociales con fórmulas vivas y trazables.
A8: CADENA DE CÁLCULO | B8: BLOQUES (SIG) → tipología (grupo × degradación) → PAQUETES (coeficientes) → CALCULO (metas y costos) ← CU_COMP ← PARTIDAS ← APU_BASE (ANIN actualizado) → OYM → FLUJO → RESUMEN.
A9: CONVENCIONES | B9: Texto azul sobre fondo amarillo = supuesto o dato editable. Texto negro = fórmula. Verde = vínculo a otra hoja. "POR DEFINIR / POR DETERMINAR" = dato faltante; no se inventan valores.
A10: TIPOLOGÍAS | B10: Grupo dominante por superficie: BES, ANDINO (matorral andino + páramo + relicto montano) o MOSAICO (zona agrícola MINAM). Degradación ALTA si ≥ 50 % del bloque está bajo el umbral MSAVI 0.4976 (DN 1–3).
A11: MODALIDADES | B11: R1 = plantación plena (MSAVI DN 1–2); R2 = enriquecimiento (DN 3); C = protección (DN 4–5, cerco). Marrón: zanjas (BES/ANDINO) o terrazas (MOSAICO) en celdas R1/R2 con PMM alto o muy alto (DN 4–5).
A12: PRECIOS | B12: Base ANIN (S10, 10/12/2020, Lima). MO: jornal rural S/ 100/día (peón); capataz, operario y oficial mantienen la relación ANIN. Materiales, equipos y servicios: factor IPC Lima dic-2020 → set-2026 (BCRP PN01272PM). Plantón: producción en vivero propio (ficha ANIN algarrobo).
A13: FLETE | B13: Rural: metodología Sierra Azul (40 kg por viaje, 5/8 km/h, 8 min, 95 %) con distancia media de acarreo SIG a vía motorizable (vecinal MTC + trocha carrozable MTC). Terrestre: solo insumos; el transporte de plantones ≤ 20 km está en el APU 04.01.02.
A14: EVALUACIÓN | B14: TSD 8 %, FC MO no calificada Sierra 0.42, MO calificada 0.79, bienes ÷ 1.18, divisa 1.08 y carbono US$ 30/tCO2e (MEF, Anexo 11, act. 27-03-2024). Costo-beneficio: beneficios POR DETERMINAR; mientras tanto se reporta costo-efectividad.
A15: FUENTES SIG | B15: Relación de bloques V6 – versión normalizada (Bloques_V7_Normalizado.xlsx, corte 09/10/2026): 117 bloques (M6B2 en 3 partes), 12 270.235 ha; geometría del KMZ B6 (se excluyen los polígonos 74 y 75, ausentes en la relación normalizada). MSAVI vectorizado V6 (38 988 polígonos). Peligro por movimientos en masa (239 462 polígonos, DN 1–5). Intersección Bloques V6 × ecosistemas MINAM. Red vial vecinal MTC (dic-2018) y trochas MTC (2026).
A16: FUENTES DE COSTOS | B16: ANIN – Fichas de infraestructura natural: reforestación con producción de plantones, zanjas de infiltración, terrazas de formación lenta, control de cárcavas (ANEXOS 05–11). Fondo Sierra Azul – Chacaya (planilla de metrados y flete) y Marachanca (calendario valorizado).
A17: VALIDACIÓN | B17: APU ANIN: Σ parciales = CU en 126 partidas y 19 subpartidas; presupuestos reconstruidos = CD reportado (reforestación 8 254 042.50; zanjas 4 977 678.14; terrazas 14 076 518.93; cárcavas 9 954 031.83). Control en PARTIDAS!G (CU 2020 recalculado).
A18: LIMITACIONES v1 | B18: Coeficientes de densidad, espaciamiento de zanjas/terrazas, cerco y años de O&M son supuestos referenciales a calibrar con el piloto. La distancia de acarreo es en línea recta (factor de sinuosidad 1.0). No incluye viveros permanentes/temporales como infraestructura separada (el costo del plantón ya amortiza el vivero ANIN), gobernanza ni gestión del proyecto.

Sheet PARAMETROS
A1: AUTORIDAD NACIONAL DE INFRAESTRUCTURA - ANIN
A2: DIRECCIÓN DE INTERVENCIONES MULTISECTORIALES Y DE EMERGENCIA - DIME
A3: SUBDIRECCIÓN DE ESTUDIOS DE INVERSIÓN
A4: PROYECTO IN PIURA – CUI 2669244 · Parámetros globales del motor
A5: Celdas en azul con fondo amarillo = supuestos editables. Fuente indicada en cada fila. Precios base ANIN: 10/12/2020 (Lima).
A6: Nombre | B6: Parámetro | C6: Valor | D6: Unidad | E6: Fuente / nota | G6: Categoría MO | H6: hh ANIN 2020 (S/) | I6: Ratio vs peón | J6: hh actualizado (S/)
A7: MANO DE OBRA Y PRECIOS | G7: CAPATAZ | H7: 25.81 | I7: =H7/$H$10 -> 1.5381406 | J7: =P_HH_PEON*I7 -> 19.226758
A8: P_JORNAL | B8: Jornal diario de mano de obra rural – peón (Administración Directa) | C8: 100 | D8: S/ / día | E8: Fijado por el Ing. H. S. Cahuas Miller (18-oct-2026): S/ 100 por jornal rural (reemplaza S/ 120). | G8: OPERARIO | H8: 23.46 | I8: =H8/$H$10 -> 1.398093 | J8: =P_HH_PEON*I8 -> 17.476162
A9: P_HORAS | B9: Horas efectivas por jornada | C9: 8 | D9: h / día | E9: Jornada estándar de 8 h (supuesto de cálculo de hh). | G9: OFICIAL | H9: 18.56 | I9: =H9/$H$10 -> 1.1060787 | J9: =P_HH_PEON*I9 -> 13.825983
A10: P_HH_PEON | B10: Costo hora-hombre peón | C10: =P_JORNAL/P_HORAS -> 12.5 | D10: S/ / hh | E10: Cálculo. | G10: PEON | H10: 16.78 | I10: =H10/$H$10 -> 1 | J10: =P_HH_PEON*I10 -> 12.5
A11: P_FACT_IPC | B11: Factor de actualización dic-2020 → set-2026 (materiales, equipos, servicios) | C11: =PRODUCT(PARAMETROS!$I$15:$I$20) -> 1.2862958 | D11: factor | E11: IPC Lima Metropolitana, var. % acumulada anual (BCRP, serie PN01272PM). Tabla en G13:I20. | G11: Supuesto: se mantiene la estructura salarial relativa de ANIN 2020; el peón se fija en S/ 100/día (jornal rural).
A12: P_TC | B12: Tipo de cambio referencial | C12: 3.4 | D12: S/ / US$ | E12: Estándar del proyecto IN Piura.
A13: P_IGV | B13: IGV | C13: 0.18 | D13: % | E13: Tasa vigente.
A14: PLANTACIÓN Y MANEJO (EJECUCIÓN) | G14: Año | H14: IPC Lima – var. % acumulada a diciembre | I14: Factor
A15: P_RECALCE | B15: Recalce (reposición por mortalidad) en ejecución | C15: 0.1 | D15: % de plantas | E15: ANIN reforestación: 65 000 recalces / 650 000 plantas. | G15: 2021 | H15: 6.4303872 | I15: =1+H15/100 -> 1.0643039
A16: P_RIEGOS | B16: Riegos manuales de establecimiento por planta | C16: 3 | D16: riegos | E16: ANIN reforestación: 1 950 000 riegos / 650 000 plantas. | G16: 2022 | H16: 8.459162 | I16: =1+H16/100 -> 1.0845916
A17: P_DESHIERBES | B17: Deshierbes manuales por ha en ejecución | C17: 4 | D17: veces | E17: ANIN reforestación: 4 000 ha-deshierbe / 1 000 ha. | G17: 2023 | H17: 3.2373826 | I17: =1+H17/100 -> 1.0323738
A18: P_PESO_PLANTON | B18: Peso de plantón en bolsa | C18: 1.5 | D18: kg / und | E18: Sierra Azul – Flete Chacaya (reforestación). | G18: 2024 | H18: 1.9663027 | I18: =1+H18/100 -> 1.019663
A19: P_PESO_INS | B19: Insumos de plantación por planta (humus, guano, fosfato, hidrogel) | C19: 0.17 | D19: kg / planta | E19: APU ANIN 04.01.04: 0.10 + 0.03 + 0.02 + 0.02 kg. | G19: 2025 | H19: 1.5087997 | I19: =1+H19/100 -> 1.015088
A20: FLETE (metodología Sierra Azul) | G20: 2026 (ene–set) | H20: 4.2825468 | I20: =1+H20/100 -> 1.0428255
A21: P_CARGA | B21: Carga por viaje en flete rural (a pie / acémila) | C21: 40 | D21: kg / viaje | E21: Sierra Azul – Flete Chacaya. | G21: Fuente: BCRPData, serie PN01272PM (consulta 18-oct-2026).
A22: P_VIDA | B22: Velocidad de ida cargado | C22: 5 | D22: km / h | E22: Sierra Azul – Flete Chacaya.
A23: P_VVUELTA | B23: Velocidad de vuelta | C23: 8 | D23: km / h | E23: Sierra Azul – Flete Chacaya.
A24: P_TCD | B24: Tiempo de carguío + descarga | C24: 8 | D24: min / viaje | E24: Sierra Azul – Flete Chacaya (4 + 4 min).
A25: P_EFIC | B25: Eficiencia de la jornada | C25: 0.95 | D25: % | E25: Sierra Azul – Flete Chacaya.
A26: P_SINUOS | B26: Factor de sinuosidad del acarreo (distancia SIG en línea recta) | C26: 1 | D26: factor | E26: SUPUESTO: 1.0 = sin ajuste. Calibrar con tracks GPS de campo.
A27: P_FT_VIAJE | B27: Flete terrestre por viaje de volquete | C27: 2500 | D27: S/ / viaje | E27: Sierra Azul – Flete Chacaya (referencia; ruta corta). Plantones: transporte incluido en APU 04.01.02 (≤ 20 km).
A28: P_FT_CAP | B28: Capacidad efectiva del volquete | C28: 15000 | D28: kg / viaje | E28: Sierra Azul – Flete Chacaya.
A29: P_FT_KG | B29: Flete terrestre por kg de insumo | C29: =P_FT_VIAJE/P_FT_CAP*P_FACT_IPC -> 0.21438264 | D29: S/ / kg | E29: Cálculo (actualizado con IPC).
A30: COSTOS INDIRECTOS (sobre costo directo)
A31: P_GG | B31: Gastos generales y obras provisionales | C31: =PARAMETROS!$C$70/PARAMETROS!$C$69 -> 0.15077351 | D31: % del CD | E31: Referencia ANIN reforestación: GG 1 244 490.96 / CD 8 254 042.50. DEFINIR para Administración Directa.
A32: P_SUP | B32: Supervisión de la ejecución | C32: 0 | D32: % del CD | E32: POR DEFINIR (0 % mientras no se fije).
A33: P_ET | B33: Expediente técnico / estudios definitivos | C33: 0 | D33: % del CD | E33: POR DEFINIR (0 % mientras no se fije).
A34: TIPOLOGÍAS
A35: P_UMBRAL | B35: Umbral MSAVI de degradación (referencial) | C35: 0.4976 | D35: MSAVI | E35: Estándar del proyecto (20-sep-2026). DN 1–3 < 0.4976 ≤ DN 4–5.
A36: P_CORTE | B36: Corte de degradación ALTA (% del bloque bajo el umbral) | C36: 0.5 | D36: % | E36: Propuesto y aceptado en sesión (18-oct-2026); calibrable.
A37: P_PMM_MARRON | B37: Clase PMM mínima que activa el paquete marrón | C37: 4 | D37: DN | E37: Decisión de sesión: PMM alto o muy alto (DN 4–5) sobre MSAVI DN 1–3.
A38: EVALUACIÓN SOCIAL (Anexo 11 Invierte.pe, act. 27-03-2024)
A39: P_TSD | B39: Tasa social de descuento (años 1–20) | C39: 0.08 | D39: % | E39: MEF, Anexo 11 – Parámetros de evaluación social. TSD-LP (5.5 %) solo desde el año 21.
A40: P_FC_MONC | B40: Factor de corrección MO no calificada – Sierra | C40: 0.42 | D40: factor | E40: MEF, Anexo 11, Tabla 03.
A41: P_FC_MOC | B41: Factor de corrección MO calificada – Sierra | C41: 0.79 | D41: factor | E41: MEF, Anexo 11, Tabla 03.
A42: P_FC_BIEN | B42: Factor de corrección bienes y servicios nacionales | C42: =1/(1+P_IGV) -> 0.84745763 | D42: factor | E42: Precio social = precio de mercado sin IGV.
A43: P_FCD | B43: Factor de corrección de la divisa | C43: 1.08 | D43: factor | E43: MEF, Anexo 11, Tabla 04.
A44: P_PSC | B44: Precio social del carbono | C44: 30 | D44: US$ / tCO2e | E44: MEF, Anexo 11, Tabla 07.
A45: HORIZONTE Y CRONOGRAMA
A46: P_ANIOS_EJ | B46: Años de ejecución | C46: 5 | D46: años | E46: Estructura del proyecto IN Piura.
A47: P_ANIOS_OM | B47: Años de operación y mantenimiento | C47: 15 | D47: años | E47: Estructura del proyecto IN Piura.
A48: P_TECHO | B48: Presupuesto total de la inversión (techo de referencia) | C48: 372442809 | D48: S/ | E48: Incluye preinversión, ET, ejecución (5 años) y O&M (15 años).
A68: REFERENCIAS ANIN PARA GG (no editar)
B69: ANIN reforestación – Costo directo | C69: 8254042.5 | E69: ANEXO 06 REFORESTACIÓN – presupuesto cliente (ANIN, 10/12/2020).
B70: ANIN reforestación – Gastos generales | C70: 1244491 | E70: ANEXO 06 REFORESTACIÓN – presupuesto cliente (ANIN, 10/12/2020).

Sheet APU_BASE
A1: AUTORIDAD NACIONAL DE INFRAESTRUCTURA - ANIN
A2: DIRECCIÓN DE INTERVENCIONES MULTISECTORIALES Y DE EMERGENCIA - DIME
A3: SUBDIRECCIÓN DE ESTUDIOS DE INVERSIÓN
A4: PROYECTO IN PIURA – CUI 2669244 · Análisis de precios unitarios – base ANIN y actualización
A5: Fuente: ANIN, Fichas de proyectos de infraestructura natural (S10, presupuesto 10/12/2020, Lima). Columnas P–R recalculan con PARAMETROS (jornal rural S/ 100 y factor IPC).
A6: Clave | B6: Tipo | C6: Item | D6: Partida | E6: Und partida | F6: CU 2020 ANIN | G6: Sección | H6: Código | I6: Recurso | J6: Und | K6: Cuadrilla | L6: Cantidad | M6: Precio 2020 | N6: Parcial 2020 | O6: Cat. MO | P6: Precio actualizado | Q6: Parcial actualizado | R6: Base MO (para %mo)
A7: CARCAVAS|01.01 | B7: CARCAVAS | C7: 01.01 | D7: MOVILIZACION Y DESMOVILIZACION PARA CARCAVAS | E7: m3 | F7: 60135.17 | G7: SC | H7: 0402010005 | I7: SC MOVILIZACION Y DESMOVILIZACION PARA CARCAVAS | J7: glb | L7: 1 | M7: 60135.17 | N7: 60135.17 | P7: =IF(J7="%mo","",IF(G7="MO",IF(J7="hh",INDEX(MO_HH,MATCH(I7,MO_CAT,0)),M7*P_FACT_IPC),IF(G7="SUBPART",IFERROR(INDEX(APU_SUBP!$C$7:$C$40,MATCH(H7,APU_SUBP!$A$7:$A$40,0)),M7*P_FACT_IPC),M7*P_FACT_IPC))) -> 77351.619 | Q7: =IF(J7="%mo",L7/100*SUMIFS($R$7:$R$782,$A$7:$A$782,A7),L7*P7) -> 77351.619 | R7: =IF(G7="MO",L7*P7,0) -> 0
A8: CARCAVAS|01.02 | B8: CARCAVAS | C8: 01.02 | D8: CONSTRUCCION DE TROCHA CARROZABLE DE ACCESO | E8: km | F8: 27992.8 | G8: MO | H8: 0101010002 | I8: CAPATAZ | J8: hh | K8: 0.5 | L8: 16 | M8: 25.81 | N8: 412.96 | O8: C | P8: =IF(J8="%mo","",IF(G8="MO",IF(J8="hh",INDEX(MO_HH,MATCH(I8,MO_CAT,0)),M8*P_FACT_IPC),IF(G8="SUBPART",IFERROR(INDEX(APU_SUBP!$C$7:$C$40,MATCH(H8,APU_SUBP!$A$7:$A$40,0)),M8*P_FACT_IPC),M8*P_FACT_IPC))) -> 19.226758 | Q8: =IF(J8="%mo",L8/100*SUMIFS($R$7:$R$782,$A$7:$A$782,A8),L8*P8) -> 307.62813 | R8: =IF(G8="MO",L8*P8,0) -> 307.62813
A9: CARCAVAS|01.02 | B9: CARCAVAS | C9: 01.02 | D9: CONSTRUCCION DE TROCHA CARROZABLE DE ACCESO | E9: km | F9: 27992.8 | G9: MO | H9: 0101010004 | I9: OFICIAL | J9: hh | K9: 2 | L9: 64 | M9: 18.56 | N9: 1187.84 | O9: C | P9: =IF(J9="%mo","",IF(G9="MO",IF(J9="hh",INDEX(MO_HH,MATCH(I9,MO_CAT,0)),M9*P_FACT_IPC),IF(G9="SUBPART",IFERROR(INDEX(APU_SUBP!$C$7:$C$40,MATCH(H9,APU_SUBP!$A$7:$A$40,0)),M9*P_FACT_IPC),M9*P_FACT_IPC))) -> 13.825983 | Q9: =IF(J9="%mo",L9/100*SUMIFS($R$7:$R$782,$A$7:$A$782,A9),L9*P9) -> 884.86293 | R9: =IF(G9="MO",L9*P9,0) -> 884.86293
A10: CARCAVAS|01.02 | B10: CARCAVAS | C10: 01.02 | D10: CONSTRUCCION DE TROCHA CARROZABLE DE ACCESO | E10: km | F10: 27992.8 | G10: MO | H10: 0101010005 | I10: PEON | J10: hh | K10: 4 | L10: 128 | M10: 16.78 | N10: 2147.84 | O10: NC | P10: =IF(J10="%mo","",IF(G10="MO",IF(J10="hh",INDEX(MO_HH,MATCH(I10,MO_CAT,0)),M10*P_FACT_IPC),IF(G10="SUBPART",IFERROR(INDEX(APU_SUBP!$C$7:$C$40,MATCH(H10,APU_SUBP!$A$7:$A$40,0)),M10*P_FACT_IPC),M10*P_FACT_IPC))) -> 12.5 | Q10: =IF(J10="%mo",L10/100*SUMIFS($R$7:$R$782,$A$7:$A$782,A10),L10*P10) -> 1600 | R10: =IF(G10="MO",L10*P10,0) -> 1600
A11: CARCAVAS|01.02 | B11: CARCAVAS | C11: 01.02 | D11: CONSTRUCCION DE TROCHA CARROZABLE DE ACCESO | E11: km | F11: 27992.8 | G11: EQ | H11: 03011600010003 | I11: CARGADOR SOBRE LLANTAS DE 125-135 HP 3 yd3 | J11: hm | K11: 0.5 | L11: 16 | M11: 170.08 | N11: 2721.28 | P11: =IF(J11="%mo","",IF(G11="MO",IF(J11="hh",INDEX(MO_HH,MATCH(I11,MO_CAT,0)),M11*P_FACT_IPC),IF(G11="SUBPART",IFERROR(INDEX(APU_SUBP!$C$7:$C$40,MATCH(H11,APU_SUBP!$A$7:$A$40,0)),M11*P_FACT_IPC),M11*P_FACT_IPC))) -> 218.7732 | Q11: =IF(J11="%mo",L11/100*SUMIFS($R$7:$R$782,$A$7:$A$782,A11),L11*P11) -> 3500.3711 | R11: =IF(G11="MO",L11*P11,0) -> 0
A12: CARCAVAS|01.02 | B12: CARCAVAS | C12: 01.02 | D12: CONSTRUCCION DE TROCHA CARROZABLE DE ACCESO | E12: km | F12: 27992.8 | G12: EQ | H12: 0301190003 | I12: RODILLO VIBRATORIO LISO AUTOPROPULSADO 101-135 HP, 10-12 TN | J12: hm | K12: 1 | L12: 32 | M12: 159.96 | N12: 5118.72 | P12: =IF(J12="%mo","",IF(G12="MO",IF(J12="hh",INDEX(MO_HH,MATCH(I12,MO_CAT,0)),M12*P_FACT_IPC),IF(G12="SUBPART",IFERROR(INDEX(APU_SUBP!$C$7:$C$40,MATCH(H12,APU_SUBP!$A$7:$A$40,0)),M12*P_FACT_IPC),M12*P_FACT_IPC))) -> 205.75588 | Q12: =IF(J12="%mo",L12/100*SUMIFS($R$7:$R$782,$A$7:$A$782,A12),L12*P12) -> 6584.1882 | R12: =IF(G12="MO",L12*P12,0) -> 0
A13: CARCAVAS|01.02 | B13: CARCAVAS | C13: 01.02 | D13: CONSTRUCCION DE TROCHA CARROZABLE DE ACCESO | E13: km | F13: 27992.8 | G13: EQ | H13: 03012000010001 | I13: MOTONIVELADORA 130 - 135 HP | J13: hm | K13: 1 | L13: 32 | M13: 182.88 | N13: 5852.16 | P13: =IF(J13="%mo","",IF(G13="MO",IF(J13="hh",INDEX(MO_HH,MATCH(I13,MO_CAT,0)),M13*P_FACT_IPC),IF(G13="SUBPART",IFERROR(INDEX(APU_SUBP!$C$7:$C$40,MATCH(H13,APU_SUBP!$A$7:$A$40,0)),M13*P_FACT_IPC),M13*P_FACT_IPC))) -> 235.23778 | Q13: =IF(J13="%mo",L13/100*SUMIFS($R$7:$R$782,$A$7:$A$782,A13),L13*P13) -> 7527.6091 | R13: =IF(G13="MO",L13*P13,0) -> 0
A14: CARCAVAS|01.02 | B14: CARCAVAS | C14: 01.02 | D14: CONSTRUCCION DE TROCHA CARROZABLE DE ACCESO | E14: km | F14: 27992.8 | G14: EQ | H14: 03012200040006 | I14: CAMION VOLQUETE 6X4, 330 HP DE 10 m3 | J14: hm | K14: 1 | L14: 32 | M14: 188.87 | N14: 6043.84 | P14: =IF(J14="%mo","",IF(G14="MO",IF(J14="hh",INDEX(MO_HH,MATCH(I14,MO_CAT,0)),M14*P_FACT_IPC),IF(G14="SUBPART",IFERROR(INDEX(APU_SUBP!$C$7:$C$40,MATCH(H14,APU_SUBP!$A$7:$A$40,0)),M14*P_FACT_IPC),M14*P_FACT_IPC))) -> 242.9427 | Q14: =IF(J14="%mo",L14/100*SUMIFS($R$7:$R$782,$A$7:$A$782,A14),L14*P14) -> 7774.1663 | R14: =IF(G14="MO",L14*P14,0) -> 0
A15: CARCAVAS|01.02 | B15: CARCAVAS | C15: 01.02 | D15: CONSTRUCCION DE TROCHA CARROZABLE DE ACCESO | E15: km | F15: 27992.8 | G15: EQ | H15: 03012200050001 | I15: CAMION CISTERNA (2,500 GLNS.) | J15: hm | K15: 1 | L15: 32 | M15: 140.88 | N15: 4508.16 | P15: =IF(J15="%mo","",IF(G15="MO",IF(J15="hh",INDEX(MO_HH,MATCH(I15,MO_CAT,0)),M15*P_FACT_IPC),IF(G15="SUBPART",IFERROR(INDEX(APU_SUBP!$C$7:$C$40,MATCH(H15,APU_SUBP!$A$7:$A$40,0)),M15*P_FACT_IPC),M15*P_FACT_IPC))) -> 181.21336 | Q15: =IF(J15="%mo",L15/100*SUMIFS($R$7:$R$782,$A$7:$A$782,A15),L15*P15) -> 5798.8275 | R15: =IF(G15="MO",L15*P15,0) -> 0
A16: CARCAVAS|01.03 | B16: CARCAVAS | C16: 01.03 | D16: MEJORAMIENTO DE TROCHA CARROZABLE DE ACCESO | E16: km | F16: 4665.44 | G16: MO | H16: 0101010002 | I16: CAPATAZ | J16: hh | K16: 0.5 | L16: 2.6667 | M16: 25.81 | N16: 68.83 | O16: C | P16: =IF(J16="%mo","",IF(G16="MO",IF(J16="hh",INDEX(MO_HH,MATCH(I16,MO_CAT,0)),M16*P_FACT_IPC),IF(G16="SUBPART",IFERROR(INDEX(APU_SUBP!$C$7:$C$40,MATCH(H16,APU_SUBP!$A$7:$A$40,0)),M16*P_FACT_IPC),M16*P_FACT_IPC))) -> 19.226758 | Q16: =IF(J16="%mo",L16/100*SUMIFS($R$7:$R$782,$A$7:$A$782,A16),L16*P16) -> 51.271996 | R16: =IF(G16="MO",L16*P16,0) -> 51.271996
A17: CARCAVAS|01.03 | B17: CARCAVAS | C17: 01.03 | D17: MEJORAMIENTO DE TROCHA CARROZABLE DE ACCESO | E17: km | F17: 4665.44 | G17: MO | H17: 0101010004 | I17: OFICIAL | J17: hh | K17: 2 | L17: 10.6667 | M17: 18.56 | N17: 197.97 | O17: C | P17: =IF(J17="%mo","",IF(G17="MO",IF(J17="hh",INDEX(MO_HH,MATCH(I17,MO_CAT,0)),M17*P_FACT_IPC),IF(G17="SUBPART",IFERROR(INDEX(APU_SUBP!$C$7:$C$40,MATCH(H17,APU_SUBP!$A$7:$A$40,0)),M17*P_FACT_IPC),M17*P_FACT_IPC))) -> 13.825983 | Q17: =IF(J17="%mo",L17/100*SUMIFS($R$7:$R$782,$A$7:$A$782,A17),L17*P17) -> 147.47762 | R17: =IF(G17="MO",L17*P17,0) -> 147.47762
A18: CARCAVAS|01.03 | B18: CARCAVAS | C18: 01.03 | D18: MEJORAMIENTO DE TROCHA CARROZABLE DE ACCESO | E18: km | F18: 4665.44 | G18: MO | H18: 0101010005 | I18: PEON | J18: hh | K18: 4 | L18: 21.3333 | M18: 16.78 | N18: 357.97 | O18: NC | P18: =IF(J18="%mo","",IF(G18="MO",IF(J18="hh",INDEX(MO_HH,MATCH(I18,MO_CAT,0)),M18*P_FACT_IPC),IF(G18="SUBPART",IFERROR(INDEX(APU_SUBP!$C$7:$C$40,MATCH(H18,APU_SUBP!$A$7:$A$40,0)),M18*P_FACT_IPC),M18*P_FACT_IPC))) -> 12.5 | Q18: =IF(J18="%mo",L18/100*SUMIFS($R$7:$R$782,$A$7:$A$782,A18),L18*P18) -> 266.66625 | R18: =IF(G18="MO",L18*P18,0) -> 266.66625
A19: CARCAVAS|01.03 | B19: CARCAVAS | C19: 01.03 | D19: MEJORAMIENTO DE TROCHA CARROZABLE DE ACCESO | E19: km | F19: 4665.44 | G19: EQ | H19: 03011600010003 | I19: CARGADOR SOBRE LLANTAS DE 125-135 HP 3 yd3 | J19: hm | K19: 0.5 | L19: 2.6667 | M19: 170.08 | N19: 453.55 | P19: =IF(J19="%mo","",IF(G19="MO",IF(J19="hh",INDEX(MO_HH,MATCH(I19,MO_CAT,0)),M19*P_FACT_IPC),IF(G19="SUBPART",IFERROR(INDEX(APU_SUBP!$C$7:$C$40,MATCH(H19,APU_SUBP!$A$7:$A$40,0)),M19*P_FACT_IPC),M19*P_FACT_IPC))) -> 218.7732 | Q19: =IF(J19="%mo",L19/100*SUMIFS($R$7:$R$782,$A$7:$A$782,A19),L19*P19) -> 583.40248 | R19: =IF(G19="MO",L19*P19,0) -> 0
A20: CARCAVAS|01.03 | B20: CARCAVAS | C20: 01.03 | D20: MEJORAMIENTO DE TROCHA CARROZABLE DE ACCESO | E20: km | F20: 4665.44 | G20: EQ | H20: 0301190003 | I20: RODILLO VIBRATORIO LISO AUTOPROPULSADO 101-135 HP, 10-12 TN | J20: hm | K20: 1 | L20: 5.3333 | M20: 159.96 | N20: 853.11 | P20: =IF(J20="%mo","",IF(G20="MO",IF(J20="hh",INDEX(MO_HH,MATCH(I20,MO_CAT,0)),M20*P_FACT_IPC),IF(G20="SUBPART",IFERROR(INDEX(APU_SUBP!$C$7:$C$40,MATCH(H20,APU_SUBP!$A$7:$A$40,0)),M20*P_FACT_IPC),M20*P_FACT_IPC))) -> 205.75588 | Q20: =IF(J20="%mo",L20/100*SUMIFS($R$7:$R$782,$A$7:$A$782,A20),L20*P20) -> 1097.3578 | R20: =IF(G20="MO",L20*P20,0) -> 0
A21: CARCAVAS|01.03 | B21: CARCAVAS | C21: 01.03 | D21: MEJORAMIENTO DE TROCHA CARROZABLE DE ACCESO | E21: km | F21: 4665.44 | G21: EQ | H21: 03012000010001 | I21: MOTONIVELADORA 130 - 135 HP | J21: hm | K21: 1 | L21: 5.3333 | M21: 182.88 | N21: 975.35 | P21: =IF(J21="%mo","",IF(G21="MO",IF(J21="hh",INDEX(MO_HH,MATCH(I21,MO_CAT,0)),M21*P_FACT_IPC),IF(G21="SUBPART",IFERROR(INDEX(APU_SUBP!$C$7:$C$40,MATCH(H21,APU_SUBP!$A$7:$A$40,0)),M21*P_FACT_IPC),M21*P_FACT_IPC))) -> 235.23778 | Q21: =IF(J21="%mo",L21/100*SUMIFS($R$7:$R$782,$A$7:$A$782,A21),L21*P21) -> 1254.5937 | R21: =IF(G21="MO",L21*P21,0) -> 0
A22: CARCAVAS|01.03 | B22: CARCAVAS | C22: 01.03 | D22: MEJORAMIENTO DE TROCHA CARROZABLE DE ACCESO | E22: km | F22: 4665.44 | G22: EQ | H22: 03012200040006 | I22: CAMION VOLQUETE 6X4, 330 HP DE 10 m3 | J22: hm | K22: 1 | L22: 5.3333 | M22: 188.87 | N22: 1007.3 | P22: =IF(J22="%mo","",IF(G22="MO",IF(J22="hh",INDEX(MO_HH,MATCH(I22,MO_CAT,0)),M22*P_FACT_IPC),IF(G22="SUBPART",IFERROR(INDEX(APU_SUBP!$C$7:$C$40,MATCH(H22,APU_SUBP!$A$7:$A$40,0)),M22*P_FACT_IPC),M22*P_FACT_IPC))) -> 242.9427 | Q22: =IF(J22="%mo",L22/100*SUMIFS($R$7:$R$782,$A$7:$A$782,A22),L22*P22) -> 1295.6863 | R22: =IF(G22="MO",L22*P22,0) -> 0
A23: CARCAVAS|01.03 | B23: CARCAVAS | C23: 01.03 | D23: MEJORAMIENTO DE TROCHA CARROZABLE DE ACCESO | E23: km | F23: 4665.44 | G23: EQ | H23: 03012200050001 | I23: CAMION CISTERNA (2,500 GLNS.) | J23: hm | K23: 1 | L23: 5.3333 | M23: 140.88 | N23: 751.36 | P23: =IF(J23="%mo","",IF(G23="MO",IF(J23="hh",INDEX(MO_HH,MATCH(I23,MO_CAT,0)),M23*P_FACT_IPC),IF(G23="SUBPART",IFERROR(INDEX(APU_SUBP!$C$7:$C$40,MATCH(H23,APU_SUBP!$A$7:$A$40,0)),M23*P_FACT_IPC),M23*P_FACT_IPC))) -> 181.21336 | Q23: =IF(J23="%mo",L23/100*SUMIFS($R$7:$R$782,$A$7:$A$782,A23),L23*P23) -> 966.4652 | R23: =IF(G23="MO",L23*P23,0) -> 0
A24: CARCAVAS|01.04 | B24: CARCAVAS | C24: 01.04 | D24: TRAZO, NIVELACION Y REPLANTEO POR KILOMETRO | E24: km | F24: 583.87 | G24: MO | H24: 0101010003 | I24: OPERARIO | J24: hh | K24: 1 | L24: 5 | M24: 23.46 | N24: 117.3 | O24: C | P24: =IF(J24="%mo","",IF(G24="MO",IF(J24="hh",INDEX(MO_HH,MATCH(I24,MO_CAT,0)),M24*P_FACT_IPC),IF(G24="SUBPART",IFERROR(INDEX(APU_SUBP!$C$7:$C$40,MATCH(H24,APU_SUBP!$A$7:$A$40,0)),M24*P_FACT_IPC),M24*P_FACT_IPC))) -> 17.476162 | Q24: =IF(J24="%mo",L24/100*SUMIFS($R$7:$R$782,$A$7:$A$782,A24),L24*P24) -> 87.38081 | R24: =IF(G24="MO",L24*P24,0) -> 87.38081
A25: CARCAVAS|01.04 | B25: CARCAVAS | C25: 01.04 | D25: TRAZO, NIVELACION Y REPLANTEO POR KILOMETRO | E25: km | F25: 583.87 | G25: MO | H25: 0101010004 | I25: OFICIAL | J25: hh | K25: 1 | L25: 5 | M25: 18.56 | N25: 92.8 | O25: C | P25: =IF(J25="%mo","",IF(G25="MO",IF(J25="hh",INDEX(MO_HH,MATCH(I25,MO_CAT,0)),M25*P_FACT_IPC),IF(G25="SUBPART",IFERROR(INDEX(APU_SUBP!$C$7:$C$40,MATCH(H25,APU_SUBP!$A$7:$A$40,0)),M25*P_FACT_IPC),M25*P_FACT_IPC))) -> 13.825983 | Q25: =IF(J25="%mo",L25/100*SUMIFS($R$7:$R$782,$A$7:$A$782,A25),L25*P25) -> 69.129917 | R25: =IF(G25="MO",L25*P25,0) -> 69.129917
A26: CARCAVAS|01.04 | B26: CARCAVAS | C26: 01.04 | D26: TRAZO, NIVELACION Y REPLANTEO POR KILOMETRO | E26: km | F26: 583.87 | G26: MO | H26: 0101010005 | I26: PEON | J26: hh | K26: 3 | L26: 15 | M26: 16.78 | N26: 251.7 | O26: NC | P26: =IF(J26="%mo","",IF(G26="MO",IF(J26="hh",INDEX(MO_HH,MATCH(I26,MO_CAT,0)),M26*P_FACT_IPC),IF(G26="SUBPART",IFERROR(INDEX(APU_SUBP!$C$7:$C$40,MATCH(H26,APU_SUBP!$A$7:$A$40,0)),M26*P_FACT_IPC),M26*P_FACT_IPC))) -> 12.5 | Q26: =IF(J26="%mo",L26/100*SUMIFS($R$7:$R$782,$A$7:$A$782,A26),L26*P26) -> 187.5 | R26: =IF(G26="MO",L26*P26,0) -> 187.5
A27: CARCAVAS|01.04 | B27: CARCAVAS | C27: 01.04 | D27: TRAZO, NIVELACION Y REPLANTEO POR KILOMETRO | E27: km | F27: 583.87 | G27: MAT | H27: 02130300010001 | I27: YESO BOLSA 28 kg | J27: bol | L27: 0.003 | M27: 14.7 | N27: 0.04 | P27: =IF(J27="%mo","",IF(G27="MO",IF(J27="hh",INDEX(MO_HH,MATCH(I27,MO_CAT,0)),M27*P_FACT_IPC),IF(G27="SUBPART",IFERROR(INDEX(APU_SUBP!$C$7:$C$40,MATCH(H27,APU_SUBP!$A$7:$A$40,0)),M27*P_FACT_IPC),M27*P_FACT_IPC))) -> 18.908549 | Q27: =IF(J27="%mo",L27/100*SUMIFS($R$7:$R$782,$A$7:$A$782,A27),L27*P27) -> 0.056725647 | R27: =IF(G27="MO",L27*P27,0) -> 0
A28: CARCAVAS|01.04 | B28: CARCAVAS | C28: 01.04 | D28: TRAZO, NIVELACION Y REPLANTEO POR KILOMETRO | E28: km | F28: 583.87 | G28: MAT | H28: 0213030003 | I28: CORDEL | J28: rll | L28: 0.01 | M28: 1.63 | N28: 0.02 | P28: =IF(J28="%mo","",IF(G28="MO",IF(J28="hh",INDEX(MO_HH,MATCH(I28,MO_CAT,0)),M28*P_FACT_IPC),IF(G28="SUBPART",IFERROR(INDEX(APU_SUBP!$C$7:$C$40,MATCH(H28,APU_SUBP!$A$7:$A$40,0)),M28*P_FACT_IPC),M28*P_FACT_IPC))) -> 2.0966622 | Q28: =IF(J28="%mo",L28/100*SUMIFS($R$7:$R$782,$A$7:$A$782,A28),L28*P28) -> 0.020966622 | R28: =IF(G28="MO",L28*P28,0) -> 0
A29: CARCAVAS|01.04 | B29: CARCAVAS | C29: 01.04 | D29: TRAZO, NIVELACION Y REPLANTEO POR KILOMETRO | E29: km | F29: 583.87 | G29: MAT | H29: 0231040002 | I29: ESTACAS DE MADERA | J29: p2 | L29: 0.007 | M29: 1.63 | N29: 0.01 | P29: =IF(J29="%mo","",IF(G29="MO",IF(J29="hh",INDEX(MO_HH,MATCH(I29,MO_CAT,0)),M29*P_FACT_IPC),IF(G29="SUBPART",IFERROR(INDEX(APU_SUBP!$C$7:$C$40,MATCH(H29,APU_SUBP!$A$7:$A$40,0)),M29*P_FACT_IPC),M29*P_FACT_IPC))) -> 2.0966622 | Q29: =IF(J29="%mo",L29/100*SUMIFS($R$7:$R$782,$A$7:$A$782,A29),L29*P29) -> 0.014676636 | R29: =IF(G29="MO",L29*P29,0) -> 0
A30: CARCAVAS|01.04 | B30: CARCAVAS | C30: 01.04 | D30: TRAZO, NIVELACION Y REPLANTEO POR KILOMETRO | E30: km | F30: 583.87 | G30: MAT | H30: 0240020001 | I30: PINTURA ESMALTE | J30: gal | L30: 0.002 | M30: 34.07 | N30: 0.07 | P30: =IF(J30="%mo","",IF(G30="MO",IF(J30="hh",INDEX(MO_HH,MATCH(I30,MO_CAT,0)),M30*P_FACT_IPC),IF(G30="SUBPART",IFERROR(INDEX(APU_SUBP!$C$7:$C$40,MATCH(H30,APU_SUBP!$A$7:$A$40,0)),M30*P_FACT_IPC),M30*P_FACT_IPC))) -> 43.824099 | Q30: =IF(J30="%mo",L30/100*SUMIFS($R$7:$R$782,$A$7:$A$782,A30),L30*P30) -> 0.087648199 | R30: =IF(G30="MO",L30*P30,0) -> 0
A31: CARCAVAS|01.04 | B31: CARCAVAS | C31: 01.04 | D31: TRAZO, NIVELACION Y REPLANTEO POR KILOMETRO | E31: km | F31: 583.87 | G31: EQ | H31: 03010000020002 | I31: NIVEL TOPOGRAFICO | J31: he | K31: 0.5 | L31: 2.5 | M31: 9.71 | N31: 24.28 | P31: =IF(J31="%mo","",IF(G31="MO",IF(J31="hh",INDEX(MO_HH,MATCH(I31,MO_CAT,0)),M31*P_FACT_IPC),IF(G31="SUBPART",IFERROR(INDEX(APU_SUBP!$C$7:$C$40,MATCH(H31,APU_SUBP!$A$7:$A$40,0)),M31*P_FACT_IPC),M31*P_FACT_IPC))) -> 12.489933 | Q31: =IF(J31="%mo",L31/100*SUMIFS($R$7:$R$782,$A$7:$A$782,A31),L31*P31) -> 31.224832 | R31: =IF(G31="MO",L31*P31,0) -> 0
A32: CARCAVAS|01.04 | B32: CARCAVAS | C32: 01.04 | D32: TRAZO, NIVELACION Y REPLANTEO POR KILOMETRO | E32: km | F32: 583.87 | G32: EQ | H32: 0301000020 | I32: ESTACION TOTAL | J32: he | K32: 1 | L32: 5 | M32: 16.7 | N32: 83.5 | P32: =IF(J32="%mo","",IF(G32="MO",IF(J32="hh",INDEX(MO_HH,MATCH(I32,MO_CAT,0)),M32*P_FACT_IPC),IF(G32="SUBPART",IFERROR(INDEX(APU_SUBP!$C$7:$C$40,MATCH(H32,APU_SUBP!$A$7:$A$40,0)),M32*P_FACT_IPC),M32*P_FACT_IPC))) -> 21.481141 | Q32: =IF(J32="%mo",L32/100*SUMIFS($R$7:$R$782,$A$7:$A$782,A32),L32*P32) -> 107.4057 | R32: =IF(G32="MO",L32*P32,0) -> 0
A33: CARCAVAS|01.04 | B33: CARCAVAS | C33: 01.04 | D33: TRAZO, NIVELACION Y REPLANTEO POR KILOMETRO | E33: km | F33: 583.87 | G33: EQ | H33: 0301000021 | I33: MIRAS Y JALONES | J33: he | K33: 0.5 | L33: 2.5 | M33: 0.12 | N33: 0.3 | P33: =IF(J33="%mo","",IF(G33="MO",IF(J33="hh",INDEX(MO_HH,MATCH(I33,MO_CAT,0)),M33*P_FACT_IPC),IF(G33="SUBPART",IFERROR(INDEX(APU_SUBP!$C$7:$C$40,MATCH(H33,APU_SUBP!$A$7:$A$40,0)),M33*P_FACT_IPC),M33*P_FACT_IPC))) -> 0.1543555 | Q33: =IF(J33="%mo",L33/100*SUMIFS($R$7:$R$782,$A$7:$A$782,A33),L33*P33) -> 0.38588875 | R33: =IF(G33="MO",L33*P33,0) -> 0
A34: CARCAVAS|01.04 | B34: CARCAVAS | C34: 01.04 | D34: TRAZO, NIVELACION Y REPLANTEO POR KILOMETRO | E34: km | F34: 583.87 | G34: EQ | H34: 0301010006 | I34: HERRAMIENTAS MANUALES | J34: %mo | L34: 3 | M34: 461.8 | N34: 13.85 | P34: =IF(J34="%mo","",IF(G34="MO",IF(J34="hh",INDEX(MO_HH,MATCH(I34,MO_CAT,0)),M34*P_FACT_IPC),IF(G34="SUBPART",IFERROR(INDEX(APU_SUBP!$C$7:$C$40,MATCH(H34,APU_SUBP!$A$7:$A$40,0)),M34*P_FACT_IPC),M34*P_FACT_IPC))) | Q34: =IF(J34="%mo",L34/100*SUMIFS($R$7:$R$782,$A$7:$A$782,A34),L34*P34) -> 10.320322 | R34: =IF(G34="MO",L34*P34,0) -> 0
A35: CARCAVAS|01.05 | B35: CARCAVAS | C35: 01.05 | D35: LIMPIEZA MANUAL DE TERRENO | E35: ha | F35: 285.04 | G35: MO | H35: 0101010002 | I35: CAPATAZ | J35: hh | K35: 1 | L35: 0.32 | M35: 25.81 | N35: 8.26 | O35: C | P35: =IF(J35="%mo","",IF(G35="MO",IF(J35="hh",INDEX(MO_HH,MATCH(I35,MO_CAT,0)),M35*P_FACT_IPC),IF(G35="SUBPART",IFERROR(INDEX(APU_SUBP!$C$7:$C$40,MATCH(H35,APU_SUBP!$A$7:$A$40,0)),M35*P_FACT_IPC),M35*P_FACT_IPC))) -> 19.226758 | Q35: =IF(J35="%mo",L35/100*SUMIFS($R$7:$R$782,$A$7:$A$782,A35),L35*P35) -> 6.1525626 | R35: =IF(G35="MO",L35*P35,0) -> 6.1525626
A36: CARCAVAS|01.05 | B36: CARCAVAS | C36: 01.05 | D36: LIMPIEZA MANUAL DE TERRENO | E36: ha | F36: 285.04 | G36: MO | H36: 0101010005 | I36: PEON | J36: hh | K36: 50 | L36: 16 | M36: 16.78 | N36: 268.48 | O36: NC | P36: =IF(J36="%mo","",IF(G36="MO",IF(J36="hh",INDEX(MO_HH,MATCH(I36,MO_CAT,0)),M36*P_FACT_IPC),IF(G36="SUBPART",IFERROR(INDEX(APU_SUBP!$C$7:$C$40,MATCH(H36,APU_SUBP!$A$7:$A$40,0)),M36*P_FACT_IPC),M36*P_FACT_IPC))) -> 12.5 | Q36: =IF(J36="%mo",L36/100*SUMIFS($R$7:$R$782,$A$7:$A$782,A36),L36*P36) -> 200 | R36: =IF(G36="MO",L36*P36,0) -> 200
A37: CARCAVAS|01.05 | B37: CARCAVAS | C37: 01.05 | D37: LIMPIEZA MANUAL DE TERRENO | E37: ha | F37: 285.04 | G37: EQ | H37: 0301010006 | I37: HERRAMIENTAS MANUALES | J37: %mo | L37: 3 | M37: 276.74 | N37: 8.3 | P37: =IF(J37="%mo","",IF(G37="MO",IF(J37="hh",INDEX(MO_HH,MATCH(I37,MO_CAT,0)),M37*P_FACT_IPC),IF(G37="SUBPART",IFERROR(INDEX(APU_SUBP!$C$7:$C$40,MATCH(H37,APU_SUBP!$A$7:$A$40,0)),M37*P_FACT_IPC),M37*P_FACT_IPC))) | Q37: =IF(J37="%mo",L37/100*SUMIFS($R$7:$R$782,$A$7:$A$782,A37),L37*P37) -> 6.1845769 | R37: =IF(G37="MO",L37*P37,0) -> 0
A38: CARCAVAS|01.06 | B38: CARCAVAS | C38: 01.06 | D38: SENSIBILIZACION A LA POBLACION EN CARCAVAS | E38: und | F38: 6000 | G38: MO | H38: 0103010014 | I38: INGENIERO ESPECIALISTA EN DIQUES PARA CONTROL DE CARCAVAS | J38: glb | L38: 1 | M38: 6000 | N38: 6000 | O38: C | P38: =IF(J38="%mo","",IF(G38="MO",IF(J38="hh",INDEX(MO_HH,MATCH(I38,MO_CAT,0)),M38*P_FACT_IPC),IF(G38="SUBPART",IFERROR(INDEX(APU_SUBP!$C$7:$C$40,MATCH(H38,APU_SUBP!$A$7:$A$40,0)),M38*P_FACT_IPC),M38*P_FACT_IPC))) -> 7717.775 | Q38: =IF(J38="%mo",L38/100*SUMIFS($R$7:$R$782,$A$7:$A$782,A38),L38*P38) -> 7717.775 | R38: =IF(G38="MO",L38*P38,0) -> 7717.775
A39: CARCAVAS|02.01 | B39: CARCAVAS | C39: 02.01 | D39: CAMPAMENTO PROVISIONAL DE OBRA Y ALMACENES | E39: m2 | F39: 202.06 | G39: SC | H39: 04020100020004 | I39: SC MUROS Y COLUMNAS DE MADERA TORNILLO O SIMILAR | J39: m2 | L39: 1 | M39: 53.5 | N39: 53.5 | P39: =IF(J39="%mo","",IF(G39="MO",IF(J39="hh",INDEX(MO_HH,MATCH(I39,MO_CAT,0)),M39*P_FACT_IPC),IF(G39="SUBPART",IFERROR(INDEX(APU_SUBP!$C$7:$C$40,MATCH(H39,APU_SUBP!$A$7:$A$40,0)),M39*P_FACT_IPC),M39*P_FACT_IPC))) -> 68.816827 | Q39: =IF(J39="%mo",L39/100*SUMIFS($R$7:$R$782,$A$7:$A$782,A39),L39*P39) -> 68.816827 | R39: =IF(G39="MO",L39*P39,0) -> 0
A40: CARCAVAS|02.01 | B40: CARCAVAS | C40: 02.01 | D40: CAMPAMENTO PROVISIONAL DE OBRA Y ALMACENES | E40: m2 | F40: 202.06 | G40: SC | H40: 04020100020005 | I40: SC TECHOS DE CALAMINA METALICA, FIBROCEMENTO SOBRE VIGERIA METALICA | J40: m2 | L40: 1 | M40: 41.46 | N40: 41.46 | P40: =IF(J40="%mo","",IF(G40="MO",IF(J40="hh",INDEX(MO_HH,MATCH(I40,MO_CAT,0)),M40*P_FACT_IPC),IF(G40="SUBPART",IFERROR(INDEX(APU_SUBP!$C$7:$C$40,MATCH(H40,APU_SUBP!$A$7:$A$40,0)),M40*P_FACT_IPC),M40*P_FACT_IPC))) -> 53.329826 | Q40: =IF(J40="%mo",L40/100*SUMIFS($R$7:$R$782,$A$7:$A$782,A40),L40*P40) -> 53.329826 | R40: =IF(G40="MO",L40*P40,0) -> 0
A41: CARCAVAS|02.01 | B41: CARCAVAS | C41: 02.01 | D41: CAMPAMENTO PROVISIONAL DE OBRA Y ALMACENES | E41: m2 | F41: 202.06 | G41: SC | H41: 04020100020006 | I41: SC LOSETA VINILICA, CEMENTO BRUÑADO COLOREADO, TAPIZON | J41: m2 | L41: 1 | M41: 25.68 | N41: 25.68 | P41: =IF(J41="%mo","",IF(G41="MO",IF(J41="hh",INDEX(MO_HH,MATCH(I41,MO_CAT,0)),M41*P_FACT_IPC),IF(G41="SUBPART",IFERROR(INDEX(APU_SUBP!$C$7:$C$40,MATCH(H41,APU_SUBP!$A$7:$A$40,0)),M41*P_FACT_IPC),M41*P_FACT_IPC))) -> 33.032077 | Q41: =IF(J41="%mo",L41/100*SUMIFS($R$7:$R$782,$A$7:$A$782,A41),L41*P41) -> 33.032077 | R41: =IF(G41="MO",L41*P41,0) -> 0
A42: CARCAVAS|02.01 | B42: CARCAVAS | C42: 02.01 | D42: CAMPAMENTO PROVISIONAL DE OBRA Y ALMACENES | E42: m2 | F42: 202.06 | G42: SC | H42: 04020100020007 | I42: SC PUERTAS Y VENTANAS, VENTANAS DE FIERRO O ALUMINIO INDUSTRIAL, PUERTA CONTRAPLACADA DE MADERA, DMF O HDF, VIDRIO | J42: m2 | L42: 1 | M42: 15.56 | N42: 15.56 | P42: =IF(J42="%mo","",IF(G42="MO",IF(J42="hh",INDEX(MO_HH,MATCH(I42,MO_CAT,0)),M42*P_FACT_IPC),IF(G42="SUBPART",IFERROR(INDEX(APU_SUBP!$C$7:$C$40,MATCH(H42,APU_SUBP!$A$7:$A$40,0)),M42*P_FACT_IPC),M42*P_FACT_IPC))) -> 20.014763 | Q42: =IF(J42="%mo",L42/100*SUMIFS($R$7:$R$782,$A$7:$A$782,A42),L42*P42) -> 20.014763 | R42: =IF(G42="MO",L42*P42,0) -> 0
A43: CARCAVAS|02.01 | B43: CARCAVAS | C43: 02.01 | D43: CAMPAMENTO PROVISIONAL DE OBRA Y ALMACENES | E43: m2 | F43: 202.06 | G43: SC | H43: 04020100020008 | I43: SC REVESTIMIENTOS, PINTADO EN LADRILLO O RUSTICO, PLACA DE CONCRETO O SIMILAR | J43: m2 | L43: 1 | M43: 12.45 | N43: 12.45 | P43: =IF(J43="%mo","",IF(G43="MO",IF(J43="hh",INDEX(MO_HH,MATCH(I43,MO_CAT,0)),M43*P_FACT_IPC),IF(G43="SUBPART",IFERROR(INDEX(APU_SUBP!$C$7:$C$40,MATCH(H43,APU_SUBP!$A$7:$A$40,0)),M43*P_FACT_IPC),M43*P_FACT_IPC))) -> 16.014383 | Q43: =IF(J43="%mo",L43/100*SUMIFS($R$7:$R$782,$A$7:$A$782,A43),L43*P43) -> 16.014383 | R43: =IF(G43="MO",L43*P43,0) -> 0
A44: CARCAVAS|02.01 | B44: CARCAVAS | C44: 02.01 | D44: CAMPAMENTO PROVISIONAL DE OBRA Y ALMACENES | E44: m2 | F44: 202.06 | G44: SC | H44: 04020100020009 | I44: SC BAÑOS COMPLETOS NACIONALES CON MAYOLICA BLANCA | J44: m2 | L44: 1 | M44: 27.78 | N44: 27.78 | P44: =IF(J44="%mo","",IF(G44="MO",IF(J44="hh",INDEX(MO_HH,MATCH(I44,MO_CAT,0)),M44*P_FACT_IPC),IF(G44="SUBPART",IFERROR(INDEX(APU_SUBP!$C$7:$C$40,MATCH(H44,APU_SUBP!$A$7:$A$40,0)),M44*P_FACT_IPC),M44*P_FACT_IPC))) -> 35.733298 | Q44: =IF(J44="%mo",L44/100*SUMIFS($R$7:$R$782,$A$7:$A$782,A44),L44*P44) -> 35.733298 | R44: =IF(G44="MO",L44*P44,0) -> 0
A45: CARCAVAS|02.01 | B45: CARCAVAS | C45: 02.01 | D45: CAMPAMENTO PROVISIONAL DE OBRA Y ALMACENES | E45: m2 | F45: 202.06 | G45: SC | H45: 04020100020010 | I45: SC INSTALACIONES ELECTRICAS Y SANITARIA, AGUA FRIA, AGUA CALIENTE, CORRIENTE MONOFASICA, TELEFONO, GAS NATURAL | J45: m2 | L45: 1 | M45: 25.63 | N45: 25.63 | P45: =IF(J45="%mo","",IF(G45="MO",IF(J45="hh",INDEX(MO_HH,MATCH(I45,MO_CAT,0)),M45*P_FACT_IPC),IF(G45="SUBPART",IFERROR(INDEX(APU_SUBP!$C$7:$C$40,MATCH(H45,APU_SUBP!$A$7:$A$40,0)),M45*P_FACT_IPC),M45*P_FACT_IPC))) -> 32.967762 | Q45: =IF(J45="%mo",L45/100*SUMIFS($R$7:$R$782,$A$7:$A$782,A45),L45*P45) -> 32.967762 | R45: =IF(G45="MO",L45*P45,0) -> 0
A46: CARCAVAS|02.02 | B46: CARCAVAS | C46: 02.02 | D46: CARTEL DE OBRA 4.80 X 3.60 M CON GIGANTOGRAFIA | E46: und | F46: 4445.55 | G46: MO | H46: 0101010002 | I46: CAPATAZ | J46: hh | K46: 0.5 | L46: 4 | M46: 25.81 | N46: 103.24 | O46: C | P46: =IF(J46="%mo","",IF(G46="MO",IF(J46="hh",INDEX(MO_HH,MATCH(I46,MO_CAT,0)),M46*P_FACT_IPC),IF(G46="SUBPART",IFERROR(INDEX(APU_SUBP!$C$7:$C$40,MATCH(H46,APU_SUBP!$A$7:$A$40,0)),M46*P_FACT_IPC),M46*P_FACT_IPC))) -> 19.226758 | Q46: =IF(J46="%mo",L46/100*SUMIFS($R$7:$R$782,$A$7:$A$782,A46),L46*P46) -> 76.907032 | R46: =IF(G46="MO",L46*P46,0) -> 76.907032
A47: CARCAVAS|02.02 | B47: CARCAVAS | C47: 02.02 | D47: CARTEL DE OBRA 4.80 X 3.60 M CON GIGANTOGRAFIA | E47: und | F47: 4445.55 | G47: MO | H47: 0101010003 | I47: OPERARIO | J47: hh | K47: 1 | L47: 8 | M47: 23.46 | N47: 187.68 | O47: C | P47: =IF(J47="%mo","",IF(G47="MO",IF(J47="hh",INDEX(MO_HH,MATCH(I47,MO_CAT,0)),M47*P_FACT_IPC),IF(G47="SUBPART",IFERROR(INDEX(APU_SUBP!$C$7:$C$40,MATCH(H47,APU_SUBP!$A$7:$A$40,0)),M47*P_FACT_IPC),M47*P_FACT_IPC))) -> 17.476162 | Q47: =IF(J47="%mo",L47/100*SUMIFS($R$7:$R$782,$A$7:$A$782,A47),L47*P47) -> 139.8093 | R47: =IF(G47="MO",L47*P47,0) -> 139.8093
A48: CARCAVAS|02.02 | B48: CARCAVAS | C48: 02.02 | D48: CARTEL DE OBRA 4.80 X 3.60 M CON GIGANTOGRAFIA | E48: und | F48: 4445.55 | G48: MO | H48: 0101010005 | I48: PEON | J48: hh | K48: 4 | L48: 32 | M48: 16.78 | N48: 536.96 | O48: NC | P48: =IF(J48="%mo","",IF(G48="MO",IF(J48="hh",INDEX(MO_HH,MATCH(I48,MO_CAT,0)),M48*P_FACT_IPC),IF(G48="SUBPART",IFERROR(INDEX(APU_SUBP!$C$7:$C$40,MATCH(H48,APU_SUBP!$A$7:$A$40,0)),M48*P_FACT_IPC),M48*P_FACT_IPC))) -> 12.5 | Q48: =IF(J48="%mo",L48/100*SUMIFS($R$7:$R$782,$A$7:$A$782,A48),L48*P48) -> 400 | R48: =IF(G48="MO",L48*P48,0) -> 400
A49: CARCAVAS|02.02 | B49: CARCAVAS | C49: 02.02 | D49: CARTEL DE OBRA 4.80 X 3.60 M CON GIGANTOGRAFIA | E49: und | F49: 4445.55 | G49: MAT | H49: 0204120001 | I49: CLAVOS PARA MADERA CON CABEZA | J49: kg | L49: 0.85 | M49: 4.43 | N49: 3.77 | P49: =IF(J49="%mo","",IF(G49="MO",IF(J49="hh",INDEX(MO_HH,MATCH(I49,MO_CAT,0)),M49*P_FACT_IPC),IF(G49="SUBPART",IFERROR(INDEX(APU_SUBP!$C$7:$C$40,MATCH(H49,APU_SUBP!$A$7:$A$40,0)),M49*P_FACT_IPC),M49*P_FACT_IPC))) -> 5.6982906 | Q49: =IF(J49="%mo",L49/100*SUMIFS($R$7:$R$782,$A$7:$A$782,A49),L49*P49) -> 4.843547 | R49: =IF(G49="MO",L49*P49,0) -> 0
A50: CARCAVAS|02.02 | B50: CARCAVAS | C50: 02.02 | D50: CARTEL DE OBRA 4.80 X 3.60 M CON GIGANTOGRAFIA | E50: und | F50: 4445.55 | G50: MAT | H50: 0213010001 | I50: CEMENTO PORTLAND TIPO I (42.5 kg) | J50: bol | L50: 1.05 | M50: 24.68 | N50: 25.91 | P50: =IF(J50="%mo","",IF(G50="MO",IF(J50="hh",INDEX(MO_HH,MATCH(I50,MO_CAT,0)),M50*P_FACT_IPC),IF(G50="SUBPART",IFERROR(INDEX(APU_SUBP!$C$7:$C$40,MATCH(H50,APU_SUBP!$A$7:$A$40,0)),M50*P_FACT_IPC),M50*P_FACT_IPC))) -> 31.745781 | Q50: =IF(J50="%mo",L50/100*SUMIFS($R$7:$R$782,$A$7:$A$782,A50),L50*P50) -> 33.33307 | R50: =IF(G50="MO",L50*P50,0) -> 0
A51: CARCAVAS|02.02 | B51: CARCAVAS | C51: 02.02 | D51: CARTEL DE OBRA 4.80 X 3.60 M CON GIGANTOGRAFIA | E51: und | F51: 4445.55 | G51: MAT | H51: 0231010002 | I51: MADERA TORNILLO PARA ENCOFRADOS INCLUYE CORTE | J51: p2 | L51: 70 | M51: 4.13 | N51: 289.1 | P51: =IF(J51="%mo","",IF(G51="MO",IF(J51="hh",INDEX(MO_HH,MATCH(I51,MO_CAT,0)),M51*P_FACT_IPC),IF(G51="SUBPART",IFERROR(INDEX(APU_SUBP!$C$7:$C$40,MATCH(H51,APU_SUBP!$A$7:$A$40,0)),M51*P_FACT_IPC),M51*P_FACT_IPC))) -> 5.3124018 | Q51: =IF(J51="%mo",L51/100*SUMIFS($R$7:$R$782,$A$7:$A$782,A51),L51*P51) -> 371.86813 | R51: =IF(G51="MO",L51*P51,0) -> 0
A52: CARCAVAS|02.02 | B52: CARCAVAS | C52: 02.02 | D52: CARTEL DE OBRA 4.80 X 3.60 M CON GIGANTOGRAFIA | E52: und | F52: 4445.55 | G52: MAT | H52: 0240020001 | I52: PINTURA ESMALTE | J52: gal | L52: 0.25 | M52: 34.07 | N52: 8.52 | P52: =IF(J52="%mo","",IF(G52="MO",IF(J52="hh",INDEX(MO_HH,MATCH(I52,MO_CAT,0)),M52*P_FACT_IPC),IF(G52="SUBPART",IFERROR(INDEX(APU_SUBP!$C$7:$C$40,MATCH(H52,APU_SUBP!$A$7:$A$40,0)),M52*P_FACT_IPC),M52*P_FACT_IPC))) -> 43.824099 | Q52: =IF(J52="%mo",L52/100*SUMIFS($R$7:$R$782,$A$7:$A$782,A52),L52*P52) -> 10.956025 | R52: =IF(G52="MO",L52*P52,0) -> 0
A53: CARCAVAS|02.02 | B53: CARCAVAS | C53: 02.02 | D53: CARTEL DE OBRA 4.80 X 3.60 M CON GIGANTOGRAFIA | E53: und | F53: 4445.55 | G53: MAT | H53: 0271050081 | I53: PERNO DE ACERO 1/2" INC./TUERCA Y ARANDELA | J53: und | L53: 15 | M53: 3.01 | N53: 45.15 | P53: =IF(J53="%mo","",IF(G53="MO",IF(J53="hh",INDEX(MO_HH,MATCH(I53,MO_CAT,0)),M53*P_FACT_IPC),IF(G53="SUBPART",IFERROR(INDEX(APU_SUBP!$C$7:$C$40,MATCH(H53,APU_SUBP!$A$7:$A$40,0)),M53*P_FACT_IPC),M53*P_FACT_IPC))) -> 3.8717505 | Q53: =IF(J53="%mo",L53/100*SUMIFS($R$7:$R$782,$A$7:$A$782,A53),L53*P53) -> 58.076257 | R53: =IF(G53="MO",L53*P53,0) -> 0
A54: CARCAVAS|02.02 | B54: CARCAVAS | C54: 02.02 | D54: CARTEL DE OBRA 4.80 X 3.60 M CON GIGANTOGRAFIA | E54: und | F54: 4445.55 | G54: EQ | H54: 0301010006 | I54: HERRAMIENTAS MANUALES | J54: %mo | L54: 3 | M54: 827.88 | N54: 24.84 | P54: =IF(J54="%mo","",IF(G54="MO",IF(J54="hh",INDEX(MO_HH,MATCH(I54,MO_CAT,0)),M54*P_FACT_IPC),IF(G54="SUBPART",IFERROR(INDEX(APU_SUBP!$C$7:$C$40,MATCH(H54,APU_SUBP!$A$7:$A$40,0)),M54*P_FACT_IPC),M54*P_FACT_IPC))) | Q54: =IF(J54="%mo",L54/100*SUMIFS($R$7:$R$782,$A$7:$A$782,A54),L54*P54) -> 18.50149 | R54: =IF(G54="MO",L54*P54,0) -> 0
A55: CARCAVAS|02.02 | B55: CARCAVAS | C55: 02.02 | D55: CARTEL DE OBRA 4.80 X 3.60 M CON GIGANTOGRAFIA | E55: und | F55: 4445.55 | G55: SC | H55: 0425010010 | I55: SC SUBCONTRATO DE CONFECCION DE GIGANTOGRAFIA 4 .80X3.60 M | J55: glb | L55: 1 | M55: 3200 | N55: 3200 | P55: =IF(J55="%mo","",IF(G55="MO",IF(J55="hh",INDEX(MO_HH,MATCH(I55,MO_CAT,0)),M55*P_FACT_IPC),IF(G55="SUBPART",IFERROR(INDEX(APU_SUBP!$C$7:$C$40,MATCH(H55,APU_SUBP!$A$7:$A$40,0)),M55*P_FACT_IPC),M55*P_FACT_IPC))) -> 4116.1467 | Q55: =IF(J55="%mo",L55/100*SUMIFS($R$7:$R$782,$A$7:$A$782,A55),L55*P55) -> 4116.1467 | R55: =IF(G55="MO",L55*P55,0) -> 0
A56: CARCAVAS|02.02 | B56: CARCAVAS | C56: 02.02 | D56: CARTEL DE OBRA 4.80 X 3.60 M CON GIGANTOGRAFIA | E56: und | F56: 4445.55 | G56: SUBPART | H56: 011002010134 | I56: ARENA PUESTA EN OBRA | J56: m3 | L56: 0.36 | M56: 56.6 | N56: 20.38 | P56: =IF(J56="%mo","",IF(G56="MO",IF(J56="hh",INDEX(MO_HH,MATCH(I56,MO_CAT,0)),M56*P_FACT_IPC),IF(G56="SUBPART",IFERROR(INDEX(APU_SUBP!$C$7:$C$40,MATCH(H56,APU_SUBP!$A$7:$A$40,0)),M56*P_FACT_IPC),M56*P_FACT_IPC))) -> 69.142511 | Q56: =IF(J56="%mo",L56/100*SUMIFS($R$7:$R$782,$A$7:$A$782,A56),L56*P56) -> 24.891304 | R56: =IF(G56="MO",L56*P56,0) -> 0
A57: CARCAVAS|03.01.01 | B57: CARCAVAS | C57: 03.01.01 | D57: PEINADO DE CARCAVAS | E57: m2 | F57: 7.45 | G57: MO | H57: 0101010002 | I57: CAPATAZ | J57: hh | K57: 0.1 | L57: 0.02 | M57: 25.81 | N57: 0.52 | O57: C | P57: =IF(J57="%mo","",IF(G57="MO",IF(J57="hh",INDEX(MO_HH,MATCH(I57,MO_CAT,0)),M57*P_FACT_IPC),IF(G57="SUBPART",IFERROR(INDEX(APU_SUBP!$C$7:$C$40,MATCH(H57,APU_SUBP!$A$7:$A$40,0)),M57*P_FACT_IPC),M57*P_FACT_IPC))) -> 19.226758 | Q57: =IF(J57="%mo",L57/100*SUMIFS($R$7:$R$782,$A$7:$A$782,A57),L57*P57) -> 0.38453516 | R57: =IF(G57="MO",L57*P57,0) -> 0.38453516
A58: CARCAVAS|03.01.01 | B58: CARCAVAS | C58: 03.01.01 | D58: PEINADO DE CARCAVAS | E58: m2 | F58: 7.45 | G58: MO | H58: 0101010005 | I58: PEON | J58: hh | K58: 2 | L58: 0.4 | M58: 16.78 | N58: 6.71 | O58: NC | P58: =IF(J58="%mo","",IF(G58="MO",IF(J58="hh",INDEX(MO_HH,MATCH(I58,MO_CAT,0)),M58*P_FACT_IPC),IF(G58="SUBPART",IFERROR(INDEX(APU_SUBP!$C$7:$C$40,MATCH(H58,APU_SUBP!$A$7:$A$40,0)),M58*P_FACT_IPC),M58*P_FACT_IPC))) -> 12.5 | Q58: =IF(J58="%mo",L58/100*SUMIFS($R$7:$R$782,$A$7:$A$782,A58),L58*P58) -> 5 | R58: =IF(G58="MO",L58*P58,0) -> 5
A59: CARCAVAS|03.01.01 | B59: CARCAVAS | C59: 03.01.01 | D59: PEINADO DE CARCAVAS | E59: m2 | F59: 7.45 | G59: EQ | H59: 0301010006 | I59: HERRAMIENTAS MANUALES | J59: %mo | L59: 3 | M59: 7.23 | N59: 0.22 | P59: =IF(J59="%mo","",IF(G59="MO",IF(J59="hh",INDEX(MO_HH,MATCH(I59,MO_CAT,0)),M59*P_FACT_IPC),IF(G59="SUBPART",IFERROR(INDEX(APU_SUBP!$C$7:$C$40,MATCH(H59,APU_SUBP!$A$7:$A$40,0)),M59*P_FACT_IPC),M59*P_FACT_IPC))) | Q59: =IF(J59="%mo",L59/100*SUMIFS($R$7:$R$782,$A$7:$A$782,A59),L59*P59) -> 0.16153605 | R59: =IF(G59="MO",L59*P59,0) -> 0
A60: CARCAVAS|03.01.02 | B60: CARCAVAS | C60: 03.01.02 | D60: EXCAVACION MANUAL EN MATERIAL SUELTO | E60: m3 | F60: 63.82 | G60: MO | H60: 0101010002 | I60: CAPATAZ | J60: hh | K60: 0.1 | L60: 0.32 | M60: 25.81 | N60: 8.26 | O60: C | P60: =IF(J60="%mo","",IF(G60="MO",IF(J60="hh",INDEX(MO_HH,MATCH(I60,MO_CAT,0)),M60*P_FACT_IPC),IF(G60="SUBPART",IFERROR(INDEX(APU_SUBP!$C$7:$C$40,MATCH(H60,APU_SUBP!$A$7:$A$40,0)),M60*P_FACT_IPC),M60*P_FACT_IPC))) -> 19.226758 | Q60: =IF(J60="%mo",L60/100*SUMIFS($R$7:$R$782,$A$7:$A$782,A60),L60*P60) -> 6.1525626 | R60: =IF(G60="MO",L60*P60,0) -> 6.1525626
A61: CARCAVAS|03.01.02 | B61: CARCAVAS | C61: 03.01.02 | D61: EXCAVACION MANUAL EN MATERIAL SUELTO | E61: m3 | F61: 63.82 | G61: MO | H61: 0101010005 | I61: PEON | J61: hh | K61: 1 | L61: 3.2 | M61: 16.78 | N61: 53.7 | O61: NC | P61: =IF(J61="%mo","",IF(G61="MO",IF(J61="hh",INDEX(MO_HH,MATCH(I61,MO_CAT,0)),M61*P_FACT_IPC),IF(G61="SUBPART",IFERROR(INDEX(APU_SUBP!$C$7:$C$40,MATCH(H61,APU_SUBP!$A$7:$A$40,0)),M61*P_FACT_IPC),M61*P_FACT_IPC))) -> 12.5 | Q61: =IF(J61="%mo",L61/100*SUMIFS($R$7:$R$782,$A$7:$A$782,A61),L61*P61) -> 40 | R61: =IF(G61="MO",L61*P61,0) -> 40
A62: CARCAVAS|03.01.02 | B62: CARCAVAS | C62: 03.01.02 | D62: EXCAVACION MANUAL EN MATERIAL SUELTO | E62: m3 | F62: 63.82 | G62: EQ | H62: 0301010006 | I62: HERRAMIENTAS MANUALES | J62: %mo | L62: 3 | M62: 61.96 | N62: 1.86 | P62: =IF(J62="%mo","",IF(G62="MO",IF(J62="hh",INDEX(MO_HH,MATCH(I62,MO_CAT,0)),M62*P_FACT_IPC),IF(G62="SUBPART",IFERROR(INDEX(APU_SUBP!$C$7:$C$40,MATCH(H62,APU_SUBP!$A$7:$A$40,0)),M62*P_FACT_IPC),M62*P_FACT_IPC))) | Q62: =IF(J62="%mo",L62/100*SUMIFS($R$7:$R$782,$A$7:$A$782,A62),L62*P62) -> 1.3845769 | R62: =IF(G62="MO",L62*P62,0) -> 0
A63: CARCAVAS|03.01.03 | B63: CARCAVAS | C63: 03.01.03 | D63: NIVELACION Y COMPACTACION MANUAL DE TERRENO | E63: m2 | F63: 3.19 | G63: MO | H63: 0101010002 | I63: CAPATAZ | J63: hh | K63: 0.1 | L63: 0.0032 | M63: 25.81 | N63: 0.08 | O63: C | P63: =IF(J63="%mo","",IF(G63="MO",IF(J63="hh",INDEX(MO_HH,MATCH(I63,MO_CAT,0)),M63*P_FACT_IPC),IF(G63="SUBPART",IFERROR(INDEX(APU_SUBP!$C$7:$C$40,MATCH(H63,APU_SUBP!$A$7:$A$40,0)),M63*P_FACT_IPC),M63*P_FACT_IPC))) -> 19.226758 | Q63: =IF(J63="%mo",L63/100*SUMIFS($R$7:$R$782,$A$7:$A$782,A63),L63*P63) -> 0.061525626 | R63: =IF(G63="MO",L63*P63,0) -> 0.061525626
A64: CARCAVAS|03.01.03 | B64: CARCAVAS | C64: 03.01.03 | D64: NIVELACION Y COMPACTACION MANUAL DE TERRENO | E64: m2 | F64: 3.19 | G64: MO | H64: 0101010003 | I64: OPERARIO | J64: hh | K64: 1 | L64: 0.032 | M64: 23.46 | N64: 0.75 | O64: C | P64: =IF(J64="%mo","",IF(G64="MO",IF(J64="hh",INDEX(MO_HH,MATCH(I64,MO_CAT,0)),M64*P_FACT_IPC),IF(G64="SUBPART",IFERROR(INDEX(APU_SUBP!$C$7:$C$40,MATCH(H64,APU_SUBP!$A$7:$A$40,0)),M64*P_FACT_IPC),M64*P_FACT_IPC))) -> 17.476162 | Q64: =IF(J64="%mo",L64/100*SUMIFS($R$7:$R$782,$A$7:$A$782,A64),L64*P64) -> 0.55923719 | R64: =IF(G64="MO",L64*P64,0) -> 0.55923719
A65: CARCAVAS|03.01.03 | B65: CARCAVAS | C65: 03.01.03 | D65: NIVELACION Y COMPACTACION MANUAL DE TERRENO | E65: m2 | F65: 3.19 | G65: MO | H65: 0101010005 | I65: PEON | J65: hh | K65: 2 | L65: 0.064 | M65: 16.78 | N65: 1.07 | O65: NC | P65: =IF(J65="%mo","",IF(G65="MO",IF(J65="hh",INDEX(MO_HH,MATCH(I65,MO_CAT,0)),M65*P_FACT_IPC),IF(G65="SUBPART",IFERROR(INDEX(APU_SUBP!$C$7:$C$40,MATCH(H65,APU_SUBP!$A$7:$A$40,0)),M65*P_FACT_IPC),M65*P_FACT_IPC))) -> 12.5 | Q65: =IF(J65="%mo",L65/100*SUMIFS($R$7:$R$782,$A$7:$A$782,A65),L65*P65) -> 0.8 | R65: =IF(G65="MO",L65*P65,0) -> 0.8
A66: CARCAVAS|03.01.03 | B66: CARCAVAS | C66: 03.01.03 | D66: NIVELACION Y COMPACTACION MANUAL DE TERRENO | E66: m2 | F66: 3.19 | G66: EQ | H66: 0301010006 | I66: HERRAMIENTAS MANUALES | J66: %mo | L66: 3 | M66: 1.9 | N66: 0.06 | P66: =IF(J66="%mo","",IF(G66="MO",IF(J66="hh",INDEX(MO_HH,MATCH(I66,MO_CAT,0)),M66*P_FACT_IPC),IF(G66="SUBPART",IFERROR(INDEX(APU_SUBP!$C$7:$C$40,MATCH(H66,APU_SUBP!$A$7:$A$40,0)),M66*P_FACT_IPC),M66*P_FACT_IPC))) | Q66: =IF(J66="%mo",L66/100*SUMIFS($R$7:$R$782,$A$7:$A$782,A66),L66*P66) -> 0.042622884 | R66: =IF(G66="MO",L66*P66,0) -> 0
A67: CARCAVAS|03.01.03 | B67: CARCAVAS | C67: 03.01.03 | D67: NIVELACION Y COMPACTACION MANUAL DE TERRENO | E67: m2 | F67: 3.19 | G67: EQ | H67: 0301100001 | I67: COMPACTADORA VIBRATORIA TIPO PLANCHA 7 HP | J67: hm | K67: 1 | L67: 0.032 | M67: 38.5 | N67: 1.23 | P67: =IF(J67="%mo","",IF(G67="MO",IF(J67="hh",INDEX(MO_HH,MATCH(I67,MO_CAT,0)),M67*P_FACT_IPC),IF(G67="SUBPART",IFERROR(INDEX(APU_SUBP!$C$7:$C$40,MATCH(H67,APU_SUBP!$A$7:$A$40,0)),M67*P_FACT_IPC),M67*P_FACT_IPC))) -> 49.52239 | Q67: =IF(J67="%mo",L67/100*SUMIFS($R$7:$R$782,$A$7:$A$782,A67),L67*P67) -> 1.5847165 | R67: =IF(G67="MO",L67*P67,0) -> 0
A68: CARCAVAS|03.01.04 | B68: CARCAVAS | C68: 03.01.04 | D68: COLOCACION DE PIEDRA CANTEADA | E68: m3 | F68: 166 | G68: MO | H68: 0101010002 | I68: CAPATAZ | J68: hh | K68: 0.1 | L68: 0.1 | M68: 25.81 | N68: 2.58 | O68: C | P68: =IF(J68="%mo","",IF(G68="MO",IF(J68="hh",INDEX(MO_HH,MATCH(I68,MO_CAT,0)),M68*P_FACT_IPC),IF(G68="SUBPART",IFERROR(INDEX(APU_SUBP!$C$7:$C$40,MATCH(H68,APU_SUBP!$A$7:$A$40,0)),M68*P_FACT_IPC),M68*P_FACT_IPC))) -> 19.226758 | Q68: =IF(J68="%mo",L68/100*SUMIFS($R$7:$R$782,$A$7:$A$782,A68),L68*P68) -> 1.9226758 | R68: =IF(G68="MO",L68*P68,0) -> 1.9226758
A69: CARCAVAS|03.01.04 | B69: CARCAVAS | C69: 03.01.04 | D69: COLOCACION DE PIEDRA CANTEADA | E69: m3 | F69: 166 | G69: MO | H69: 0101010004 | I69: OFICIAL | J69: hh | K69: 0.5 | L69: 0.5 | M69: 18.56 | N69: 9.28 | O69: C | P69: =IF(J69="%mo","",IF(G69="MO",IF(J69="hh",INDEX(MO_HH,MATCH(I69,MO_CAT,0)),M69*P_FACT_IPC),IF(G69="SUBPART",IFERROR(INDEX(APU_SUBP!$C$7:$C$40,MATCH(H69,APU_SUBP!$A$7:$A$40,0)),M69*P_FACT_IPC),M69*P_FACT_IPC))) -> 13.825983 | Q69: =IF(J69="%mo",L69/100*SUMIFS($R$7:$R$782,$A$7:$A$782,A69),L69*P69) -> 6.9129917 | R69: =IF(G69="MO",L69*P69,0) -> 6.9129917
A70: CARCAVAS|03.01.04 | B70: CARCAVAS | C70: 03.01.04 | D70: COLOCACION DE PIEDRA CANTEADA | E70: m3 | F70: 166 | G70: MO | H70: 0101010005 | I70: PEON | J70: hh | K70: 2 | L70: 2 | M70: 16.78 | N70: 33.56 | O70: NC | P70: =IF(J70="%mo","",IF(G70="MO",IF(J70="hh",INDEX(MO_HH,MATCH(I70,MO_CAT,0)),M70*P_FACT_IPC),IF(G70="SUBPART",IFERROR(INDEX(APU_SUBP!$C$7:$C$40,MATCH(H70,APU_SUBP!$A$7:$A$40,0)),M70*P_FACT_IPC),M70*P_FACT_IPC))) -> 12.5 | Q70: =IF(J70="%mo",L70/100*SUMIFS($R$7:$R$782,$A$7:$A$782,A70),L70*P70) -> 25 | R70: =IF(G70="MO",L70*P70,0) -> 25
A71: CARCAVAS|03.01.04 | B71: CARCAVAS | C71: 03.01.04 | D71: COLOCACION DE PIEDRA CANTEADA | E71: m3 | F71: 166 | G71: EQ | H71: 0301010006 | I71: HERRAMIENTAS MANUALES | J71: %mo | L71: 3 | M71: 45.42 | N71: 1.36 | P71: =IF(J71="%mo","",IF(G71="MO",IF(J71="hh",INDEX(MO_HH,MATCH(I71,MO_CAT,0)),M71*P_FACT_IPC),IF(G71="SUBPART",IFERROR(INDEX(APU_SUBP!$C$7:$C$40,MATCH(H71,APU_SUBP!$A$7:$A$40,0)),M71*P_FACT_IPC),M71*P_FACT_IPC))) | Q71: =IF(J71="%mo",L71/100*SUMIFS($R$7:$R$782,$A$7:$A$782,A71),L71*P71) -> 1.01507 | R71: =IF(G71="MO",L71*P71,0) -> 0
A72: CARCAVAS|03.01.04 | B72: CARCAVAS | C72: 03.01.04 | D72: COLOCACION DE PIEDRA CANTEADA | E72: m3 | F72: 166 | G72: SUBPART | H72: 011002010210 | I72: PIEDRA CANTEADA PUESTA EN OBRA DIA. MAX. 12" | J72: m3 | L72: 1.05 | M72: 113.54 | N72: 119.22 | P72: =IF(J72="%mo","",IF(G72="MO",IF(J72="hh",INDEX(MO_HH,MATCH(I72,MO_CAT,0)),M72*P_FACT_IPC),IF(G72="SUBPART",IFERROR(INDEX(APU_SUBP!$C$7:$C$40,MATCH(H72,APU_SUBP!$A$7:$A$40,0)),M72*P_FACT_IPC),M72*P_FACT_IPC))) -> 86.441692 | Q72: =IF(J72="%mo",L72/100*SUMIFS($R$7:$R$782,$A$7:$A$782,A72),L72*P72) -> 90.763776 | R72: =IF(G72="MO",L72*P72,0) -> 0
A73: CARCAVAS|03.02.01 | B73: CARCAVAS | C73: 03.02.01 | D73: APERTURA DE HOYOS 0.30x0.30x0.30 M. PARA ESQUEJES | E73: und | F73: 1.73 | G73: MO | H73: 0101010002 | I73: CAPATAZ | J73: hh | K73: 0.1 | L73: 0.0087 | M73: 25.81 | N73: 0.22 | O73: C | P73: =IF(J73="%mo","",IF(G73="MO",IF(J73="hh",INDEX(MO_HH,MATCH(I73,MO_CAT,0)),M73*P_FACT_IPC),IF(G73="SUBPART",IFERROR(INDEX(APU_SUBP!$C$7:$C$40,MATCH(H73,APU_SUBP!$A$7:$A$40,0)),M73*P_FACT_IPC),M73*P_FACT_IPC))) -> 19.226758 | Q73: =IF(J73="%mo",L73/100*SUMIFS($R$7:$R$782,$A$7:$A$782,A73),L73*P73) -> 0.16727279 | R73: =IF(G73="MO",L73*P73,0) -> 0.16727279
A74: CARCAVAS|03.02.01 | B74: CARCAVAS | C74: 03.02.01 | D74: APERTURA DE HOYOS 0.30x0.30x0.30 M. PARA ESQUEJES | E74: und | F74: 1.73 | G74: MO | H74: 0101010005 | I74: PEON | J74: hh | K74: 1 | L74: 0.087 | M74: 16.78 | N74: 1.46 | O74: NC | P74: =IF(J74="%mo","",IF(G74="MO",IF(J74="hh",INDEX(MO_HH,MATCH(I74,MO_CAT,0)),M74*P_FACT_IPC),IF(G74="SUBPART",IFERROR(INDEX(APU_SUBP!$C$7:$C$40,MATCH(H74,APU_SUBP!$A$7:$A$40,0)),M74*P_FACT_IPC),M74*P_FACT_IPC))) -> 12.5 | Q74: =IF(J74="%mo",L74/100*SUMIFS($R$7:$R$782,$A$7:$A$782,A74),L74*P74) -> 1.0875 | R74: =IF(G74="MO",L74*P74,0) -> 1.0875
A75: CARCAVAS|03.02.01 | B75: CARCAVAS | C75: 03.02.01 | D75: APERTURA DE HOYOS 0.30x0.30x0.30 M. PARA ESQUEJES | E75: und | F75: 1.73 | G75: EQ | H75: 0301010006 | I75: HERRAMIENTAS MANUALES | J75: %mo | L75: 3 | M75: 1.68 | N75: 0.05 | P75: =IF(J75="%mo","",IF(G75="MO",IF(J75="hh",INDEX(MO_HH,MATCH(I75,MO_CAT,0)),M75*P_FACT_IPC),IF(G75="SUBPART",IFERROR(INDEX(APU_SUBP!$C$7:$C$40,MATCH(H75,APU_SUBP!$A$7:$A$40,0)),M75*P_FACT_IPC),M75*P_FACT_IPC))) | Q75: =IF(J75="%mo",L75/100*SUMIFS($R$7:$R$782,$A$7:$A$782,A75),L75*P75) -> 0.037643184 | R75: =IF(G75="MO",L75*P75,0) -> 0
A76: CARCAVAS|03.02.02 | B76: CARCAVAS | C76: 03.02.02 | D76: SELECCION Y CORTE DE ESQUEJES PARA REVEGETACION | E76: und | F76: 1.17 | G76: MO | H76: 0101010004 | I76: OFICIAL | J76: hh | K76: 0.1 | L76: 0.005 | M76: 18.56 | N76: 0.09 | O76: C | P76: =IF(J76="%mo","",IF(G76="MO",IF(J76="hh",INDEX(MO_HH,MATCH(I76,MO_CAT,0)),M76*P_FACT_IPC),IF(G76="SUBPART",IFERROR(INDEX(APU_SUBP!$C$7:$C$40,MATCH(H76,APU_SUBP!$A$7:$A$40,0)),M76*P_FACT_IPC),M76*P_FACT_IPC))) -> 13.825983 | Q76: =IF(J76="%mo",L76/100*SUMIFS($R$7:$R$782,$A$7:$A$782,A76),L76*P76) -> 0.069129917 | R76: =IF(G76="MO",L76*P76,0) -> 0.069129917
A77: CARCAVAS|03.02.02 | B77: CARCAVAS | C77: 03.02.02 | D77: SELECCION Y CORTE DE ESQUEJES PARA REVEGETACION | E77: und | F77: 1.17 | G77: MO | H77: 0101010005 | I77: PEON | J77: hh | K77: 1 | L77: 0.05 | M77: 16.78 | N77: 0.84 | O77: NC | P77: =IF(J77="%mo","",IF(G77="MO",IF(J77="hh",INDEX(MO_HH,MATCH(I77,MO_CAT,0)),M77*P_FACT_IPC),IF(G77="SUBPART",IFERROR(INDEX(APU_SUBP!$C$7:$C$40,MATCH(H77,APU_SUBP!$A$7:$A$40,0)),M77*P_FACT_IPC),M77*P_FACT_IPC))) -> 12.5 | Q77: =IF(J77="%mo",L77/100*SUMIFS($R$7:$R$782,$A$7:$A$782,A77),L77*P77) -> 0.625 | R77: =IF(G77="MO",L77*P77,0) -> 0.625
A78: CARCAVAS|03.02.02 | B78: CARCAVAS | C78: 03.02.02 | D78: SELECCION Y CORTE DE ESQUEJES PARA REVEGETACION | E78: und | F78: 1.17 | G78: MAT | H78: 02070500010007 | I78: GUANO DE ISLA | J78: kg | L78: 0.11 | M78: 1.16 | N78: 0.13 | P78: =IF(J78="%mo","",IF(G78="MO",IF(J78="hh",INDEX(MO_HH,MATCH(I78,MO_CAT,0)),M78*P_FACT_IPC),IF(G78="SUBPART",IFERROR(INDEX(APU_SUBP!$C$7:$C$40,MATCH(H78,APU_SUBP!$A$7:$A$40,0)),M78*P_FACT_IPC),M78*P_FACT_IPC))) -> 1.4921032 | Q78: =IF(J78="%mo",L78/100*SUMIFS($R$7:$R$782,$A$7:$A$782,A78),L78*P78) -> 0.16413135 | R78: =IF(G78="MO",L78*P78,0) -> 0
A79: CARCAVAS|03.02.02 | B79: CARCAVAS | C79: 03.02.02 | D79: SELECCION Y CORTE DE ESQUEJES PARA REVEGETACION | E79: und | F79: 1.17 | G79: MAT | H79: 02901100020006 | I79: BOLSA PLASTICA DE POLIETILENO DE 4"X7" | J79: und | L79: 1 | M79: 0.05 | N79: 0.05 | P79: =IF(J79="%mo","",IF(G79="MO",IF(J79="hh",INDEX(MO_HH,MATCH(I79,MO_CAT,0)),M79*P_FACT_IPC),IF(G79="SUBPART",IFERROR(INDEX(APU_SUBP!$C$7:$C$40,MATCH(H79,APU_SUBP!$A$7:$A$40,0)),M79*P_FACT_IPC),M79*P_FACT_IPC))) -> 0.064314792 | Q79: =IF(J79="%mo",L79/100*SUMIFS($R$7:$R$782,$A$7:$A$782,A79),L79*P79) -> 0.064314792 | R79: =IF(G79="MO",L79*P79,0) -> 0
A80: CARCAVAS|03.02.02 | B80: CARCAVAS | C80: 03.02.02 | D80: SELECCION Y CORTE DE ESQUEJES PARA REVEGETACION | E80: und | F80: 1.17 | G80: EQ | H80: 0301010006 | I80: HERRAMIENTAS MANUALES | J80: %mo | L80: 3 | M80: 0.93 | N80: 0.03 | P80: =IF(J80="%mo","",IF(G80="MO",IF(J80="hh",INDEX(MO_HH,MATCH(I80,MO_CAT,0)),M80*P_FACT_IPC),IF(G80="SUBPART",IFERROR(INDEX(APU_SUBP!$C$7:$C$40,MATCH(H80,APU_SUBP!$A$7:$A$40,0)),M80*P_FACT_IPC),M80*P_FACT_IPC))) | Q80: =IF(J80="%mo",L80/100*SUMIFS($R$7:$R$782,$A$7:$A$782,A80),L80*P80) -> 0.020823897 | R80: =IF(G80="MO",L80*P80,0) -> 0
A81: CARCAVAS|03.02.02 | B81: CARCAVAS | C81: 03.02.02 | D81: SELECCION Y CORTE DE ESQUEJES PARA REVEGETACION | E81: und | F81: 1.17 | G81: SUBPART | H81: 011002010124 | I81: TIERRA DE CULTIVO | J81: m3 | L81: 0.0012 | M81: 24.35 | N81: 0.03 | P81: =IF(J81="%mo","",IF(G81="MO",IF(J81="hh",INDEX(MO_HH,MATCH(I81,MO_CAT,0)),M81*P_FACT_IPC),IF(G81="SUBPART",IFERROR(INDEX(APU_SUBP!$C$7:$C$40,MATCH(H81,APU_SUBP!$A$7:$A$40,0)),M81*P_FACT_IPC),M81*P_FACT_IPC))) -> 30.561493 | Q81: =IF(J81="%mo",L81/100*SUMIFS($R$7:$R$782,$A$7:$A$782,A81),L81*P81) -> 0.036673792 | R81: =IF(G81="MO",L81*P81,0) -> 0
A82: CARCAVAS|03.02.03 | B82: CARCAVAS | C82: 03.02.03 | D82: TRANSPORTE DE ESQUEJES HASTA 15 KM | E82: und | F82: 0.16 | G82: MO | H82: 0101010004 | I82: OFICIAL | J82: hh | K82: 1 | L82: 0.0013 | M82: 18.56 | N82: 0.02 | O82: C | P82: =IF(J82="%mo","",IF(G82="MO",IF(J82="hh",INDEX(MO_HH,MATCH(I82,MO_CAT,0)),M82*P_FACT_IPC),IF(G82="SUBPART",IFERROR(INDEX(APU_SUBP!$C$7:$C$40,MATCH(H82,APU_SUBP!$A$7:$A$40,0)),M82*P_FACT_IPC),M82*P_FACT_IPC))) -> 13.825983 | Q82: =IF(J82="%mo",L82/100*SUMIFS($R$7:$R$782,$A$7:$A$782,A82),L82*P82) -> 0.017973778 | R82: =IF(G82="MO",L82*P82,0) -> 0.017973778
A83: CARCAVAS|03.02.03 | B83: CARCAVAS | C83: 03.02.03 | D83: TRANSPORTE DE ESQUEJES HASTA 15 KM | E83: und | F83: 0.16 | G83: MO | H83: 0101010005 | I83: PEON | J83: hh | K83: 2 | L83: 0.0027 | M83: 16.78 | N83: 0.05 | O83: NC | P83: =IF(J83="%mo","",IF(G83="MO",IF(J83="hh",INDEX(MO_HH,MATCH(I83,MO_CAT,0)),M83*P_FACT_IPC),IF(G83="SUBPART",IFERROR(INDEX(APU_SUBP!$C$7:$C$40,MATCH(H83,APU_SUBP!$A$7:$A$40,0)),M83*P_FACT_IPC),M83*P_FACT_IPC))) -> 12.5 | Q83: =IF(J83="%mo",L83/100*SUMIFS($R$7:$R$782,$A$7:$A$782,A83),L83*P83) -> 0.03375 | R83: =IF(G83="MO",L83*P83,0) -> 0.03375
A84: CARCAVAS|03.02.03 | B84: CARCAVAS | C84: 03.02.03 | D84: TRANSPORTE DE ESQUEJES HASTA 15 KM | E84: und | F84: 0.16 | G84: EQ | H84: 03012200070001 | I84: CAMION BARANDA (4TN) | J84: hm | K84: 1 | L84: 0.0013 | M84: 65.48 | N84: 0.09 | P84: =IF(J84="%mo","",IF(G84="MO",IF(J84="hh",INDEX(MO_HH,MATCH(I84,MO_CAT,0)),M84*P_FACT_IPC),IF(G84="SUBPART",IFERROR(INDEX(APU_SUBP!$C$7:$C$40,MATCH(H84,APU_SUBP!$A$7:$A$40,0)),M84*P_FACT_IPC),M84*P_FACT_IPC))) -> 84.226652 | Q84: =IF(J84="%mo",L84/100*SUMIFS($R$7:$R$782,$A$7:$A$782,A84),L84*P84) -> 0.10949465 | R84: =IF(G84="MO",L84*P84,0) -> 0
A85: CARCAVAS|03.02.04 | B85: CARCAVAS | C85: 03.02.04 | D85: TRATAMIENTO CON HORMONA ENRAIZADORA | E85: und | F85: 0.34 | G85: MO | H85: 0101010002 | I85: CAPATAZ | J85: hh | K85: 0.1 | L85: 0.0007 | M85: 25.81 | N85: 0.02 | O85: C | P85: =IF(J85="%mo","",IF(G85="MO",IF(J85="hh",INDEX(MO_HH,MATCH(I85,MO_CAT,0)),M85*P_FACT_IPC),IF(G85="SUBPART",IFERROR(INDEX(APU_SUBP!$C$7:$C$40,MATCH(H85,APU_SUBP!$A$7:$A$40,0)),M85*P_FACT_IPC),M85*P_FACT_IPC))) -> 19.226758 | Q85: =IF(J85="%mo",L85/100*SUMIFS($R$7:$R$782,$A$7:$A$782,A85),L85*P85) -> 0.013458731 | R85: =IF(G85="MO",L85*P85,0) -> 0.013458731
A86: CARCAVAS|03.02.04 | B86: CARCAVAS | C86: 03.02.04 | D86: TRATAMIENTO CON HORMONA ENRAIZADORA | E86: und | F86: 0.34 | G86: MO | H86: 0101010005 | I86: PEON | J86: hh | K86: 1 | L86: 0.0067 | M86: 16.78 | N86: 0.11 | O86: NC | P86: =IF(J86="%mo","",IF(G86="MO",IF(J86="hh",INDEX(MO_HH,MATCH(I86,MO_CAT,0)),M86*P_FACT_IPC),IF(G86="SUBPART",IFERROR(INDEX(APU_SUBP!$C$7:$C$40,MATCH(H86,APU_SUBP!$A$7:$A$40,0)),M86*P_FACT_IPC),M86*P_FACT_IPC))) -> 12.5 | Q86: =IF(J86="%mo",L86/100*SUMIFS($R$7:$R$782,$A$7:$A$782,A86),L86*P86) -> 0.08375 | R86: =IF(G86="MO",L86*P86,0) -> 0.08375
A87: CARCAVAS|03.02.04 | B87: CARCAVAS | C87: 03.02.04 | D87: TRATAMIENTO CON HORMONA ENRAIZADORA | E87: und | F87: 0.34 | G87: MAT | H87: 02070500010010 | I87: HORMONA ENRAIZADORA | J87: l | L87: 0.002 | M87: 107.04 | N87: 0.21 | P87: =IF(J87="%mo","",IF(G87="MO",IF(J87="hh",INDEX(MO_HH,MATCH(I87,MO_CAT,0)),M87*P_FACT_IPC),IF(G87="SUBPART",IFERROR(INDEX(APU_SUBP!$C$7:$C$40,MATCH(H87,APU_SUBP!$A$7:$A$40,0)),M87*P_FACT_IPC),M87*P_FACT_IPC))) -> 137.68511 | Q87: =IF(J87="%mo",L87/100*SUMIFS($R$7:$R$782,$A$7:$A$782,A87),L87*P87) -> 0.27537021 | R87: =IF(G87="MO",L87*P87,0) -> 0
A88: CARCAVAS|03.02.04 | B88: CARCAVAS | C88: 03.02.04 | D88: TRATAMIENTO CON HORMONA ENRAIZADORA | E88: und | F88: 0.34 | G88: EQ | H88: 0301010006 | I88: HERRAMIENTAS MANUALES | J88: %mo | L88: 3 | M88: 0.13 | N88: 0.0039 | P88: =IF(J88="%mo","",IF(G88="MO",IF(J88="hh",INDEX(MO_HH,MATCH(I88,MO_CAT,0)),M88*P_FACT_IPC),IF(G88="SUBPART",IFERROR(INDEX(APU_SUBP!$C$7:$C$40,MATCH(H88,APU_SUBP!$A$7:$A$40,0)),M88*P_FACT_IPC),M88*P_FACT_IPC))) | Q88: =IF(J88="%mo",L88/100*SUMIFS($R$7:$R$782,$A$7:$A$782,A88),L88*P88) -> 0.0029162619 | R88: =IF(G88="MO",L88*P88,0) -> 0
A89: CARCAVAS|03.02.05 | B89: CARCAVAS | C89: 03.02.05 | D89: RIEGO MANUAL EN CAMA DE ALMACIGO/REPIQUE | E89: m2 | F89: 0.81 | G89: MO | H89: 0101010002 | I89: CAPATAZ | J89: hh | K89: 0.1 | L89: 0.004 | M89: 25.81 | N89: 0.1 | O89: C | P89: =IF(J89="%mo","",IF(G89="MO",IF(J89="hh",INDEX(MO_HH,MATCH(I89,MO_CAT,0)),M89*P_FACT_IPC),IF(G89="SUBPART",IFERROR(INDEX(APU_SUBP!$C$7:$C$40,MATCH(H89,APU_SUBP!$A$7:$A$40,0)),M89*P_FACT_IPC),M89*P_FACT_IPC))) -> 19.226758 | Q89: =IF(J89="%mo",L89/100*SUMIFS($R$7:$R$782,$A$7:$A$782,A89),L89*P89) -> 0.076907032 | R89: =IF(G89="MO",L89*P89,0) -> 0.076907032
A90: CARCAVAS|03.02.05 | B90: CARCAVAS | C90: 03.02.05 | D90: RIEGO MANUAL EN CAMA DE ALMACIGO/REPIQUE | E90: m2 | F90: 0.81 | G90: MO | H90: 0101010005 | I90: PEON | J90: hh | K90: 1 | L90: 0.04 | M90: 16.78 | N90: 0.67 | O90: NC | P90: =IF(J90="%mo","",IF(G90="MO",IF(J90="hh",INDEX(MO_HH,MATCH(I90,MO_CAT,0)),M90*P_FACT_IPC),IF(G90="SUBPART",IFERROR(INDEX(APU_SUBP!$C$7:$C$40,MATCH(H90,APU_SUBP!$A$7:$A$40,0)),M90*P_FACT_IPC),M90*P_FACT_IPC))) -> 12.5 | Q90: =IF(J90="%mo",L90/100*SUMIFS($R$7:$R$782,$A$7:$A$782,A90),L90*P90) -> 0.5 | R90: =IF(G90="MO",L90*P90,0) -> 0.5
A91: CARCAVAS|03.02.05 | B91: CARCAVAS | C91: 03.02.05 | D91: RIEGO MANUAL EN CAMA DE ALMACIGO/REPIQUE | E91: m2 | F91: 0.81 | G91: EQ | H91: 0301010006 | I91: HERRAMIENTAS MANUALES | J91: %mo | L91: 3 | M91: 0.77 | N91: 0.02 | P91: =IF(J91="%mo","",IF(G91="MO",IF(J91="hh",INDEX(MO_HH,MATCH(I91,MO_CAT,0)),M91*P_FACT_IPC),IF(G91="SUBPART",IFERROR(INDEX(APU_SUBP!$C$7:$C$40,MATCH(H91,APU_SUBP!$A$7:$A$40,0)),M91*P_FACT_IPC),M91*P_FACT_IPC))) | Q91: =IF(J91="%mo",L91/100*SUMIFS($R$7:$R$782,$A$7:$A$782,A91),L91*P91) -> 0.017307211 | R91: =IF(G91="MO",L91*P91,0) -> 0
A92: CARCAVAS|03.02.05 | B92: CARCAVAS | C92: 03.02.05 | D92: RIEGO MANUAL EN CAMA DE ALMACIGO/REPIQUE | E92: m2 | F92: 0.81 | G92: SUBPART | H92: 011002010133 | I92: AGUA PUESTA EN OBRA HASTA 10 KM | J92: m3 | L92: 0.001 | M92: 21.15 | N92: 0.02 | P92: =IF(J92="%mo","",IF(G92="MO",IF(J92="hh",INDEX(MO_HH,MATCH(I92,MO_CAT,0)),M92*P_FACT_IPC),IF(G92="SUBPART",IFERROR(INDEX(APU_SUBP!$C$7:$C$40,MATCH(H92,APU_SUBP!$A$7:$A$40,0)),M92*P_FACT_IPC),M92*P_FACT_IPC))) -> 22.743882 | Q92: =IF(J92="%mo",L92/100*SUMIFS($R$7:$R$782,$A$7:$A$782,A92),L92*P92) -> 0.022743882 | R92: =IF(G92="MO",L92*P92,0) -> 0
A93: CARCAVAS|03.02.06 | B93: CARCAVAS | C93: 03.02.06 | D93: APLICACION Y SIEMBRA DE ESQUEJES | E93: und | F93: 1.48 | G93: MO | H93: 0101010002 | I93: CAPATAZ | J93: hh | K93: 1 | L93: 0.001 | M93: 25.81 | N93: 0.03 | O93: C | P93: =IF(J93="%mo","",IF(G93="MO",IF(J93="hh",INDEX(MO_HH,MATCH(I93,MO_CAT,0)),M93*P_FACT_IPC),IF(G93="SUBPART",IFERROR(INDEX(APU_SUBP!$C$7:$C$40,MATCH(H93,APU_SUBP!$A$7:$A$40,0)),M93*P_FACT_IPC),M93*P_FACT_IPC))) -> 19.226758 | Q93: =IF(J93="%mo",L93/100*SUMIFS($R$7:$R$782,$A$7:$A$782,A93),L93*P93) -> 0.019226758 | R93: =IF(G93="MO",L93*P93,0) -> 0.019226758
A94: CARCAVAS|03.02.06 | B94: CARCAVAS | C94: 03.02.06 | D94: APLICACION Y SIEMBRA DE ESQUEJES | E94: und | F94: 1.48 | G94: MO | H94: 0101010005 | I94: PEON | J94: hh | K94: 50 | L94: 0.05 | M94: 16.78 | N94: 0.84 | O94: NC | P94: =IF(J94="%mo","",IF(G94="MO",IF(J94="hh",INDEX(MO_HH,MATCH(I94,MO_CAT,0)),M94*P_FACT_IPC),IF(G94="SUBPART",IFERROR(INDEX(APU_SUBP!$C$7:$C$40,MATCH(H94,APU_SUBP!$A$7:$A$40,0)),M94*P_FACT_IPC),M94*P_FACT_IPC))) -> 12.5 | Q94: =IF(J94="%mo",L94/100*SUMIFS($R$7:$R$782,$A$7:$A$782,A94),L94*P94) -> 0.625 | R94: =IF(G94="MO",L94*P94,0) -> 0.625
A95: CARCAVAS|03.02.06 | B95: CARCAVAS | C95: 03.02.06 | D95: APLICACION Y SIEMBRA DE ESQUEJES | E95: und | F95: 1.48 | G95: MAT | H95: 02070500010007 | I95: GUANO DE ISLA | J95: kg | L95: 0.5 | M95: 1.16 | N95: 0.58 | P95: =IF(J95="%mo","",IF(G95="MO",IF(J95="hh",INDEX(MO_HH,MATCH(I95,MO_CAT,0)),M95*P_FACT_IPC),IF(G95="SUBPART",IFERROR(INDEX(APU_SUBP!$C$7:$C$40,MATCH(H95,APU_SUBP!$A$7:$A$40,0)),M95*P_FACT_IPC),M95*P_FACT_IPC))) -> 1.4921032 | Q95: =IF(J95="%mo",L95/100*SUMIFS($R$7:$R$782,$A$7:$A$782,A95),L95*P95) -> 0.74605159 | R95: =IF(G95="MO",L95*P95,0) -> 0
A96: CARCAVAS|03.02.06 | B96: CARCAVAS | C96: 03.02.06 | D96: APLICACION Y SIEMBRA DE ESQUEJES | E96: und | F96: 1.48 | G96: EQ | H96: 0301010006 | I96: HERRAMIENTAS MANUALES | J96: %mo | L96: 3 | M96: 0.87 | N96: 0.03 | P96: =IF(J96="%mo","",IF(G96="MO",IF(J96="hh",INDEX(MO_HH,MATCH(I96,MO_CAT,0)),M96*P_FACT_IPC),IF(G96="SUBPART",IFERROR(INDEX(APU_SUBP!$C$7:$C$40,MATCH(H96,APU_SUBP!$A$7:$A$40,0)),M96*P_FACT_IPC),M96*P_FACT_IPC))) | Q96: =IF(J96="%mo",L96/100*SUMIFS($R$7:$R$782,$A$7:$A$782,A96),L96*P96) -> 0.019326803 | R96: =IF(G96="MO",L96*P96,0) -> 0
A97: CARCAVAS|03.02.07 | B97: CARCAVAS | C97: 03.02.07 | D97: RIEGO MANUAL CON BALDE | E97: und | F97: 1.05 | G97: MO | H97: 0101010002 | I97: CAPATAZ | J97: hh | K97: 1 | L97: 0.001 | M97: 25.81 | N97: 0.03 | O97: C | P97: =IF(J97="%mo","",IF(G97="MO",IF(J97="hh",INDEX(MO_HH,MATCH(I97,MO_CAT,0)),M97*P_FACT_IPC),IF(G97="SUBPART",IFERROR(INDEX(APU_SUBP!$C$7:$C$40,MATCH(H97,APU_SUBP!$A$7:$A$40,0)),M97*P_FACT_IPC),M97*P_FACT_IPC))) -> 19.226758 | Q97: =IF(J97="%mo",L97/100*SUMIFS($R$7:$R$782,$A$7:$A$782,A97),L97*P97) -> 0.019226758 | R97: =IF(G97="MO",L97*P97,0) -> 0.019226758
A98: CARCAVAS|03.02.07 | B98: CARCAVAS | C98: 03.02.07 | D98: RIEGO MANUAL CON BALDE | E98: und | F98: 1.05 | G98: MO | H98: 0101010005 | I98: PEON | J98: hh | K98: 50 | L98: 0.05 | M98: 16.78 | N98: 0.84 | O98: NC | P98: =IF(J98="%mo","",IF(G98="MO",IF(J98="hh",INDEX(MO_HH,MATCH(I98,MO_CAT,0)),M98*P_FACT_IPC),IF(G98="SUBPART",IFERROR(INDEX(APU_SUBP!$C$7:$C$40,MATCH(H98,APU_SUBP!$A$7:$A$40,0)),M98*P_FACT_IPC),M98*P_FACT_IPC))) -> 12.5 | Q98: =IF(J98="%mo",L98/100*SUMIFS($R$7:$R$782,$A$7:$A$782,A98),L98*P98) -> 0.625 | R98: =IF(G98="MO",L98*P98,0) -> 0.625
A99: CARCAVAS|03.02.07 | B99: CARCAVAS | C99: 03.02.07 | D99: RIEGO MANUAL CON BALDE | E99: und | F99: 1.05 | G99: MAT | H99: 0254030002 | I99: MANGUERA PARA AGUA 2.5" | J99: m | L99: 0.01 | M99: 0.7 | N99: 0.01 | P99: =IF(J99="%mo","",IF(G99="MO",IF(J99="hh",INDEX(MO_HH,MATCH(I99,MO_CAT,0)),M99*P_FACT_IPC),IF(G99="SUBPART",IFERROR(INDEX(APU_SUBP!$C$7:$C$40,MATCH(H99,APU_SUBP!$A$7:$A$40,0)),M99*P_FACT_IPC),M99*P_FACT_IPC))) -> 0.90040709 | Q99: =IF(J99="%mo",L99/100*SUMIFS($R$7:$R$782,$A$7:$A$782,A99),L99*P99) -> 0.0090040709 | R99: =IF(G99="MO",L99*P99,0) -> 0
A100: CARCAVAS|03.02.07 | B100: CARCAVAS | C100: 03.02.07 | D100: RIEGO MANUAL CON BALDE | E100: und | F100: 1.05 | G100: MAT | H100: 02903200090008 | I100: BALDE PLASTICO PARA AGUA SIN TAPA 5 gl | J100: pza | L100: 0.0025 | M100: 14.5 | N100: 0.04 | P100: =IF(J100="%mo","",IF(G100="MO",IF(J100="hh",INDEX(MO_HH,MATCH(I100,MO_CAT,0)),M100*P_FACT_IPC),IF(G100="SUBPART",IFERROR(INDEX(APU_SUBP!$C$7:$C$40,MATCH(H100,APU_SUBP!$A$7:$A$40,0)),M100*P_FACT_IPC),M100*P_FACT_IPC))) -> 18.65129 | Q100: =IF(J100="%mo",L100/100*SUMIFS($R$7:$R$782,$A$7:$A$782,A100),L100*P100) -> 0.046628224 | R100: =IF(G100="MO",L100*P100,0) -> 0
...

Sheet APU_SUBP
A1: AUTORIDAD NACIONAL DE INFRAESTRUCTURA - ANIN
A2: DIRECCIÓN DE INTERVENCIONES MULTISECTORIALES Y DE EMERGENCIA - DIME
A3: SUBDIRECCIÓN DE ESTUDIOS DE INVERSIÓN
A4: PROYECTO IN PIURA – CUI 2669244 · Subpartidas de catálogo (lookup por código)
A5: Una fila por código de subpartida; el CU actualizado se toma de la primera definición encontrada en APU_BASE.
A6: Código | B6: Subpartida | C6: CU actualizado | D6: CU 2020 ANIN | E6: Clave usada | F6: Und
A7: 011002010124 | B7: TIERRA DE CULTIVO | C7: =SUMIFS(APU_BASE!$Q$7:$Q$782,APU_BASE!$A$7:$A$782,E7) -> 30.561493 | D7: 24.35 | E7: CARCAVAS_SUB|011002010124-1003001-01 | F7: m3
A8: 011002010133 | B8: AGUA PUESTA EN OBRA HASTA 10 KM | C8: =SUMIFS(APU_BASE!$Q$7:$Q$782,APU_BASE!$A$7:$A$782,E8) -> 22.743882 | D8: 21.15 | E8: CARCAVAS_SUB|011002010133-1003001-01 | F8: m3
A9: 011002010134 | B9: ARENA PUESTA EN OBRA | C9: =SUMIFS(APU_BASE!$Q$7:$Q$782,APU_BASE!$A$7:$A$782,E9) -> 69.142511 | D9: 56.6 | E9: CARCAVAS_SUB|011002010134-1003001-01 | F9: m3
A10: 011002010135 | B10: EXTRACCION Y APILAMIENTO DE MATERIAL GRAVO ARENOSO ARCILLOSO | C10: =SUMIFS(APU_BASE!$Q$7:$Q$782,APU_BASE!$A$7:$A$782,E10) -> 5.2439637 | D10: 4.33 | E10: CARCAVAS_SUB|011002010135-1003001-01 | F10: m3
A11: 011002010139 | B11: CARGUIO Y TRANSPORTE DE MATERIAL ARENOSO HASTA 40 KM | C11: =SUMIFS(APU_BASE!$Q$7:$Q$782,APU_BASE!$A$7:$A$782,E11) -> 63.898548 | D11: 52.27 | E11: CARCAVAS_SUB|011002010139-1003001-01 | F11: m3
A12: 011002010153 | B12: EXTRACCION Y APILAMIENTO DE TIERRA DE CULTIVO | C12: =SUMIFS(APU_BASE!$Q$7:$Q$782,APU_BASE!$A$7:$A$782,E12) -> 2.6155691 | D12: 2.08 | E12: CARCAVAS_SUB|011002010153-1003001-01 | F12: m3
A13: 011002010154 | B13: CARGUIO Y TRANSPORTE DE TIERRA DE CULTIVO HASTA 10 KM | C13: =SUMIFS(APU_BASE!$Q$7:$Q$782,APU_BASE!$A$7:$A$782,E13) -> 27.945924 | D13: 22.27 | E13: CARCAVAS_SUB|011002010154-1003001-01 | F13: m3
A14: 011002010193 | B14: ARENA ZARANDEADA | C14: =SUMIFS(APU_BASE!$Q$7:$Q$782,APU_BASE!$A$7:$A$782,E14) -> 64.499739 | D14: 86.3 | E14: CARCAVAS_SUB|011002010193-1003001-01 | F14: m3
A15: 011002010210 | B15: PIEDRA CANTEADA PUESTA EN OBRA DIA. MAX. 12" | C15: =SUMIFS(APU_BASE!$Q$7:$Q$782,APU_BASE!$A$7:$A$782,E15) -> 86.441692 | D15: 113.54 | E15: CARCAVAS_SUB|011002010210-1003001-01 | F15: m3
A16: 011002010211 | B16: RECOLECCION Y ACOPIO MANUAL DE PIEDRA DE 12" | C16: =SUMIFS(APU_BASE!$Q$7:$Q$782,APU_BASE!$A$7:$A$782,E16) -> 43.478522 | D16: 58.37 | E16: CARCAVAS_SUB|011002010211-1003001-01 | F16: m3
A17: 011002010212 | B17: CARGUIO Y TRANSPORTE DE PIEDRA DIA. MAX. 12" HASTA 5 KM | C17: =SUMIFS(APU_BASE!$Q$7:$Q$782,APU_BASE!$A$7:$A$782,E17) -> 7.2123485 | D17: 7.18 | E17: CARCAVAS_SUB|011002010212-1003001-01 | F17: m3
A18: 011002010216 | B18: CANTEO MANUAL DE PIEDRA DIA. MAX. 12" | C18: =SUMIFS(APU_BASE!$Q$7:$Q$782,APU_BASE!$A$7:$A$782,E18) -> 33.576895 | D18: 45.07 | E18: CARCAVAS_SUB|011002010216-1003001-01 | F18: m3
... A28: 011002010220 | B28: PIEDRA PUESTA EN OBRA, DIA. MAX 12" | C28: =SUMIFS(APU_BASE!$Q$7:$Q$782,APU_BASE!$A$7:$A$782,E28) -> 52.864797 | D28: 68.47 | E28: REFORESTACION_SUB|011002010220-1003001-01 | F28: m3

Sheet PARTIDAS
A1: AUTORIDAD NACIONAL DE INFRAESTRUCTURA - ANIN
A2: DIRECCIÓN DE INTERVENCIONES MULTISECTORIALES Y DE EMERGENCIA - DIME
A3: SUBDIRECCIÓN DE ESTUDIOS DE INVERSIÓN
A4: PROYECTO IN PIURA – CUI 2669244 · Costos unitarios por partida (2020 vs. actualizado) y desagregación para precios sociales
A5: CU actualizado = Σ parcial actualizado de APU_BASE. MO NC = peón; MO C = capataz, operario, oficial e ingeniería.
A6: Clave | B6: Tipo | C6: Item | D6: Partida | E6: Und | F6: CU 2020 ANIN | G6: CU 2020 recalculado (control) | H6: CU actualizado | I6: MO no calificada | J6: MO calificada | K6: Bienes, equipos y servicios | L6: Variación vs 2020
A7: CARCAVAS|01.01 | B7: CARCAVAS | C7: 01.01 | D7: MOVILIZACION Y DESMOVILIZACION PARA CARCAVAS | E7: m3 | F7: 60135.17 | G7: =SUMIFS(APU_BASE!$N$7:$N$782,APU_BASE!$A$7:$A$782,A7) -> 60135.17 | H7: =SUMIFS(APU_BASE!$Q$7:$Q$782,APU_BASE!$A$7:$A$782,A7) -> 77351.619 | I7: =SUMIFS(APU_BASE!$Q$7:$Q$782,APU_BASE!$A$7:$A$782,A7,APU_BASE!$O$7:$O$782,"NC") -> 0 | J7: =SUMIFS(APU_BASE!$Q$7:$Q$782,APU_BASE!$A$7:$A$782,A7,APU_BASE!$O$7:$O$782,"C") -> 0 | K7: =H7-I7-J7 -> 77351.619 | L7: =IF(F7=0,0,H7/F7-1) -> 0.28629584
A8: CARCAVAS|01.02 | B8: CARCAVAS | C8: 01.02 | D8: CONSTRUCCION DE TROCHA CARROZABLE DE ACCESO | E8: km | F8: 27992.8 | G8: =SUMIFS(APU_BASE!$N$7:$N$782,APU_BASE!$A$7:$A$782,A8) -> 27992.8 | H8: =SUMIFS(APU_BASE!$Q$7:$Q$782,APU_BASE!$A$7:$A$782,A8) -> 33977.653 | I8: =SUMIFS(APU_BASE!$Q$7:$Q$782,APU_BASE!$A$7:$A$782,A8,APU_BASE!$O$7:$O$782,"NC") -> 1600 | J8: =SUMIFS(APU_BASE!$Q$7:$Q$782,APU_BASE!$A$7:$A$782,A8,APU_BASE!$O$7:$O$782,"C") -> 1192.4911 | K8: =H8-I8-J8 -> 31185.162 | L8: =IF(F8=0,0,H8/F8-1) -> 0.21379974
A9: CARCAVAS|01.03 | B9: CARCAVAS | C9: 01.03 | D9: MEJORAMIENTO DE TROCHA CARROZABLE DE ACCESO | E9: km | F9: 4665.44 | G9: =SUMIFS(APU_BASE!$N$7:$N$782,APU_BASE!$A$7:$A$782,A9) -> 4665.44 | H9: =SUMIFS(APU_BASE!$Q$7:$Q$782,APU_BASE!$A$7:$A$782,A9) -> 5662.9213 | I9: =SUMIFS(APU_BASE!$Q$7:$Q$782,APU_BASE!$A$7:$A$782,A9,APU_BASE!$O$7:$O$782,"NC") -> 266.66625 | J9: =SUMIFS(APU_BASE!$Q$7:$Q$782,APU_BASE!$A$7:$A$782,A9,APU_BASE!$O$7:$O$782,"C") -> 198.74961 | K9: =H9-I9-J9 -> 5197.5055 | L9: =IF(F9=0,0,H9/F9-1) -> 0.2138022
A10: CARCAVAS|01.04 | B10: CARCAVAS | C10: 01.04 | D10: TRAZO, NIVELACION Y REPLANTEO POR KILOMETRO | E10: km | F10: 583.87 | G10: =SUMIFS(APU_BASE!$N$7:$N$782,APU_BASE!$A$7:$A$782,A10) -> 583.87 | H10: =SUMIFS(APU_BASE!$Q$7:$Q$782,APU_BASE!$A$7:$A$782,A10) -> 493.52749 | I10: =SUMIFS(APU_BASE!$Q$7:$Q$782,APU_BASE!$A$7:$A$782,A10,APU_BASE!$O$7:$O$782,"NC") -> 187.5 | J10: =SUMIFS(APU_BASE!$Q$7:$Q$782,APU_BASE!$A$7:$A$782,A10,APU_BASE!$O$7:$O$782,"C") -> 156.51073 | K10: =H10-I10-J10 -> 149.51676 | L10: =IF(F10=0,0,H10/F10-1) -> -0.15473052
A11: CARCAVAS|01.05 | B11: CARCAVAS | C11: 01.05 | D11: LIMPIEZA MANUAL DE TERRENO | E11: ha | F11: 285.04 | G11: =SUMIFS(APU_BASE!$N$7:$N$782,APU_BASE!$A$7:$A$782,A11) -> 285.04 | H11: =SUMIFS(APU_BASE!$Q$7:$Q$782,APU_BASE!$A$7:$A$782,A11) -> 212.33714 | I11: =SUMIFS(APU_BASE!$Q$7:$Q$782,APU_BASE!$A$7:$A$782,A11,APU_BASE!$O$7:$O$782,"NC") -> 200 | J11: =SUMIFS(APU_BASE!$Q$7:$Q$782,APU_BASE!$A$7:$A$782,A11,APU_BASE!$O$7:$O$782,"C") -> 6.1525626 | K11: =H11-I11-J11 -> 6.1845769 | L11: =IF(F11=0,0,H11/F11-1) -> -0.25506196
A12: CARCAVAS|01.06 | B12: CARCAVAS | C12: 01.06 | D12: SENSIBILIZACION A LA POBLACION EN CARCAVAS | E12: und | F12: 6000 | G12: =SUMIFS(APU_BASE!$N$7:$N$782,APU_BASE!$A$7:$A$782,A12) -> 6000 | H12: =SUMIFS(APU_BASE!$Q$7:$Q$782,APU_BASE!$A$7:$A$782,A12) -> 7717.775 | I12: =SUMIFS(APU_BASE!$Q$7:$Q$782,APU_BASE!$A$7:$A$782,A12,APU_BASE!$O$7:$O$782,"NC") -> 0 | J12: =SUMIFS(APU_BASE!$Q$7:$Q$782,APU_BASE!$A$7:$A$782,A12,APU_BASE!$O$7:$O$782,"C") -> 7717.775 | K12: =H12-I12-J12 -> 0 | L12: =IF(F12=0,0,H12/F12-1) -> 0.28629584
A13: CARCAVAS|02.01 | B13: CARCAVAS | C13: 02.01 | D13: CAMPAMENTO PROVISIONAL DE OBRA Y ALMACENES | E13: m2 | F13: 202.06 | G13: =SUMIFS(APU_BASE!$N$7:$N$782,APU_BASE!$A$7:$A$782,A13) -> 202.06 | H13: =SUMIFS(APU_BASE!$Q$7:$Q$782,APU_BASE!$A$7:$A$782,A13) -> 259.90894 | I13: =SUMIFS(APU_BASE!$Q$7:$Q$782,APU_BASE!$A$7:$A$782,A13,APU_BASE!$O$7:$O$782,"NC") -> 0 | J13: =SUMIFS(APU_BASE!$Q$7:$Q$782,APU_BASE!$A$7:$A$782,A13,APU_BASE!$O$7:$O$782,"C") -> 0 | K13: =H13-I13-J13 -> 259.90894 | L13: =IF(F13=0,0,H13/F13-1) -> 0.28629584
A14: CARCAVAS|02.02 | B14: CARCAVAS | C14: 02.02 | D14: CARTEL DE OBRA 4.80 X 3.60 M CON GIGANTOGRAFIA | E14: und | F14: 4445.55 | G14: =SUMIFS(APU_BASE!$N$7:$N$782,APU_BASE!$A$7:$A$782,A14) -> 4445.55 | H14: =SUMIFS(APU_BASE!$Q$7:$Q$782,APU_BASE!$A$7:$A$782,A14) -> 5255.3328 | I14: =SUMIFS(APU_BASE!$Q$7:$Q$782,APU_BASE!$A$7:$A$782,A14,APU_BASE!$O$7:$O$782,"NC") -> 400 | J14: =SUMIFS(APU_BASE!$Q$7:$Q$782,APU_BASE!$A$7:$A$782,A14,APU_BASE!$O$7:$O$782,"C") -> 216.71633 | K14: =H14-I14-J14 -> 4638.6165 | L14: =IF(F14=0,0,H14/F14-1) -> 0.18215583
A15: CARCAVAS|03.01.01 | B15: CARCAVAS | C15: 03.01.01 | D15: PEINADO DE CARCAVAS | E15: m2 | F15: 7.45 | G15: =SUMIFS(APU_BASE!$N$7:$N$782,APU_BASE!$A$7:$A$782,A15) -> 7.45 | H15: =SUMIFS(APU_BASE!$Q$7:$Q$782,APU_BASE!$A$7:$A$782,A15) -> 5.5460712 | I15: =SUMIFS(APU_BASE!$Q$7:$Q$782,APU_BASE!$A$7:$A$782,A15,APU_BASE!$O$7:$O$782,"NC") -> 5 | J15: =SUMIFS(APU_BASE!$Q$7:$Q$782,APU_BASE!$A$7:$A$782,A15,APU_BASE!$O$7:$O$782,"C") -> 0.38453516 | K15: =H15-I15-J15 -> 0.16153605 | L15: =IF(F15=0,0,H15/F15-1) -> -0.25556091
A16: CARCAVAS|03.01.02 | B16: CARCAVAS | C16: 03.01.02 | D16: EXCAVACION MANUAL EN MATERIAL SUELTO | E16: m3 | F16: 63.82 | G16: =SUMIFS(APU_BASE!$N$7:$N$782,APU_BASE!$A$7:$A$782,A16) -> 63.82 | H16: =SUMIFS(APU_BASE!$Q$7:$Q$782,APU_BASE!$A$7:$A$782,A16) -> 47.537139 | I16: =SUMIFS(APU_BASE!$Q$7:$Q$782,APU_BASE!$A$7:$A$782,A16,APU_BASE!$O$7:$O$782,"NC") -> 40 | J16: =SUMIFS(APU_BASE!$Q$7:$Q$782,APU_BASE!$A$7:$A$782,A16,APU_BASE!$O$7:$O$782,"C") -> 6.1525626 | K16: =H16-I16-J16 -> 1.3845769 | L16: =IF(F16=0,0,H16/F16-1) -> -0.25513727
A17: CARCAVAS|03.01.03 | B17: CARCAVAS | C17: 03.01.03 | D17: NIVELACION Y COMPACTACION MANUAL DE TERRENO | E17: m2 | F17: 3.19 | G17: =SUMIFS(APU_BASE!$N$7:$N$782,APU_BASE!$A$7:$A$782,A17) -> 3.19 | H17: =SUMIFS(APU_BASE!$Q$7:$Q$782,APU_BASE!$A$7:$A$782,A17) -> 3.0481022 | I17: =SUMIFS(APU_BASE!$Q$7:$Q$782,APU_BASE!$A$7:$A$782,A17,APU_BASE!$O$7:$O$782,"NC") -> 0.8 | J17: =SUMIFS(APU_BASE!$Q$7:$Q$782,APU_BASE!$A$7:$A$782,A17,APU_BASE!$O$7:$O$782,"C") -> 0.62076281 | K17: =H17-I17-J17 -> 1.6273394 | L17: =IF(F17=0,0,H17/F17-1) -> -0.044482077
A18: CARCAVAS|03.01.04 | B18: CARCAVAS | C18: 03.01.04 | D18: COLOCACION DE PIEDRA CANTEADA | E18: m3 | F18: 166 | G18: =SUMIFS(APU_BASE!$N$7:$N$782,APU_BASE!$A$7:$A$782,A18) -> 166 | H18: =SUMIFS(APU_BASE!$Q$7:$Q$782,APU_BASE!$A$7:$A$782,A18) -> 125.61451 | I18: =SUMIFS(APU_BASE!$Q$7:$Q$782,APU_BASE!$A$7:$A$782,A18,APU_BASE!$O$7:$O$782,"NC") -> 25 | J18: =SUMIFS(APU_BASE!$Q$7:$Q$782,APU_BASE!$A$7:$A$782,A18,APU_BASE!$O$7:$O$782,"C") -> 8.8356675 | K18: =H18-I18-J18 -> 91.778846 | L18: =IF(F18=0,0,H18/F18-1) -> -0.24328606
... A132: ZANJAS|03.03.07 | B132: ZANJAS | C132: 03.03.07 | D132: RIEGO MANUAL CON BALDE | E132: und | F132: 1.05 | G132: =SUMIFS(APU_BASE!$N$7:$N$782,APU_BASE!$A$7:$A$782,A132) -> 1.05 | H132: =SUMIFS(APU_BASE!$Q$7:$Q$782,APU_BASE!$A$7:$A$782,A132) -> 0.83367041 | I132: =SUMIFS(APU_BASE!$Q$7:$Q$782,APU_BASE!$A$7:$A$782,A132,APU_BASE!$O$7:$O$782,"NC") -> 0.625 | J132: =SUMIFS(APU_BASE!$Q$7:$Q$782,APU_BASE!$A$7:$A$782,A132,APU_BASE!$O$7:$O$782,"C") -> 0.019226758 | K132: =H132-I132-J132 -> 0.18944365 | L132: =IF(F132=0,0,H132/F132-1) -> -0.20602819

Sheet CU_COMP
A1: AUTORIDAD NACIONAL DE INFRAESTRUCTURA - ANIN
A2: DIRECCIÓN DE INTERVENCIONES MULTISECTORIALES Y DE EMERGENCIA - DIME
A3: SUBDIRECCIÓN DE ESTUDIOS DE INVERSIÓN
A4: PROYECTO IN PIURA – CUI 2669244 · Costos unitarios compuestos del paquete tecnológico
A5: Coeficientes = metrado ANIN ÷ meta base ANIN (trazables). Costo = coeficiente × CU actualizado de PARTIDAS.
A6: Grupo | B6: Clave partida | C6: Descripción | D6: Metrado ANIN | E6: Base ANIN | F6: Coeficiente por unidad | G6: CU actualizado | H6: Costo por unidad | I6: MO no calificada | J6: MO calificada | K6: Bienes y servicios
A7: PLANTON | B7: REFORESTACION|02.02.01 | C7: NIVELACION Y COMPACTACION MANUAL DE TERRENO | D7: 2500 | E7: 650000 | F7: =D7/E7 -> 0.0038461538 | G7: =INDEX(PARTIDAS!$H$7:$H$132,MATCH(B7,PARTIDAS!$A$7:$A$132,0)) -> 3.0481022 | H7: =F7*G7 -> 0.01172347 | I7: =F7*INDEX(PARTIDAS!$I$7:$I$132,MATCH(B7,PARTIDAS!$A$7:$A$132,0)) -> 0.0030769231 | J7: =F7*INDEX(PARTIDAS!$J$7:$J$132,MATCH(B7,PARTIDAS!$A$7:$A$132,0)) -> 0.0023875493 | K7: =H7-I7-J7 -> 0.0062589975
A8: PLANTON | B8: REFORESTACION|02.02.02 | C8: CERCO PERIMETRICO DE ALAMBRE DE PUAS | D8: 200 | E8: 650000 | F8: =D8/E8 -> 0.00030769231 | G8: =INDEX(PARTIDAS!$H$7:$H$132,MATCH(B8,PARTIDAS!$A$7:$A$132,0)) -> 21.969803 | H8: =F8*G8 -> 0.0067599393 | I8: =F8*INDEX(PARTIDAS!$I$7:$I$132,MATCH(B8,PARTIDAS!$A$7:$A$132,0)) -> 0 | J8: =F8*INDEX(PARTIDAS!$J$7:$J$132,MATCH(B8,PARTIDAS!$A$7:$A$132,0)) -> 0 | K8: =H8-I8-J8 -> 0.0067599393
A9: PLANTON | B9: REFORESTACION|02.02.03 | C9: POSTE ROLLIZO DE 3"x3.00 M. PARA COBERTURA INTERIOR | D9: 144 | E9: 650000 | F9: =D9/E9 -> 0.00022153846 | G9: =INDEX(PARTIDAS!$H$7:$H$132,MATCH(B9,PARTIDAS!$A$7:$A$132,0)) -> 19.616442 | H9: =F9*G9 -> 0.0043457964 | I9: =F9*INDEX(PARTIDAS!$I$7:$I$132,MATCH(B9,PARTIDAS!$A$7:$A$132,0)) -> 0.0022153846 | J9: =F9*INDEX(PARTIDAS!$J$7:$J$132,MATCH(B9,PARTIDAS!$A$7:$A$132,0)) -> 0.00012251948 | K9: =H9-I9-J9 -> 0.0020078923
A10: PLANTON | B10: REFORESTACION|02.02.04 | C10: MALLA RASHEL A 50% DE SOMBRA | D10: 2980 | E10: 650000 | F10: =D10/E10 -> 0.0045846154 | G10: =INDEX(PARTIDAS!$H$7:$H$132,MATCH(B10,PARTIDAS!$A$7:$A$132,0)) -> 1.1090006 | H10: =F10*G10 -> 0.0050843412 | I10: =F10*INDEX(PARTIDAS!$I$7:$I$132,MATCH(B10,PARTIDAS!$A$7:$A$132,0)) -> 0.0030545 | J10: =F10*INDEX(PARTIDAS!$J$7:$J$132,MATCH(B10,PARTIDAS!$A$7:$A$132,0)) -> 0.0001711444 | K10: =H10-I10-J10 -> 0.0018586968
A11: PLANTON | B11: REFORESTACION|02.02.05 | C11: ALAMBRE N°08 PARA SOSTENIMIENTO DE MALLA RASHEL | D11: 1540 | E11: 650000 | F11: =D11/E11 -> 0.0023692308 | G11: =INDEX(PARTIDAS!$H$7:$H$132,MATCH(B11,PARTIDAS!$A$7:$A$132,0)) -> 3.0768313 | H11: =F11*G11 -> 0.0072897233 | I11: =F11*INDEX(PARTIDAS!$I$7:$I$132,MATCH(B11,PARTIDAS!$A$7:$A$132,0)) -> 0.0011846154 | J11: =F11*INDEX(PARTIDAS!$J$7:$J$132,MATCH(B11,PARTIDAS!$A$7:$A$132,0)) -> 0.00013102778 | K11: =H11-I11-J11 -> 0.0059740801
A12: PLANTON | B12: REFORESTACION|02.02.06 | C12: ALAMBRE DE PUA GALVANIZADO | D12: 220 | E12: 650000 | F12: =D12/E12 -> 0.00033846154 | G12: =INDEX(PARTIDAS!$H$7:$H$132,MATCH(B12,PARTIDAS!$A$7:$A$132,0)) -> 1.5008287 | H12: =F12*G12 -> 0.0005079728 | I12: =F12*INDEX(PARTIDAS!$I$7:$I$132,MATCH(B12,PARTIDAS!$A$7:$A$132,0)) -> 0.00033846154 | J12: =F12*INDEX(PARTIDAS!$J$7:$J$132,MATCH(B12,PARTIDAS!$A$7:$A$132,0)) -> 1.8718254e-05 | K12: =H12-I12-J12 -> 0.00015079301
A13: PLANTON | B13: REFORESTACION|02.02.07 | C13: PUERTA DE INGRESO DE VIVERO | D13: 1 | E13: 650000 | F13: =D13/E13 -> 1.5384615e-06 | G13: =INDEX(PARTIDAS!$H$7:$H$132,MATCH(B13,PARTIDAS!$A$7:$A$132,0)) -> 155.44006 | H13: =F13*G13 -> 0.00023913856 | I13: =F13*INDEX(PARTIDAS!$I$7:$I$132,MATCH(B13,PARTIDAS!$A$7:$A$132,0)) -> 7.6923077e-05 | J13: =F13*INDEX(PARTIDAS!$J$7:$J$132,MATCH(B13,PARTIDAS!$A$7:$A$132,0)) -> 4.2541487e-05 | K13: =H13-I13-J13 -> 0.000119674
A14: PLANTON | B14: REFORESTACION|02.02.08 | C14: CONSTRUCCION DE CAMAS DE REPIQUE | D14: 1687.5 | E14: 650000 | F14: =D14/E14 -> 0.0025961538 | G14: =INDEX(PARTIDAS!$H$7:$H$132,MATCH(B14,PARTIDAS!$A$7:$A$132,0)) -> 21.008906 | H14: =F14*G14 -> 0.054542351 | I14: =F14*INDEX(PARTIDAS!$I$7:$I$132,MATCH(B14,PARTIDAS!$A$7:$A$132,0)) -> 0.010384615 | J14: =F14*INDEX(PARTIDAS!$J$7:$J$132,MATCH(B14,PARTIDAS!$A$7:$A$132,0)) -> 0.0011486202 | K14: =H14-I14-J14 -> 0.043009115
A15: PLANTON | B15: REFORESTACION|02.02.09 | C15: INSTALACIONES SANITARIAS PARA VIVEROS | D15: 2500 | E15: 650000 | F15: =D15/E15 -> 0.0038461538 | G15: =INDEX(PARTIDAS!$H$7:$H$132,MATCH(B15,PARTIDAS!$A$7:$A$132,0)) -> 14.149254 | H15: =F15*G15 -> 0.054420209 | I15: =F15*INDEX(PARTIDAS!$I$7:$I$132,MATCH(B15,PARTIDAS!$A$7:$A$132,0)) -> 0 | J15: =F15*INDEX(PARTIDAS!$J$7:$J$132,MATCH(B15,PARTIDAS!$A$7:$A$132,0)) -> 0 | K15: =H15-I15-J15 -> 0.054420209
A16: PLANTON | B16: REFORESTACION|02.02.10 | C16: AREA DE CARGA Y DESCARGA | D16: 50 | E16: 650000 | F16: =D16/E16 -> 7.6923077e-05 | G16: =INDEX(PARTIDAS!$H$7:$H$132,MATCH(B16,PARTIDAS!$A$7:$A$132,0)) -> 10.782309 | H16: =F16*G16 -> 0.00082940842 | I16: =F16*INDEX(PARTIDAS!$I$7:$I$132,MATCH(B16,PARTIDAS!$A$7:$A$132,0)) -> 0.00038461538 | J16: =F16*INDEX(PARTIDAS!$J$7:$J$132,MATCH(B16,PARTIDAS!$A$7:$A$132,0)) -> 0.00013593335 | K16: =H16-I16-J16 -> 0.00030885969
A17: PLANTON | B17: REFORESTACION|02.03.01 | C17: CONSTRUCCION DE CAMAS DE ALMACIGO | D17: 360 | E17: 650000 | F17: =D17/E17 -> 0.00055384615 | G17: =INDEX(PARTIDAS!$H$7:$H$132,MATCH(B17,PARTIDAS!$A$7:$A$132,0)) -> 70.904974 | H17: =F17*G17 -> 0.039270447 | I17: =F17*INDEX(PARTIDAS!$I$7:$I$132,MATCH(B17,PARTIDAS!$A$7:$A$132,0)) -> 0.0018463846 | J17: =F17*INDEX(PARTIDAS!$J$7:$J$132,MATCH(B17,PARTIDAS!$A$7:$A$132,0)) -> 0.0010207404 | K17: =H17-I17-J17 -> 0.036403322
A18: PLANTON | B18: REFORESTACION|02.03.02 | C18: TINGLADO DE CARRIZO | D18: 360 | E18: 650000 | F18: =D18/E18 -> 0.00055384615 | G18: =INDEX(PARTIDAS!$H$7:$H$132,MATCH(B18,PARTIDAS!$A$7:$A$132,0)) -> 19.463554 | H18: =F18*G18 -> 0.010779815 | I18: =F18*INDEX(PARTIDAS!$I$7:$I$132,MATCH(B18,PARTIDAS!$A$7:$A$132,0)) -> 0.0069230769 | J18: =F18*INDEX(PARTIDAS!$J$7:$J$132,MATCH(B18,PARTIDAS!$A$7:$A$132,0)) -> 0.00076574677 | K18: =H18-I18-J18 -> 0.0030909909
... A35: PLANTA | B35: REFORESTACION|04.02.05 | C35: TRANSPORTE DE PERSONAL EN CAMION BARANDA HASTA 16 KM | D35: 5300 | E35: 650000 | F35: =D35/E35 -> 0.0081538462 | G35: =INDEX(PARTIDAS!$H$7:$H$132,MATCH(B35,PARTIDAS!$A$7:$A$132,0)) -> 2.6180054 | H35: =F35*G35 -> 0.021346813 | I35: =F35*INDEX(PARTIDAS!$I$7:$I$132,MATCH(B35,PARTIDAS!$A$7:$A$132,0)) -> 0 | J35: =F35*INDEX(PARTIDAS!$J$7:$J$132,MATCH(B35,PARTIDAS!$A$7:$A$132,0)) -> 0.0030100229 | K35: =H35-I35-J35 -> 0.01833679
A36: PLANTA | B36: REFORESTACION|04.02.02 | C36: RIEGO MANUAL CON BALDE | D36: =P_RIEGOS -> 3 | E36: 1 | F36: =D36/E36 -> 3 | G36: =INDEX(PARTIDAS!$H$7:$H$132,MATCH(B36,PARTIDAS!$A$7:$A$132,0)) -> 0.83367041 | H36: =F36*G36 -> 2.5010112 | I36: =F36*INDEX(PARTIDAS!$I$7:$I$132,MATCH(B36,PARTIDAS!$A$7:$A$132,0)) -> 1.875 | J36: =F36*INDEX(PARTIDAS!$J$7:$J$132,MATCH(B36,PARTIDAS!$A$7:$A$132,0)) -> 0.057680274 | K36: =H36-I36-J36 -> 0.56833094
A37: PLANTA | B37: REFORESTACION|04.02.04 | C37: RECALCE DE PLANTONES DE ALGARROBO | D37: =P_RECALCE -> 0.1 | E37: 1 | F37: =D37/E37 -> 0.1 | G37: =INDEX(PARTIDAS!$H$7:$H$132,MATCH(B37,PARTIDAS!$A$7:$A$132,0)) -> 5.5860472 | H37: =F37*G37 -> 0.55860472 | I37: =F37*INDEX(PARTIDAS!$I$7:$I$132,MATCH(B37,PARTIDAS!$A$7:$A$132,0)) -> 0.333375 | J37: =F37*INDEX(PARTIDAS!$J$7:$J$132,MATCH(B37,PARTIDAS!$A$7:$A$132,0)) -> 0.025571588 | K37: =H37-I37-J37 -> 0.19965814
A38: HA | B38: REFORESTACION|01.04 | C38: TRAZO, NIVELACION Y REPLANTEO POR HECTAREA | D38: 1000.05 | E38: 1000.05 | F38: =D38/E38 -> 1 | G38: =INDEX(PARTIDAS!$H$7:$H$132,MATCH(B38,PARTIDAS!$A$7:$A$132,0)) -> 438.98644 | H38: =F38*G38 -> 438.98644 | I38: =F38*INDEX(PARTIDAS!$I$7:$I$132,MATCH(B38,PARTIDAS!$A$7:$A$132,0)) -> 166.66625 | J38: =F38*INDEX(PARTIDAS!$J$7:$J$132,MATCH(B38,PARTIDAS!$A$7:$A$132,0)) -> 139.11926 | K38: =H38-I38-J38 -> 133.20093
A39: HA | B39: REFORESTACION|01.05 | C39: LIMPIEZA MANUAL DE TERRENO | D39: 1000.05 | E39: 1000.05 | F39: =D39/E39 -> 1 | G39: =INDEX(PARTIDAS!$H$7:$H$132,MATCH(B39,PARTIDAS!$A$7:$A$132,0)) -> 212.33714 | H39: =F39*G39 -> 212.33714 | I39: =F39*INDEX(PARTIDAS!$I$7:$I$132,MATCH(B39,PARTIDAS!$A$7:$A$132,0)) -> 200 | J39: =F39*INDEX(PARTIDAS!$J$7:$J$132,MATCH(B39,PARTIDAS!$A$7:$A$132,0)) -> 6.1525626 | K39: =H39-I39-J39 -> 6.1845769
A40: HA | B40: REFORESTACION|04.01.03 | C40: CONTROL SANITARIO PREVIO A PLANTACION | D40: 1000 | E40: 1000 | F40: =D40/E40 -> 1 | G40: =INDEX(PARTIDAS!$H$7:$H$132,MATCH(B40,PARTIDAS!$A$7:$A$132,0)) -> 44.257816 | H40: =F40*G40 -> 44.257816 | I40: =F40*INDEX(PARTIDAS!$I$7:$I$132,MATCH(B40,PARTIDAS!$A$7:$A$132,0)) -> 25 | J40: =F40*INDEX(PARTIDAS!$J$7:$J$132,MATCH(B40,PARTIDAS!$A$7:$A$132,0)) -> 0.76907032 | K40: =H40-I40-J40 -> 18.488745
A41: HA | B41: REFORESTACION|04.02.03 | C41: DESHIERBE MANUAL EN AREAS REFORESTADAS | D41: =P_DESHIERBES -> 4 | E41: 1 | F41: =D41/E41 -> 4 | G41: =INDEX(PARTIDAS!$H$7:$H$132,MATCH(B41,PARTIDAS!$A$7:$A$132,0)) -> 106.16857 | H41: =F41*G41 -> 424.67428 | I41: =F41*INDEX(PARTIDAS!$I$7:$I$132,MATCH(B41,PARTIDAS!$A$7:$A$132,0)) -> 400 | J41: =F41*INDEX(PARTIDAS!$J$7:$J$132,MATCH(B41,PARTIDAS!$A$7:$A$132,0)) -> 12.305125 | K41: =H41-I41-J41 -> 12.369154
A42: CERCO | B42: REFORESTACION|02.02.02 | C42: CERCO PERIMETRICO DE ALAMBRE DE PUAS | D42: 1 | E42: 1 | F42: =D42/E42 -> 1 | G42: =INDEX(PARTIDAS!$H$7:$H$132,MATCH(B42,PARTIDAS!$A$7:$A$132,0)) -> 21.969803 | H42: =F42*G42 -> 21.969803 | I42: =F42*INDEX(PARTIDAS!$I$7:$I$132,MATCH(B42,PARTIDAS!$A$7:$A$132,0)) -> 0 | J42: =F42*INDEX(PARTIDAS!$J$7:$J$132,MATCH(B42,PARTIDAS!$A$7:$A$132,0)) -> 0 | K42: =H42-I42-J42 -> 21.969803
A43: ZANJA | B43: ZANJAS|01.04 | C43: TRAZO, NIVELACION Y REPLANTEO POR KILOMETRO | D43: 360 | E43: 360 | F43: =D43/E43 -> 1 | G43: =INDEX(PARTIDAS!$H$7:$H$132,MATCH(B43,PARTIDAS!$A$7:$A$132,0)) -> 493.52749 | H43: =F43*G43 -> 493.52749 | I43: =F43*INDEX(PARTIDAS!$I$7:$I$132,MATCH(B43,PARTIDAS!$A$7:$A$132,0)) -> 187.5 | J43: =F43*INDEX(PARTIDAS!$J$7:$J$132,MATCH(B43,PARTIDAS!$A$7:$A$132,0)) -> 156.51073 | K43: =H43-I43-J43 -> 149.51676
A44: ZANJA | B44: ZANJAS|03.01.01 | C44: APERTURA MANUAL DE ZANJAS DE 0.40x0.30 M. EN MATERIAL SUELTO | D44: 360 | E44: 360 | F44: =D44/E44 -> 1 | G44: =INDEX(PARTIDAS!$H$7:$H$132,MATCH(B44,PARTIDAS!$A$7:$A$132,0)) -> 2527.8227 | H44: =F44*G44 -> 2527.8227 | I44: =F44*INDEX(PARTIDAS!$I$7:$I$132,MATCH(B44,PARTIDAS!$A$7:$A$132,0)) -> 2380.9525 | J44: =F44*INDEX(PARTIDAS!$J$7:$J$132,MATCH(B44,PARTIDAS!$A$7:$A$132,0)) -> 73.244335 | K44: =H44-I44-J44 -> 73.625905
A45: ZANJA | B45: ZANJAS|03.01.02 | C45: PERFILADO MANUAL DE TALUDES | D45: 216000 | E45: 360 | F45: =D45/E45 -> 600 | G45: =INDEX(PARTIDAS!$H$7:$H$132,MATCH(B45,PARTIDAS!$A$7:$A$132,0)) -> 1.0563285 | H45: =F45*G45 -> 633.79712 | I45: =F45*INDEX(PARTIDAS!$I$7:$I$132,MATCH(B45,PARTIDAS!$A$7:$A$132,0)) -> 571.5 | J45: =F45*INDEX(PARTIDAS!$J$7:$J$132,MATCH(B45,PARTIDAS!$A$7:$A$132,0)) -> 43.837008 | K45: =H45-I45-J45 -> 18.46011
A46: ZANJA | B46: ZANJAS|03.01.03 | C46: CONFORMACION DEL CAMELLON | D46: 36000 | E46: 360 | F46: =D46/E46 -> 100 | G46: =INDEX(PARTIDAS!$H$7:$H$132,MATCH(B46,PARTIDAS!$A$7:$A$132,0)) -> 52.711005 | H46: =F46*G46 -> 5271.1005 | I46: =F46*INDEX(PARTIDAS!$I$7:$I$132,MATCH(B46,PARTIDAS!$A$7:$A$132,0)) -> 4444.5 | J46: =F46*INDEX(PARTIDAS!$J$7:$J$132,MATCH(B46,PARTIDAS!$A$7:$A$132,0)) -> 341.85176 | K46: =H46-I46-J46 -> 484.74879
A47: ZANJA | B47: ZANJAS|03.01.04 | C47: ELIMINACION MANUAL DE DESMONTE DIST. PROM. 0.5 KM | D47: 9000 | E47: 360 | F47: =D47/E47 -> 25 | G47: =INDEX(PARTIDAS!$H$7:$H$132,MATCH(B47,PARTIDAS!$A$7:$A$132,0)) -> 27.174076 | H47: =F47*G47 -> 679.35191 | I47: =F47*INDEX(PARTIDAS!$I$7:$I$132,MATCH(B47,PARTIDAS!$A$7:$A$132,0)) -> 625 | J47: =F47*INDEX(PARTIDAS!$J$7:$J$132,MATCH(B47,PARTIDAS!$A$7:$A$132,0)) -> 34.564958 | K47: =H47-I47-J47 -> 19.786949
A48: TERRAZA | B48: TERRAZAS|01.04 | C48: TRAZO, NIVELACION Y REPLANTEO POR KILOMETRO | D48: 120 | E48: 120 | F48: =D48/E48 -> 1 | G48: =INDEX(PARTIDAS!$H$7:$H$132,MATCH(B48,PARTIDAS!$A$7:$A$132,0)) -> 493.52749 | H48: =F48*G48 -> 493.52749 | I48: =F48*INDEX(PARTIDAS!$I$7:$I$132,MATCH(B48,PARTIDAS!$A$7:$A$132,0)) -> 187.5 | J48: =F48*INDEX(PARTIDAS!$J$7:$J$132,MATCH(B48,PARTIDAS!$A$7:$A$132,0)) -> 156.51073 | K48: =H48-I48-J48 -> 149.51676
A49: TERRAZA | B49: TERRAZAS|03.01.01 | C49: EXCAVACION MANUAL PARA CONFORMACION DE TERRAZAS EN MATERIAL SUELTO | D49: 138000 | E49: 120 | F49: =D49/E49 -> 1150 | G49: =INDEX(PARTIDAS!$H$7:$H$132,MATCH(B49,PARTIDAS!$A$7:$A$132,0)) -> 26.542142 | H49: =F49*G49 -> 30523.464 | I49: =F49*INDEX(PARTIDAS!$I$7:$I$132,MATCH(B49,PARTIDAS!$A$7:$A$132,0)) -> 28750 | J49: =F49*INDEX(PARTIDAS!$J$7:$J$132,MATCH(B49,PARTIDAS!$A$7:$A$132,0)) -> 884.43087 | K49: =H49-I49-J49 -> 889.03293
A50: TERRAZA | B50: TERRAZAS|03.01.02 | C50: RELLENO COMPACTADO CON MATERIAL PROPIO | D50: 132000 | E50: 120 | F50: =D50/E50 -> 1100 | G50: =INDEX(PARTIDAS!$H$7:$H$132,MATCH(B50,PARTIDAS!$A$7:$A$132,0)) -> 30.677571 | H50: =F50*G50 -> 33745.328 | I50: =F50*INDEX(PARTIDAS!$I$7:$I$132,MATCH(B50,PARTIDAS!$A$7:$A$132,0)) -> 15714.875 | J50: =F50*INDEX(PARTIDAS!$J$7:$J$132,MATCH(B50,PARTIDAS!$A$7:$A$132,0)) -> 4878.8778 | K50: =H50-I50-J50 -> 13151.576
A51: TERRAZA | B51: TERRAZAS|03.01.03 | C51: PIRCADO CON PIEDRA, DIA. PROM. 12" PARA CONFORMACION TERRAZAS | D51: 28800 | E51: 120 | F51: =D51/E51 -> 240 | G51: =INDEX(PARTIDAS!$H$7:$H$132,MATCH(B51,PARTIDAS!$A$7:$A$132,0)) -> 98.849553 | H51: =F51*G51 -> 23723.893 | I51: =F51*INDEX(PARTIDAS!$I$7:$I$132,MATCH(B51,PARTIDAS!$A$7:$A$132,0)) -> 7680 | J51: =F51*INDEX(PARTIDAS!$J$7:$J$132,MATCH(B51,PARTIDAS!$A$7:$A$132,0)) -> 2418.994 | K51: =H51-I51-J51 -> 13624.899
A52: TERRAZA | B52: TERRAZAS|03.01.04 | C52: ELIMINACION MANUAL DE DESMONTE DIST. PROM. 0.5 KM | D52: 7500 | E52: 120 | F52: =D52/E52 -> 62.5 | G52: =INDEX(PARTIDAS!$H$7:$H$132,MATCH(B52,PARTIDAS!$A$7:$A$132,0)) -> 27.174076 | H52: =F52*G52 -> 1698.3798 | I52: =F52*INDEX(PARTIDAS!$I$7:$I$132,MATCH(B52,PARTIDAS!$A$7:$A$132,0)) -> 1562.5 | J52: =F52*INDEX(PARTIDAS!$J$7:$J$132,MATCH(B52,PARTIDAS!$A$7:$A$132,0)) -> 86.412396 | K52: =H52-I52-J52 -> 49.467372
A53: CARCAVA | B53: CARCAVAS|01.04 | C53: TRAZO, NIVELACION Y REPLANTEO POR KILOMETRO | D53: 3.24 | E53: 3.24 | F53: =D53/E53 -> 1 | G53: =INDEX(PARTIDAS!$H$7:$H$132,MATCH(B53,PARTIDAS!$A$7:$A$132,0)) -> 493.52749 | H53: =F53*G53 -> 493.52749 | I53: =F53*INDEX(PARTIDAS!$I$7:$I$132,MATCH(B53,PARTIDAS!$A$7:$A$132,0)) -> 187.5 | J53: =F53*INDEX(PARTIDAS!$J$7:$J$132,MATCH(B53,PARTIDAS!$A$7:$A$132,0)) -> 156.51073 | K53: =H53-I53-J53 -> 149.51676
... A57: CARCAVA | B57: CARCAVAS|03.01.04 | C57: COLOCACION DE PIEDRA CANTEADA | D57: 15681.6 | E57: 3.24 | F57: =D57/E57 -> 4840 | G57: =INDEX(PARTIDAS!$H$7:$H$132,MATCH(B57,PARTIDAS!$A$7:$A$132,0)) -> 125.61451 | H57: =F57*G57 -> 607974.25 | I57: =F57*INDEX(PARTIDAS!$I$7:$I$132,MATCH(B57,PARTIDAS!$A$7:$A$132,0)) -> 121000 | J57: =F57*INDEX(PARTIDAS!$J$7:$J$132,MATCH(B57,PARTIDAS!$A$7:$A$132,0)) -> 42764.631 | K57: =H57-I57-J57 -> 444209.62
A59: Compuesto | B59: Nombre | C59: Descripción | H59: Costo unitario | I59: MO no calificada | J59: MO calificada | K59: Bienes y servicios
A60: PLANTON | B60: CU_PLANTON | C60: S/ por plantón producido en vivero propio (ANIN: 650 000 plantones; infraestructura de vivero amortizada en una campaña) | H60: =SUM(H7:H29) -> 1.3333864 | I60: =SUM(I7:I29) -> 0.79089155 | J60: =SUM(J7:J29) -> 0.13492729 | K60: =SUM(K7:K29) -> 0.40756753
A61: PLANTA | B61: CU_PLANTA | C61: S/ por planta instalada (sin plantón) | H61: =SUM(H30:H37) -> 6.860882 | I61: =SUM(I30:I37) -> 3.950875 | J61: =SUM(J30:J37) -> 0.17485699 | K61: =SUM(K30:K37) -> 2.73515
A62: HA | B62: CU_HA | C62: S/ por ha plantada (R1 + R2) | H62: =SUM(H38:H41) -> 1120.2557 | I62: =SUM(I38:I41) -> 791.66625 | J62: =SUM(J38:J41) -> 158.34601 | K62: =SUM(K38:K41) -> 170.24341
A63: CERCO | B63: CU_CERCO | C63: S/ por m de cerco | H63: =SUM(H42:H42) -> 21.969803 | I63: =SUM(I42:I42) -> 0 | J63: =SUM(J42:J42) -> 0 | K63: =SUM(K42:K42) -> 21.969803
A64: ZANJA | B64: CU_ZANJA | C64: S/ por km de zanja de infiltración (0.40 × 0.30 m; ANIN: 360 km) | H64: =SUM(H43:H47) -> 9605.5998 | I64: =SUM(I43:I47) -> 8209.4525 | J64: =SUM(J43:J47) -> 650.00879 | K64: =SUM(K43:K47) -> 746.13851
A65: TERRAZA | B65: CU_TERRAZA | C65: S/ por km de terraza de formación lenta (ANIN: 120 km) | H65: =SUM(H48:H52) -> 90184.592 | I65: =SUM(I48:I52) -> 53894.875 | J65: =SUM(J48:J52) -> 8425.2258 | K65: =SUM(K48:K52) -> 27864.491
A66: CARCAVA | B66: CU_CARCAVA | C66: S/ por km de cárcava con diques de piedra canteada (ANIN: 3.24 km) | H66: =SUM(H53:H57) -> 700993.31 | I66: =SUM(I53:I57) -> 202489.48 | J66: =SUM(J53:J57) -> 50159.104 | K66: =SUM(K53:K57) -> 448344.73
A68: Notas: (1) El plantón se costea con producción en vivero propio (decisión del 18-oct-2026), sobre la ficha ANIN de algarrobo. (2) En PLANTA, riego y recalce usan P_RIEGOS y P_RECALCE. (3) Las fichas ANIN de zanjas, terrazas y cárcavas incluyen además revegetación con esquejes y siembra al voleo, que aquí no se suman para no duplicar la plantación.

Sheet PAQUETES
A1: AUTORIDAD NACIONAL DE INFRAESTRUCTURA - ANIN
A2: DIRECCIÓN DE INTERVENCIONES MULTISECTORIALES Y DE EMERGENCIA - DIME
A3: SUBDIRECCIÓN DE ESTUDIOS DE INVERSIÓN
A4: PROYECTO IN PIURA – CUI 2669244 · Paquetes tecnológicos por tipología (6) – coeficientes editables
A5: Grupo × degradación. R1 = MSAVI DN 1–2 (< 0.3813); R2 = DN 3 (0.3813–0.4976); C = DN 4–5 (protección). Marrón: celdas R1/R2 con PMM ≥ DN 4.
A6: Tipología | B6: Clave | C6: Grupo de ecosistema | D6: Degradación | E6: Densidad R1 (pl/ha) | F6: Densidad R2 enriquecimiento (pl/ha) | G6: Espaciamiento zanjas (m) [0 = no aplica] | H6: Espaciamiento terrazas (m) [0 = no aplica] | I6: Cerco (fracción del perímetro) | J6: Zanjas (m/ha) | K6: Terrazas (m/ha) | L6: Fuente de los coeficientes
A7: T1 | B7: BES|Alta | C7: Bosque estacionalmente seco de colina y montaña | D7: Alta | E7: 650 | F7: 325 | G7: 2.7778 | H7: 0 | I7: 1 | J7: =IF(G7>0,10000/G7,0) -> 3599.9712 | K7: =IF(H7>0,10000/H7,0) -> 0 | L7: R1: ANIN algarrobo 650 pl/ha. R2: SUPUESTO 50 % de R1. Zanjas: ANIN 360 km/100 ha (esp. 2.78 m). Cerco: SUPUESTO 100 % del perímetro.
A8: T2 | B8: BES|Moderada | C8: Bosque estacionalmente seco de colina y montaña | D8: Moderada | E8: 650 | F8: 325 | G8: 2.7778 | H8: 0 | I8: 1 | J8: =IF(G8>0,10000/G8,0) -> 3599.9712 | K8: =IF(H8>0,10000/H8,0) -> 0 | L8: R1: ANIN algarrobo 650 pl/ha. R2: SUPUESTO 50 % de R1. Zanjas: ANIN 360 km/100 ha (esp. 2.78 m). Cerco: SUPUESTO 100 % del perímetro.
A9: T3 | B9: ANDINO|Alta | C9: Andino (matorral andino + páramo + relicto montano) | D9: Alta | E9: 722 | F9: 361 | G9: 2.7778 | H9: 0 | I9: 1 | J9: =IF(G9>0,10000/G9,0) -> 3599.9712 | K9: =IF(H9>0,10000/H9,0) -> 0 | L9: R1: Sierra Azul Chacaya 722 pl/ha. R2: SUPUESTO 50 % de R1. Zanjas: ANIN 360 km/100 ha. Cerco: SUPUESTO 100 %.
A10: T4 | B10: ANDINO|Moderada | C10: Andino (matorral andino + páramo + relicto montano) | D10: Moderada | E10: 722 | F10: 361 | G10: 2.7778 | H10: 0 | I10: 1 | J10: =IF(G10>0,10000/G10,0) -> 3599.9712 | K10: =IF(H10>0,10000/H10,0) -> 0 | L10: R1: Sierra Azul Chacaya 722 pl/ha. R2: SUPUESTO 50 % de R1. Zanjas: ANIN 360 km/100 ha. Cerco: SUPUESTO 100 %.
A11: T5 | B11: MOSAICO|Alta | C11: Mosaico agroforestal (zona agrícola MINAM) | D11: Alta | E11: 650 | F11: 325 | G11: 0 | H11: 8.3333 | I11: 1 | J11: =IF(G11>0,10000/G11,0) -> 0 | K11: =IF(H11>0,10000/H11,0) -> 1200.0048 | L11: R1: ANIN 650 pl/ha (SUPUESTO para SAF). R2: SUPUESTO 50 %. Terrazas: ANIN 120 km/100 ha (esp. 8.33 m). Cerco: SUPUESTO 100 %.
A12: T6 | B12: MOSAICO|Moderada | C12: Mosaico agroforestal (zona agrícola MINAM) | D12: Moderada | E12: 650 | F12: 325 | G12: 0 | H12: 8.3333 | I12: 1 | J12: =IF(G12>0,10000/G12,0) -> 0 | K12: =IF(H12>0,10000/H12,0) -> 1200.0048 | L12: R1: ANIN 650 pl/ha (SUPUESTO para SAF). R2: SUPUESTO 50 %. Terrazas: ANIN 120 km/100 ha (esp. 8.33 m). Cerco: SUPUESTO 100 %.
A14: Los coeficientes de zanjas y terrazas provienen de fichas ANIN de referencia y deben calibrarse con el piloto (bloques 21, 66, 73, 31 y M6B10). Cárcavas: metrado por bloque (ml) en la hoja BLOQUES, columna AD.

Sheet BLOQUES
A1: AUTORIDAD NACIONAL DE INFRAESTRUCTURA - ANIN
A2: DIRECCIÓN DE INTERVENCIONES MULTISECTORIALES Y DE EMERGENCIA - DIME
A3: SUBDIRECCIÓN DE ESTUDIOS DE INVERSIÓN
A4: PROYECTO IN PIURA – CUI 2669244 · Datos de entrada por bloque (SIG) y asignación de tipología
A5: Fuentes: Relación de bloques V6 – versión normalizada (Bloques_V7_Normalizado.xlsx, corte 09/10/2026: 117 bloques, 12 270.235 ha); geometría KMZ B6, MSAVI vectorizado (DN 1–5), PMM (DN 1–5), Intersección ecosistemas MINAM, red vial vecinal MTC (dic-2018) y trochas MTC (2026). Áreas en ha (UTM 17S).
A6: Bloque | B6: Provincia | C6: Distrito | D6: Microcuenca | E6: Área (ha) | F6: Perímetro (m) | G6: MSAVI 2024 medio | H6: BES (ha) | I6: Andino (ha) | J6: Zona agrícola (ha) | K6: MSAVI DN1 (ha) | L6: MSAVI DN2 (ha) | M6: MSAVI DN3 (ha) | N6: MSAVI DN4 (ha) | O6: MSAVI DN5 (ha) | P6: PMM DN1 (ha) | Q6: PMM DN2 (ha) | R6: PMM DN3 (ha) | S6: PMM DN4 (ha) | T6: PMM DN5 (ha) | U6: R1 · PMM alto (ha) | V6: R1 · PMM bajo (ha) | W6: R2 · PMM alto (ha) | X6: R2 · PMM bajo (ha) | Y6: C · PMM alto (ha) | Z6: C · PMM bajo (ha) | AA6: Dist. borde a vía motorizable (m) | AB6: Dist. media de acarreo (m) | AC6: Superficie vía más cercana | AD6: Cárcavas (ml) [por inventario dron/satélite] | AE6: Piloto | AF6: % bajo umbral MSAVI | AG6: Grupo dominante | AH6: Degradación | AI6: Tipología | AJ6: N° (V7 normalizado) | AK6: UBIGEO | AL6: Superposición reportada (ha) | AM6: Observación (V7 normalizado)
A7: 3 | B7: AYABACA | C7: FRIAS | D7: C1096-Q9545 | E7: 459.295 | F7: 11633.7 | G7: 0.567707 | H7: 25.097 | I7: 0 | J7: 434.197 | K7: 0.002 | L7: 5.641 | M7: 127.959 | N7: 175.098 | O7: 150.975 | P7: 0.119 | Q7: 2.747 | R7: 15.564 | S7: 111.384 | T7: 329.48 | U7: 5.243 | V7: 0.38 | W7: 121.406 | X7: 6.452 | Y7: 314.215 | Z7: 11.598 | AA7: 5 | AB7: 621 | AC7: Trocha | AE7: No | AF7: =IF(E7=0,0,(K7+L7+M7)/(K7+L7+M7+N7+O7)) -> 0.29064448 | AG7: =IF(J7>=MAX(H7,I7),"MOSAICO",IF(H7>=I7,"BES","ANDINO")) -> MOSAICO | AH7: =IF(AF7>=P_CORTE,"Alta","Moderada") -> Moderada | AI7: =INDEX(PAQ_T,MATCH(AG7&"|"&AH7,PAQ_KEY,0)) -> T6 | AJ7: 1 | AK7: 200202
A8: 6 | B8: AYABACA | C8: FRIAS | D8: C1096-Q9547 | E8: 168.411 | F8: 8376.1 | G8: 0.538144 | H8: 4.175 | I8: 0 | J8: 164.236 | K8: 0.065 | L8: 4.226 | M8: 55.399 | N8: 77.184 | O8: 31.686 | P8: 0.047 | Q8: 1.389 | R8: 3.54 | S8: 20.164 | T8: 143.271 | U8: 3.819 | V8: 0.462 | W8: 52.451 | X8: 2.902 | Y8: 107.164 | Z8: 1.612 | AA8: 0 | AB8: 433 | AC8: Trocha | AE8: No | AF8: =IF(E8=0,0,(K8+L8+M8)/(K8+L8+M8+N8+O8)) -> 0.35411723 | AG8: =IF(J8>=MAX(H8,I8),"MOSAICO",IF(H8>=I8,"BES","ANDINO")) -> MOSAICO | AH8: =IF(AF8>=P_CORTE,"Alta","Moderada") -> Moderada | AI8: =INDEX(PAQ_T,MATCH(AG8&"|"&AH8,PAQ_KEY,0)) -> T6 | AJ8: 2 | AK8: 200202
A9: 36 | B9: AYABACA | C9: FRIAS | D9: C1096-Q9547 | E9: 24.843 | F9: 2675.4 | G9: 0.539458 | H9: 0 | I9: 0 | J9: 24.843 | K9: 0 | L9: 0.349 | M9: 8.512 | N9: 11.302 | O9: 4.702 | P9: 0 | Q9: 0 | R9: 0.194 | S9: 4.739 | T9: 19.911 | U9: 0.347 | V9: 0 | W9: 8.505 | X9: 0 | Y9: 15.797 | Z9: 0.194 | AA9: 14 | AB9: 168 | AC9: Trocha | AE9: No | AF9: =IF(E9=0,0,(K9+L9+M9)/(K9+L9+M9+N9+O9)) -> 0.35636437 | AG9: =IF(J9>=MAX(H9,I9),"MOSAICO",IF(H9>=I9,"BES","ANDINO")) -> MOSAICO | AH9: =IF(AF9>=P_CORTE,"Alta","Moderada") -> Moderada | AI9: =INDEX(PAQ_T,MATCH(AG9&"|"&AH9,PAQ_KEY,0)) -> T6 | AJ9: 3 | AK9: 200202
A10: 27 | B10: AYABACA | C10: FRIAS | D10: C1096-Q9556 | E10: 78.154 | F10: 4228.3 | G10: 0.53228 | H10: 0 | I10: 0 | J10: 78.154 | K10: 0 | L10: 0.807 | M10: 28.525 | N10: 36.504 | O10: 12.379 | P10: 0.045 | Q10: 1.059 | R10: 4.095 | S10: 16.225 | T10: 56.731 | U10: 0.765 | V10: 0.039 | W10: 25.511 | X10: 2.991 | Y10: 46.68 | Z10: 2.168 | AA10: 251 | AB10: 801 | AC10: Trocha | AE10: No | AF10: =IF(E10=0,0,(K10+L10+M10)/(K10+L10+M10+N10+O10)) -> 0.37501758 | AG10: =IF(J10>=MAX(H10,I10),"MOSAICO",IF(H10>=I10,"BES","ANDINO")) -> MOSAICO | AH10: =IF(AF10>=P_CORTE,"Alta","Moderada") -> Moderada | AI10: =INDEX(PAQ_T,MATCH(AG10&"|"&AH10,PAQ_KEY,0)) -> T6 | AJ10: 4 | AK10: 200202
A11: M17B10 | B11: AYABACA | C11: FRIAS | D11: C1096-Q9556 | E11: 75.363 | F11: 3644.3 | G11: 0.472466 | H11: 32.046 | I11: 0 | J11: 43.318 | K11: 0 | L11: 2.351 | M11: 52.948 | N11: 15.593 | O11: 4.524 | P11: 0 | Q11: 0.286 | R11: 2.343 | S11: 27.809 | T11: 44.925 | U11: 2.169 | V11: 0.177 | W11: 50.882 | X11: 2.037 | Y11: 19.684 | Z11: 0.415 | AA11: 352 | AB11: 785 | AC11: Afirmado | AE11: No | AF11: =IF(E11=0,0,(K11+L11+M11)/(K11+L11+M11+N11+O11)) -> 0.73325289 | AG11: =IF(J11>=MAX(H11,I11),"MOSAICO",IF(H11>=I11,"BES","ANDINO")) -> MOSAICO | AH11: =IF(AF11>=P_CORTE,"Alta","Moderada") -> Alta | AI11: =INDEX(PAQ_T,MATCH(AG11&"|"&AH11,PAQ_KEY,0)) -> T5 | AJ11: 5 | AK11: 200202
A12: M17B5 | B12: AYABACA | C12: FRIAS | D12: C1096-Q9556 | E12: 74.028 | F12: 4276.5 | G12: 0.54817 | H12: 52.459 | I12: 0 | J12: 21.569 | K12: 0 | L12: 0.437 | M12: 21.009 | N12: 36.814 | O12: 15.837 | P12: 0.017 | Q12: 0.592 | R12: 3.426 | S12: 21.578 | T12: 48.415 | U12: 0.435 | V12: 0 | W12: 19.808 | X12: 1.182 | Y12: 49.749 | Z12: 2.853 | AA12: 1093 | AB12: 1697 | AC12: Afirmado | AE12: No | AF12: =IF(E12=0,0,(K12+L12+M12)/(K12+L12+M12+N12+O12)) -> 0.28943142 | AG12: =IF(J12>=MAX(H12,I12),"MOSAICO",IF(H12>=I12,"BES","ANDINO")) -> BES | AH12: =IF(AF12>=P_CORTE,"Alta","Moderada") -> Moderada | AI12: =INDEX(PAQ_T,MATCH(AG12&"|"&AH12,PAQ_KEY,0)) -> T2 | AJ12: 6 | AK12: 200202
A13: M17B6 | B13: AYABACA | C13: FRIAS | D13: C1096-Q9556 | E13: 106.538 | F13: 6508.8 | G13: 0.446441 | H13: 106.538 | I13: 0 | J13: 0 | K13: 0.019 | L13: 13.367 | M13: 73.848 | N13: 17.7 | O13: 1.696 | P13: 0.125 | Q13: 2.619 | R13: 8.661 | S13: 45.707 | T13: 49.426 | U13: 10.209 | V13: 3.153 | W13: 66.437 | X13: 7.37 | Y13: 18.488 | Z13: 0.882 | AA13: 7 | AB13: 531 | AC13: Afirmado | AE13: No | AF13: =IF(E13=0,0,(K13+L13+M13)/(K13+L13+M13+N13+O13)) -> 0.81809997 | AG13: =IF(J13>=MAX(H13,I13),"MOSAICO",IF(H13>=I13,"BES","ANDINO")) -> BES | AH13: =IF(AF13>=P_CORTE,"Alta","Moderada") -> Alta | AI13: =INDEX(PAQ_T,MATCH(AG13&"|"&AH13,PAQ_KEY,0)) -> T1 | AJ13: 7 | AK13: 200202
A14: M17B7 | B14: AYABACA | C14: FRIAS | D14: C1096-Q9556 | E14: 258.837 | F14: 12968.1 | G14: 0.508715 | H14: 114.158 | I14: 0 | J14: 144.679 | K14: 0.004 | L14: 15.085 | M14: 110.281 | N14: 98.067 | O14: 35.622 | P14: 0.031 | Q14: 0.218 | R14: 2.62 | S14: 45.08 | T14: 210.887 | U14: 14.863 | V14: 0.199 | W14: 108.521 | X14: 1.683 | Y14: 132.584 | Z14: 0.988 | AA14: 0 | AB14: 484 | AC14: Afirmado | AE14: No | AF14: =IF(E14=0,0,(K14+L14+M14)/(K14+L14+M14+N14+O14)) -> 0.48394381 | AG14: =IF(J14>=MAX(H14,I14),"MOSAICO",IF(H14>=I14,"BES","ANDINO")) -> MOSAICO | AH14: =IF(AF14>=P_CORTE,"Alta","Moderada") -> Moderada | AI14: =INDEX(PAQ_T,MATCH(AG14&"|"&AH14,PAQ_KEY,0)) -> T6 | AJ14: 8 | AK14: 200202
A15: 39 | B15: AYABACA | C15: FRIAS | D15: C1096-Q9564 | E15: 68.569 | F15: 3605.6 | G15: 0.701601 | H15: 0 | I15: 68.569 | J15: 0 | K15: 0 | L15: 0 | M15: 2.641 | N15: 9.533 | O15: 56.446 | P15: 0 | Q15: 0.009 | R15: 3.398 | S15: 39.07 | T15: 26.092 | U15: 0 | V15: 0 | W15: 2.521 | X15: 0.114 | Y15: 62.641 | Z15: 3.293 | AA15: 237 | AB15: 600 | AC15: Trocha | AE15: No | AF15: =IF(E15=0,0,(K15+L15+M15)/(K15+L15+M15+N15+O15)) -> 0.038487321 | AG15: =IF(J15>=MAX(H15,I15),"MOSAICO",IF(H15>=I15,"BES","ANDINO")) -> ANDINO | AH15: =IF(AF15>=P_CORTE,"Alta","Moderada") -> Moderada | AI15: =INDEX(PAQ_T,MATCH(AG15&"|"&AH15,PAQ_KEY,0)) -> T4 | AJ15: 9 | AK15: 200202 | AM15: Microcuenca sin codigo M asignado
A16: 56 | B16: AYABACA | C16: FRIAS | D16: C1096-Q9564 | E16: 77.666 | F16: 3472.6 | G16: 0.677658 | H16: 0 | I16: 41.849 | J16: 35.817 | K16: 0 | L16: 0.02 | M16: 2.154 | N16: 14.19 | O16: 61.344 | P16: 0 | Q16: 0.078 | R16: 0.805 | S16: 19.938 | T16: 56.844 | U16: 0.02 | V16: 0 | W16: 2.13 | X16: 0.021 | Y16: 74.632 | Z16: 0.863 | AA16: 1054 | AB16: 1462 | AC16: Trocha | AE16: No | AF16: =IF(E16=0,0,(K16+L16+M16)/(K16+L16+M16+N16+O16)) -> 0.027976528 | AG16: =IF(J16>=MAX(H16,I16),"MOSAICO",IF(H16>=I16,"BES","ANDINO")) -> ANDINO | AH16: =IF(AF16>=P_CORTE,"Alta","Moderada") -> Moderada | AI16: =INDEX(PAQ_T,MATCH(AG16&"|"&AH16,PAQ_KEY,0)) -> T4 | AJ16: 10 | AK16: 200202 | AM16: Microcuenca sin codigo M asignado
A17: 81 | B17: HUANCABAMBA | C17: CANCHAQUE | D17: C1076-Q9585 | E17: 8.929 | F17: 1243.6 | G17: 0.274714 | H17: 8.929 | I17: 0 | J17: 0 | K17: 3.961 | L17: 4.84 | M17: 0.137 | N17: 0 | O17: 0 | P17: 0.005 | Q17: 0.951 | R17: 3.184 | S17: 3.7 | T17: 1.089 | U17: 4.678 | V17: 4.114 | W17: 0.111 | X17: 0.026 | Y17: 0 | Z17: 0 | AA17: 133 | AB17: 292 | AC17: Trocha | AE17: No | AF17: =IF(E17=0,0,(K17+L17+M17)/(K17+L17+M17+N17+O17)) -> 1 | AG17: =IF(J17>=MAX(H17,I17),"MOSAICO",IF(H17>=I17,"BES","ANDINO")) -> BES | AH17: =IF(AF17>=P_CORTE,"Alta","Moderada") -> Alta | AI17: =INDEX(PAQ_T,MATCH(AG17&"|"&AH17,PAQ_KEY,0)) -> T1 | AJ17: 11 | AK17: 200302
A18: 79 | B18: HUANCABAMBA | C18: CANCHAQUE | D18: C1076-Q9587 | E18: 94.812 | F18: 5495.2 | G18: 0.547879 | H18: 94.812 | I18: 0 | J18: 0 | K18: 0 | L18: 0.327 | M18: 27.84 | N18: 44.939 | O18: 21.748 | P18: 0.11 | Q18: 9.022 | R18: 30.308 | S18: 34.228 | T18: 21.143 | U18: 0.084 | V18: 0.24 | W18: 9.907 | X18: 17.921 | Y18: 45.381 | Z18: 21.279 | AA18: 93 | AB18: 902 | AC18: Trocha | AE18: No | AF18: =IF(E18=0,0,(K18+L18+M18)/(K18+L18+M18+N18+O18)) -> 0.2969511 | AG18: =IF(J18>=MAX(H18,I18),"MOSAICO",IF(H18>=I18,"BES","ANDINO")) -> BES | AH18: =IF(AF18>=P_CORTE,"Alta","Moderada") -> Moderada | AI18: =INDEX(PAQ_T,MATCH(AG18&"|"&AH18,PAQ_KEY,0)) -> T2 | AJ18: 12 | AK18: 200302 | AM18: Microcuenca sin codigo M asignado
A19: 24 | B19: HUANCABAMBA | C19: CANCHAQUE | D19: C1081-Q9583 | E19: 90.159 | F19: 3954.3 | G19: 0.674839 | H19: 13.972 | I19: 16.613 | J19: 59.575 | K19: 0 | L19: 0 | M19: 2.067 | N19: 20.024 | O19: 68.101 | P19: 0 | Q19: 0.297 | R19: 0.853 | S19: 12.859 | T19: 76.15 | U19: 0 | V19: 0 | W19: 2.061 | X19: 0 | Y19: 86.949 | Z19: 1.15 | AA19: 566 | AB19: 1051 | AC19: Trocha | AE19: No | AF19: =IF(E19=0,0,(K19+L19+M19)/(K19+L19+M19+N19+O19)) -> 0.022917775 | AG19: =IF(J19>=MAX(H19,I19),"MOSAICO",IF(H19>=I19,"BES","ANDINO")) -> MOSAICO | AH19: =IF(AF19>=P_CORTE,"Alta","Moderada") -> Moderada | AI19: =INDEX(PAQ_T,MATCH(AG19&"|"&AH19,PAQ_KEY,0)) -> T6 | AJ19: 13 | AK19: 200302
A20: 63 | B20: HUANCABAMBA | C20: CANCHAQUE | D20: C1081-Q9583 | E20: 50.459 | F20: 3007.5 | G20: 0.603582 | H20: 0 | I20: 50.459 | J20: 0 | K20: 0 | L20: 0 | M20: 1.488 | N20: 30.623 | O20: 18.36 | P20: 0 | Q20: 0.015 | R20: 0.031 | S20: 1.644 | T20: 48.768 | U20: 0 | V20: 0 | W20: 1.482 | X20: 0.005 | Y20: 48.931 | Z20: 0.04 | AA20: 1558 | AB20: 1932 | AC20: Trocha | AE20: No | AF20: =IF(E20=0,0,(K20+L20+M20)/(K20+L20+M20+N20+O20)) -> 0.029482277 | AG20: =IF(J20>=MAX(H20,I20),"MOSAICO",IF(H20>=I20,"BES","ANDINO")) -> ANDINO | AH20: =IF(AF20>=P_CORTE,"Alta","Moderada") -> Moderada | AI20: =INDEX(PAQ_T,MATCH(AG20&"|"&AH20,PAQ_KEY,0)) -> T4 | AJ20: 14 | AK20: 200302
A21: 21 | B21: HUANCABAMBA | C21: CANCHAQUE | D21: C1081-Q9591 | E21: 84.227 | F21: 3530.8 | G21: 0.620078 | H21: 0 | I21: 37.002 | J21: 47.225 | K21: 0 | L21: 0.01 | M21: 4.349 | N21: 38.697 | O21: 41.193 | P21: 0.031 | Q21: 0.133 | R21: 1.282 | S21: 19.46 | T21: 63.32 | U21: 0.01 | V21: 0 | W21: 4.304 | X21: 0.043 | Y21: 78.466 | Z21: 1.403 | AA21: 41 | AB21: 579 | AC21: Trocha | AE21: Sí | AF21: =IF(E21=0,0,(K21+L21+M21)/(K21+L21+M21+N21+O21)) -> 0.051739487 | AG21: =IF(J21>=MAX(H21,I21),"MOSAICO",IF(H21>=I21,"BES","ANDINO")) -> MOSAICO | AH21: =IF(AF21>=P_CORTE,"Alta","Moderada") -> Moderada | AI21: =INDEX(PAQ_T,MATCH(AG21&"|"&AH21,PAQ_KEY,0)) -> T6 | AJ21: 15 | AK21: 200302
A22: 28 | B22: HUANCABAMBA | C22: CANCHAQUE | D22: C1081-Q9591 | E22: 52.966 | F22: 3639.4 | G22: 0.639425 | H22: 0 | I22: 21.015 | J22: 31.95 | K22: 0 | L22: 0 | M22: 0.496 | N22: 19.203 | O22: 33.288 | P22: 0 | Q22: 0.038 | R22: 0.882 | S22: 11.742 | T22: 40.304 | U22: 0 | V22: 0 | W22: 0.483 | X22: 0.012 | Y22: 51.563 | Z22: 0.908 | AA22: 6 | AB22: 273 | AC22: Trocha | AE22: No | AF22: =IF(E22=0,0,(K22+L22+M22)/(K22+L22+M22+N22+O22)) -> 0.0093607866 | AG22: =IF(J22>=MAX(H22,I22),"MOSAICO",IF(H22>=I22,"BES","ANDINO")) -> MOSAICO | AH22: =IF(AF22>=P_CORTE,"Alta","Moderada") -> Moderada | AI22: =INDEX(PAQ_T,MATCH(AG22&"|"&AH22,PAQ_KEY,0)) -> T6 | AJ22: 16 | AK22: 200302
A23: 30 | B23: HUANCABAMBA | C23: CANCHAQUE | D23: C1081-Q9591 | E23: 34.874 | F23: 2492.5 | G23: 0.663804 | H23: 0 | I23: 7.869 | J23: 27.004 | K23: 0 | L23: 0 | M23: 0.46 | N23: 9.619 | O23: 24.808 | P23: 0 | Q23: 0.047 | R23: 0.784 | S23: 9.267 | T23: 24.776 | U23: 0 | V23: 0 | W23: 0.456 | X23: 0 | Y23: 33.588 | Z23: 0.83 | AA23: 508 | AB23: 903 | AC23: Trocha | AE23: No | AF23: =IF(E23=0,0,(K23+L23+M23)/(K23+L23+M23+N23+O23)) -> 0.013185427 | AG23: =IF(J23>=MAX(H23,I23),"MOSAICO",IF(H23>=I23,"BES","ANDINO")) -> MOSAICO | AH23: =IF(AF23>=P_CORTE,"Alta","Moderada") -> Moderada | AI23: =INDEX(PAQ_T,MATCH(AG23&"|"&AH23,PAQ_KEY,0)) -> T6 | AJ23: 17 | AK23: 200302
A24: 40 | B24: HUANCABAMBA | C24: CANCHAQUE | D24: C1081-Q9591 | E24: 28.523 | F24: 2169.9 | G24: 0.640099 | H24: 0 | I24: 11.54 | J24: 16.984 | K24: 0 | L24: 0 | M24: 0.83 | N24: 9.413 | O24: 18.29 | P24: 0 | Q24: 0.062 | R24: 0.125 | S24: 3.53 | T24: 24.806 | U24: 0 | V24: 0 | W24: 0.826 | X24: 0.001 | Y24: 27.51 | Z24: 0.186 | AA24: 959 | AB24: 1215 | AC24: Trocha | AE24: No | AF24: =IF(E24=0,0,(K24+L24+M24)/(K24+L24+M24+N24+O24)) -> 0.029089125 | AG24: =IF(J24>=MAX(H24,I24),"MOSAICO",IF(H24>=I24,"BES","ANDINO")) -> MOSAICO | AH24: =IF(AF24>=P_CORTE,"Alta","Moderada") -> Moderada | AI24: =INDEX(PAQ_T,MATCH(AG24&"|"&AH24,PAQ_KEY,0)) -> T6 | AJ24: 18 | AK24: 200302
A25: 60 | B25: HUANCABAMBA | C25: CANCHAQUE | D25: C1081-Q9591 | E25: 40.132 | F25: 3160.2 | G25: 0.67447 | H25: 0 | I25: 23.721 | J25: 16.41 | K25: 0 | L25: 0 | M25: 0.245 | N25: 5.987 | O25: 33.909 | P25: 0 | Q25: 0.045 | R25: 0.285 | S25: 3.935 | T25: 35.867 | U25: 0 | V25: 0 | W25: 0.245 | X25: 0 | Y25: 39.557 | Z25: 0.33 | AA25: 19 | AB25: 206 | AC25: Trocha | AE25: No | AF25: =IF(E25=0,0,(K25+L25+M25)/(K25+L25+M25+N25+O25)) -> 0.0061034852 | AG25: =IF(J25>=MAX(H25,I25),"MOSAICO",IF(H25>=I25,"BES","ANDINO")) -> ANDINO | AH25: =IF(AF25>=P_CORTE,"Alta","Moderada") -> Moderada | AI25: =INDEX(PAQ_T,MATCH(AG25&"|"&AH25,PAQ_KEY,0)) -> T4 | AJ25: 19 | AK25: 200302
A26: 66 | B26: HUANCABAMBA | C26: CANCHAQUE | D26: C1081-Q9591 | E26: 102.335 | F26: 4967.8 | G26: 0.640254 | H26: 19.246 | I26: 6.039 | J26: 77.05 | K26: 0.02 | L26: 0.531 | M26: 8.503 | N26: 32.268 | O26: 61.055 | P26: 0.031 | Q26: 0.565 | R26: 4.158 | S26: 24.336 | T26: 73.246 | U26: 0.547 | V26: 0.003 | W26: 8.419 | X26: 0.078 | Y26: 88.615 | Z26: 4.672 | AA26: 38 | AB26: 663 | AC26: Trocha | AE26: Sí | AF26: =IF(E26=0,0,(K26+L26+M26)/(K26+L26+M26+N26+O26)) -> 0.088437833 | AG26: =IF(J26>=MAX(H26,I26),"MOSAICO",IF(H26>=I26,"BES","ANDINO")) -> MOSAICO | AH26: =IF(AF26>=P_CORTE,"Alta","Moderada") -> Moderada | AI26: =INDEX(PAQ_T,MATCH(AG26&"|"&AH26,PAQ_KEY,0)) -> T6 | AJ26: 20 | AK26: 200302
A27: 64 | B27: HUANCABAMBA | C27: HUANCABAMBA | D27: C1081-Q9591 | E27: 35.774 | F27: 2645.8 | G27: 0.525448 | H27: 0 | I27: 0 | J27: 35.774 | K27: 0 | L27: 2.715 | M27: 12.131 | N27: 12.801 | O27: 8.145 | P27: 0.016 | Q27: 0.357 | R27: 1.256 | S27: 8.981 | T27: 25.164 | U27: 2.407 | V27: 0.308 | W27: 11.415 | X27: 0.711 | Y27: 20.323 | Z27: 0.61 | AA27: 196 | AB27: 502 | AC27: Sin afirmar | AE27: No | AF27: =IF(E27=0,0,(K27+L27+M27)/(K27+L27+M27+N27+O27)) -> 0.41478543 | AG27: =IF(J27>=MAX(H27,I27),"MOSAICO",IF(H27>=I27,"BES","ANDINO")) -> MOSAICO | AH27: =IF(AF27>=P_CORTE,"Alta","Moderada") -> Moderada | AI27: =INDEX(PAQ_T,MATCH(AG27&"|"&AH27,PAQ_KEY,0)) -> T6 | AJ27: 21 | AK27: 200301
A28: M30B5 | B28: HUANCABAMBA | C28: HUANCABAMBA | D28: C1081-Q9591 | E28: 90.903 | F28: 5622.2 | G28: 0.5564 | H28: 0 | I28: 16.267 | J28: 74.636 | K28: 0 | L28: 0.652 | M28: 29.389 | N28: 35.043 | O28: 25.858 | P28: 0.103 | Q28: 3.215 | R28: 10.735 | S28: 46.685 | T28: 30.166 | U28: 0.41 | V28: 0.24 | W28: 25.176 | X28: 4.202 | Y28: 51.265 | Z28: 9.612 | AA28: 0 | AB28: 313 | AC28: Trocha | AE28: No | AF28: =IF(E28=0,0,(K28+L28+M28)/(K28+L28+M28+N28+O28)) -> 0.33033142 | AG28: =IF(J28>=MAX(H28,I28),"MOSAICO",IF(H28>=I28,"BES","ANDINO")) -> MOSAICO | AH28: =IF(AF28>=P_CORTE,"Alta","Moderada") -> Moderada | AI28: =INDEX(PAQ_T,MATCH(AG28&"|"&AH28,PAQ_KEY,0)) -> T6 | AJ28: 22 | AK28: 200301
A29: 4 | B29: HUANCABAMBA | C29: HUARMACA | D29: C1076-Q9588 | E29: 230.098 | F29: 7181.6 | G29: 0.660111 | H29: 0 | I29: 0 | J29: 230.098 | K29: 0.693 | L29: 2.259 | M29: 18.289 | N29: 43.804 | O29: 165.129 | P29: 0.031 | Q29: 0.408 | R29: 2.15 | S29: 28.469 | T29: 199.04 | U29: 2.444 | V29: 0.507 | W29: 18.224 | X29: 0.054 | Y29: 206.842 | Z29: 2.028 | AA29: 29 | AB29: 804 | AC29: Trocha | AE29: No | AF29: =IF(E29=0,0,(K29+L29+M29)/(K29+L29+M29+N29+O29)) -> 0.09228236 | AG29: =IF(J29>=MAX(H29,I29),"MOSAICO",IF(H29>=I29,"BES","ANDINO")) -> MOSAICO | AH29: =IF(AF29>=P_CORTE,"Alta","Moderada") -> Moderada | AI29: =INDEX(PAQ_T,MATCH(AG29&"|"&AH29,PAQ_KEY,0)) -> T6 | AJ29: 23 | AK29: 200304
A30: M12B1 | B30: HUANCABAMBA | C30: HUARMACA | D30: C1076-Q9588 | E30: 268.393 | F30: 8005.8 | G30: 0.34753 | H30: 268.347 | I30: 0 | J30: 0.046 | K30: 42.174 | L30: 139.279 | M30: 77.998 | N30: 8.979 | O30: 0.119 | P30: 2.677 | Q30: 14.146 | R30: 54.914 | S30: 149.893 | T30: 46.763 | U30: 118.586 | V30: 62.763 | W30: 69.61 | X30: 8.349 | Y30: 8.459 | Z30: 0.625 | AA30: 26 | AB30: 676 | AC30: Trocha | AE30: No | AF30: =IF(E30=0,0,(K30+L30+M30)/(K30+L30+M30+N30+O30)) -> 0.96612164 | AG30: =IF(J30>=MAX(H30,I30),"MOSAICO",IF(H30>=I30,"BES","ANDINO")) -> BES | AH30: =IF(AF30>=P_CORTE,"Alta","Moderada") -> Alta | AI30: =INDEX(PAQ_T,MATCH(AG30&"|"&AH30,PAQ_KEY,0)) -> T1 | AJ30: 24 | AK30: 200304
... A32: M4B4 | B32: HUANCABAMBA | C32: HUARMACA | D32: C1076-Q9589 | E32: 289.914 | F32: 9333.8 | G32: 0.319788 | H32: 289.914 | I32: 0 | J32: 0 | K32: 60.464 | L32: 182.678 | M32: 44.711 | N32: 2.212 | O32: 0.01 | P32: 0.445 | Q32: 17.534 | R32: 81.049 | S32: 172.371 | T32: 18.515 | U32: 149.3 | V32: 93.719 | W32: 39.611 | X32: 5.066 | Y32: 1.975 | Z32: 0.244 | AA32: 0 | AB32: 525 | AC32: Trocha | AE32: No | AF32: =IF(E32=0,0,(K32+L32+M32)/(K32+L32+M32+N32+O32)) -> 0.99233991 | AG32: =IF(J32>=MAX(H32,I32),"MOSAICO",IF(H32>=I32,"BES","ANDINO")) -> BES | AH32: =IF(AF32>=P_CORTE,"Alta","Moderada") -> Alta | AI32: =INDEX(PAQ_T,MATCH(AG32&"|"&AH32,PAQ_KEY,0)) -> T1 | AJ32: 26 | AK32: 200304
A33: 18 | B33: HUANCABAMBA | C33: HUARMACA | D33: C1076-Q9592 | E33: 103.617 | F33: 5009.1 | G33: 0.640219 | H33: 94.298 | I33: 0 | J33: 9.319 | K33: 0 | L33: 0 | M33: 3.114 | N33: 31.503 | O33: 69.033 | P33: 0.016 | Q33: 0.211 | R33: 1.234 | S33: 22.999 | T33: 79.158 | U33: 0 | V33: 0 | W33: 3.028 | X33: 0.083 | Y33: 99.128 | Z33: 1.378 | AA33: 0 | AB33: 626 | AC33: Trocha | AE33: No | AF33: =IF(E33=0,0,(K33+L33+M33)/(K33+L33+M33+N33+O33)) -> 0.030043415 | AG33: =IF(J33>=MAX(H33,I33),"MOSAICO",IF(H33>=I33,"BES","ANDINO")) -> BES | AH33: =IF(AF33>=P_CORTE,"Alta","Moderada") -> Moderada | AI33: =INDEX(PAQ_T,MATCH(AG33&"|"&AH33,PAQ_KEY,0)) -> T2 | AJ33: 27 | AK33: 200304 | AM33: Microcuenca sin codigo M asignado
A34: 19 | B34: HUANCABAMBA | C34: HUARMACA | D34: C1076-Q9592 | E34: 82.088 | F34: 4507.3 | G34: 0.537184 | H34: 0 | I34: 42.246 | J34: 39.842 | K34: 0.006 | L34: 2.884 | M34: 32.117 | N34: 25.095 | O34: 22.008 | P34: 0.016 | Q34: 0.203 | R34: 1.343 | S34: 14.948 | T34: 65.578 | U34: 2.886 | V34: 0.002 | W34: 31.705 | X34: 0.404 | Y34: 45.935 | Z34: 1.156 | AA34: 1161 | AB34: 1578 | AC34: Trocha | AE34: No | AF34: =IF(E34=0,0,(K34+L34+M34)/(K34+L34+M34+N34+O34)) -> 0.42634271 | AG34: =IF(J34>=MAX(H34,I34),"MOSAICO",IF(H34>=I34,"BES","ANDINO")) -> ANDINO | AH34: =IF(AF34>=P_CORTE,"Alta","Moderada") -> Moderada | AI34: =INDEX(PAQ_T,MATCH(AG34&"|"&AH34,PAQ_KEY,0)) -> T4 | AJ34: 28 | AK34: 200304 | AM34: Microcuenca sin codigo M asignado
A35: 31 | B35: HUANCABAMBA | C35: HUARMACA | D35: C1076-Q9592 | E35: 47.581 | F35: 5706.2 | G35: 0.435805 | H35: 0 | I35: 47.581 | J35: 0 | K35: 0.579 | L35: 11.052 | M35: 25.696 | N35: 7.473 | O35: 2.803 | P35: 0.031 | Q35: 0.39 | R35: 1.24 | S35: 14.909 | T35: 31.011 | U35: 11 | V35: 0.624 | W35: 24.986 | X35: 0.701 | Y35: 9.934 | Z35: 0.336 | AA35: 0 | AB35: 774 | AC35: Trocha | AE35: Sí | AF35: =IF(E35=0,0,(K35+L35+M35)/(K35+L35+M35+N35+O35)) -> 0.78413125 | AG35: =IF(J35>=MAX(H35,I35),"MOSAICO",IF(H35>=I35,"BES","ANDINO")) -> ANDINO | AH35: =IF(AF35>=P_CORTE,"Alta","Moderada") -> Alta | AI35: =INDEX(PAQ_T,MATCH(AG35&"|"&AH35,PAQ_KEY,0)) -> T3 | AJ35: 29 | AK35: 200304 | AM35: Microcuenca sin codigo M asignado
A36: 41 | B36: HUANCABAMBA | C36: HUARMACA | D36: C1076-Q9592 | E36: 64.923 | F36: 4653.2 | G36: 0.592669 | H36: 0 | I36: 0 | J36: 64.923 | K36: 0 | L36: 0.244 | M36: 7.719 | N36: 29.546 | O36: 27.428 | P36: 0 | Q36: 0.047 | R36: 1.561 | S36: 25.096 | T36: 38.219 | U36: 0.24 | V36: 0.003 | W36: 7.569 | X36: 0.15 | Y36: 55.507 | Z36: 1.455 | AA36: 853 | AB36: 1235 | AC36: Trocha | AE36: No | AF36: =IF(E36=0,0,(K36+L36+M36)/(K36+L36+M36+N36+O36)) -> 0.12262655 | AG36: =IF(J36>=MAX(H36,I36),"MOSAICO",IF(H36>=I36,"BES","ANDINO")) -> MOSAICO | AH36: =IF(AF36>=P_CORTE,"Alta","Moderada") -> Moderada | AI36: =INDEX(PAQ_T,MATCH(AG36&"|"&AH36,PAQ_KEY,0)) -> T6 | AJ36: 30 | AK36: 200304 | AM36: Microcuenca sin codigo M asignado
A37: 53 | B37: HUANCABAMBA | C37: HUARMACA | D37: C1076-Q9592 | E37: 13.065 | F37: 2208.6 | G37: 0.596277 | H37: 0 | I37: 13.065 | J37: 0 | K37: 0 | L37: 0.099 | M37: 1.529 | N37: 5.865 | O37: 5.577 | P37: 0.016 | Q37: 0.196 | R37: 0.641 | S37: 3.667 | T37: 8.545 | U37: 0.099 | V37: 0 | W37: 1.4 | X37: 0.127 | Y37: 10.713 | Z37: 0.726 | AA37: 214 | AB37: 384 | AC37: Trocha | AE37: No | AF37: =IF(E37=0,0,(K37+L37+M37)/(K37+L37+M37+N37+O37)) -> 0.12456006 | AG37: =IF(J37>=MAX(H37,I37),"MOSAICO",IF(H37>=I37,"BES","ANDINO")) -> ANDINO | AH37: =IF(AF37>=P_CORTE,"Alta","Moderada") -> Moderada | AI37: =INDEX(PAQ_T,MATCH(AG37&"|"&AH37,PAQ_KEY,0)) -> T4 | AJ37: 31 | AK37: 200304 | AM37: Microcuenca sin codigo M asignado
A38: 69 | B38: HUANCABAMBA | C38: HUARMACA | D38: C1076-Q9592 | E38: 19.425 | F38: 2260.3 | G38: 0.448926 | H38: 0 | I38: 19.03 | J38: 0.395 | K38: 0 | L38: 2.481 | M38: 13.313 | N38: 1.973 | O38: 1.667 | P38: 0 | Q38: 0.187 | R38: 0.232 | S38: 4.074 | T38: 14.933 | U38: 2.476 | V38: 0 | W38: 12.907 | X38: 0.404 | Y38: 3.623 | Z38: 0.015 | AA38: 402 | AB38: 867 | AC38: Trocha | AE38: No | AF38: =IF(E38=0,0,(K38+L38+M38)/(K38+L38+M38+N38+O38)) -> 0.81269939 | AG38: =IF(J38>=MAX(H38,I38),"MOSAICO",IF(H38>=I38,"BES","ANDINO")) -> ANDINO | AH38: =IF(AF38>=P_CORTE,"Alta","Moderada") -> Alta | AI38: =INDEX(PAQ_T,MATCH(AG38&"|"&AH38,PAQ_KEY,0)) -> T3 | AJ38: 32 | AK38: 200304 | AM38: Microcuenca sin codigo M asignado
A39: 70 | B39: HUANCABAMBA | C39: HUARMACA | D39: C1076-Q9592 | E39: 22.388 | F39: 2128.2 | G39: 0.622295 | H39: 0 | I39: 22.127 | J39: 0.261 | K39: 0 | L39: 0 | M39: 1.091 | N39: 8.435 | O39: 12.868 | P39: 0 | Q39: 0.375 | R39: 2.48 | S39: 7.894 | T39: 11.639 | U39: 0 | V39: 0 | W39: 0.528 | X39: 0.562 | Y39: 19.006 | Z39: 2.292 | AA39: 2 | AB39: 202 | AC39: Trocha | AE39: No | AF39: =IF(E39=0,0,(K39+L39+M39)/(K39+L39+M39+N39+O39)) -> 0.048718407 | AG39: =IF(J39>=MAX(H39,I39),"MOSAICO",IF(H39>=I39,"BES","ANDINO")) -> ANDINO | AH39: =IF(AF39>=P_CORTE,"Alta","Moderada") -> Moderada | AI39: =INDEX(PAQ_T,MATCH(AG39&"|"&AH39,PAQ_KEY,0)) -> T4 | AJ39: 33 | AK39: 200304 | AM39: Microcuenca sin codigo M asignado
A40: 72 | B40: HUANCABAMBA | C40: HUARMACA | D40: C1076-Q9592 | E40: 12.398 | F40: 1390 | G40: 0.518477 | H40: 0 | I40: 0 | J40: 12.398 | K40: 0 | L40: 0.081 | M40: 5.047 | N40: 6.077 | O40: 1.195 | P40: 0 | Q40: 0 | R40: 0 | S40: 2.904 | T40: 9.494 | U40: 0.081 | V40: 0 | W40: 5.046 | X40: 0 | Y40: 7.271 | Z40: 0 | AA40: 770 | AB40: 942 | AC40: Trocha | AE40: No | AF40: =IF(E40=0,0,(K40+L40+M40)/(K40+L40+M40+N40+O40)) -> 0.41354839 | AG40: =IF(J40>=MAX(H40,I40),"MOSAICO",IF(H40>=I40,"BES","ANDINO")) -> MOSAICO | AH40: =IF(AF40>=P_CORTE,"Alta","Moderada") -> Moderada | AI40: =INDEX(PAQ_T,MATCH(AG40&"|"&AH40,PAQ_KEY,0)) -> T6 | AJ40: 34 | AK40: 200304 | AM40: Microcuenca sin codigo M asignado
A41: 73 | B41: HUANCABAMBA | C41: HUARMACA | D41: C1076-Q9592 | E41: 54.29 | F41: 3135.9 | G41: 0.554974 | H41: 0 | I41: 0 | J41: 54.29 | K41: 0 | L41: 0.962 | M41: 9.321 | N41: 32.849 | O41: 11.174 | P41: 0 | Q41: 0 | R41: 0.047 | S41: 2.32 | T41: 51.924 | U41: 0.962 | V41: 0 | W41: 9.318 | X41: 0 | Y41: 43.963 | Z41: 0.047 | AA41: 111 | AB41: 598 | AC41: Trocha | AE41: Sí | AF41: =IF(E41=0,0,(K41+L41+M41)/(K41+L41+M41+N41+O41)) -> 0.18935293 | AG41: =IF(J41>=MAX(H41,I41),"MOSAICO",IF(H41>=I41,"BES","ANDINO")) -> MOSAICO | AH41: =IF(AF41>=P_CORTE,"Alta","Moderada") -> Moderada | AI41: =INDEX(PAQ_T,MATCH(AG41&"|"&AH41,PAQ_KEY,0)) -> T6 | AJ41: 35 | AK41: 200304 | AM41: Microcuenca sin codigo M asignado
A42: 8 | B42: HUANCABAMBA | C42: HUARMACA | D42: C1076-Q9593 | E42: 126.952 | F42: 5559 | G42: 0.554802 | H42: 0 | I42: 121.817 | J42: 5.135 | K42: 0.053 | L42: 4.367 | M42: 31.657 | N42: 54.04 | O42: 36.889 | P42: 0.078 | Q42: 1.225 | R42: 3.476 | S42: 28.351 | T42: 93.822 | U42: 3.841 | V42: 0.572 | W42: 29.963 | X42: 1.682 | Y42: 88.368 | Z42: 2.525 | AA42: 5 | AB42: 296 | AC42: Trocha | AE42: No | AF42: =IF(E42=0,0,(K42+L42+M42)/(K42+L42+M42+N42+O42)) -> 0.28405745 | AG42: =IF(J42>=MAX(H42,I42),"MOSAICO",IF(H42>=I42,"BES","ANDINO")) -> ANDINO | AH42: =IF(AF42>=P_CORTE,"Alta","Moderada") -> Moderada | AI42: =INDEX(PAQ_T,MATCH(AG42&"|"&AH42,PAQ_KEY,0)) -> T4 | AJ42: 36 | AK42: 200304 | AL42: 94.685 | AM42: Reporte de superposición de área 94.685 ha con Catastro minero: Zafiro Mining S.A.C. – LM30 (010524926)
A43: 10 | B43: HUANCABAMBA | C43: HUARMACA | D43: C1076-Q9593 | E43: 150.214 | F43: 6238.1 | G43: 0.546492 | H43: 129.386 | I43: 0 | J43: 20.828 | K43: 1.634 | L43: 5.454 | M43: 35.773 | N43: 70.696 | O43: 36.748 | P43: 0.094 | Q43: 2.517 | R43: 7.294 | S43: 42.673 | T43: 97.637 | U43: 5.766 | V43: 1.312 | W43: 33.334 | X43: 2.417 | Y43: 101.21 | Z43: 6.175 | AA43: 0 | AB43: 352 | AC43: Trocha | AE43: No | AF43: =IF(E43=0,0,(K43+L43+M43)/(K43+L43+M43+N43+O43)) -> 0.28516017 | AG43: =IF(J43>=MAX(H43,I43),"MOSAICO",IF(H43>=I43,"BES","ANDINO")) -> BES | AH43: =IF(AF43>=P_CORTE,"Alta","Moderada") -> Moderada | AI43: =INDEX(PAQ_T,MATCH(AG43&"|"&AH43,PAQ_KEY,0)) -> T2 | AJ43: 37 | AK43: 200304 | AM43: Microcuenca sin codigo M asignado
A44: 16 | B44: HUANCABAMBA | C44: HUARMACA | D44: C1076-Q9593 | E44: 83.327 | F44: 4957.4 | G44: 0.628423 | H44: 37.687 | I44: 0 | J44: 45.641 | K44: 0 | L44: 0.195 | M44: 5.889 | N44: 29.377 | O44: 47.897 | P44: 0.219 | Q44: 1.821 | R44: 10.962 | S44: 35.544 | T44: 34.783 | U44: 0.143 | V44: 0.051 | W44: 4.823 | X44: 1.064 | Y44: 65.36 | Z44: 11.886 | AA44: 13 | AB44: 235 | AC44: Trocha | AE44: No | AF44: =IF(E44=0,0,(K44+L44+M44)/(K44+L44+M44+N44+O44)) -> 0.072986396 | AG44: =IF(J44>=MAX(H44,I44),"MOSAICO",IF(H44>=I44,"BES","ANDINO")) -> MOSAICO | AH44: =IF(AF44>=P_CORTE,"Alta","Moderada") -> Moderada | AI44: =INDEX(PAQ_T,MATCH(AG44&"|"&AH44,PAQ_KEY,0)) -> T6 | AJ44: 38 | AK44: 200304 | AM44: Microcuenca sin codigo M asignado
A45: 20 | B45: HUANCABAMBA | C45: HUARMACA | D45: C1076-Q9593 | E45: 81.334 | F45: 3732.4 | G45: 0.48513 | H45: 42.284 | I45: 39.05 | J45: 0 | K45: 0 | L45: 5.625 | M45: 42.577 | N45: 28.216 | O45: 4.974 | P45: 0 | Q45: 0.335 | R45: 2.529 | S45: 36.164 | T45: 42.306 | U45: 5.55 | V45: 0.063 | W45: 41.206 | X45: 1.352 | Y45: 31.713 | Z45: 1.449 | AA45: 457 | AB45: 1018 | AC45: Trocha | AE45: No | AF45: =IF(E45=0,0,(K45+L45+M45)/(K45+L45+M45+N45+O45)) -> 0.59222037 | AG45: =IF(J45>=MAX(H45,I45),"MOSAICO",IF(H45>=I45,"BES","ANDINO")) -> BES | AH45: =IF(AF45>=P_CORTE,"Alta","Moderada") -> Alta | AI45: =INDEX(PAQ_T,MATCH(AG45&"|"&AH45,PAQ_KEY,0)) -> T1 | AJ45: 39 | AK45: 200304 | AM45: Microcuenca sin codigo M asignado
A46: 51 | B46: HUANCABAMBA | C46: HUARMACA | D46: C1076-Q9593 | E46: 22.927 | F46: 2582.9 | G46: 0.523788 | H46: 0 | I46: 2.696 | J46: 20.231 | K46: 0 | L46: 1.567 | M46: 6.379 | N46: 11.478 | O46: 3.52 | P46: 0 | Q46: 0.061 | R46: 0.306 | S46: 4.42 | T46: 18.141 | U46: 1.564 | V46: 0.002 | W46: 6.317 | X46: 0.056 | Y46: 14.679 | Z46: 0.308 | AA46: 4 | AB46: 185 | AC46: Trocha | AE46: No | AF46: =IF(E46=0,0,(K46+L46+M46)/(K46+L46+M46+N46+O46)) -> 0.34632148 | AG46: =IF(J46>=MAX(H46,I46),"MOSAICO",IF(H46>=I46,"BES","ANDINO")) -> MOSAICO | AH46: =IF(AF46>=P_CORTE,"Alta","Moderada") -> Moderada | AI46: =INDEX(PAQ_T,MATCH(AG46&"|"&AH46,PAQ_KEY,0)) -> T6 | AJ46: 40 | AK46: 200304 | AM46: Microcuenca sin codigo M asignado
A47: 71 | B47: HUANCABAMBA | C47: HUARMACA | D47: C1076-Q9593 | E47: 10.673 | F47: 1816.8 | G47: 0.557066 | H47: 0 | I47: 10.673 | J47: 0 | K47: 0 | L47: 0.081 | M47: 2.69 | N47: 5.117 | O47: 2.791 | P47: 0 | Q47: 0.007 | R47: 0.135 | S47: 2.794 | T47: 7.737 | U47: 0.08 | V47: 0 | W47: 2.679 | X47: 0.01 | Y47: 7.773 | Z47: 0.132 | AA47: 23 | AB47: 89 | AC47: Trocha | AE47: No | AF47: =IF(E47=0,0,(K47+L47+M47)/(K47+L47+M47+N47+O47)) -> 0.25948122 | AG47: =IF(J47>=MAX(H47,I47),"MOSAICO",IF(H47>=I47,"BES","ANDINO")) -> ANDINO | AH47: =IF(AF47>=P_CORTE,"Alta","Moderada") -> Moderada | AI47: =INDEX(PAQ_T,MATCH(AG47&"|"&AH47,PAQ_KEY,0)) -> T4 | AJ47: 41 | AK47: 200304 | AL47: 4.266 | AM47: Reporte de superposición de área 4.266 ha con Catastro minero: Zafiro Mining S.A.C. – LM30 (010524926)
A48: 76 | B48: HUANCABAMBA | C48: HUARMACA | D48: C1076-Q9593 | E48: 19.615 | F48: 2083.6 | G48: 0.492462 | H48: 0 | I48: 0 | J48: 19.615 | K48: 0 | L48: 1.614 | M48: 9.008 | N48: 7.143 | O48: 1.855 | P48: 0 | Q48: 0.075 | R48: 0.799 | S48: 7.24 | T48: 11.501 | U48: 1.449 | V48: 0.165 | W48: 8.327 | X48: 0.678 | Y48: 8.966 | Z48: 0.03 | AA48: 1348 | AB48: 1543 | AC48: Trocha | AE48: No | AF48: =IF(E48=0,0,(K48+L48+M48)/(K48+L48+M48+N48+O48)) -> 0.54138634 | AG48: =IF(J48>=MAX(H48,I48),"MOSAICO",IF(H48>=I48,"BES","ANDINO")) -> MOSAICO | AH48: =IF(AF48>=P_CORTE,"Alta","Moderada") -> Alta | AI48: =INDEX(PAQ_T,MATCH(AG48&"|"&AH48,PAQ_KEY,0)) -> T5 | AJ48: 42 | AK48: 200304 | AM48: Microcuenca sin codigo M asignado
A49: 80 | B49: HUANCABAMBA | C49: HUARMACA | D49: C1076-Q9593 | E49: 28.83 | F49: 2861.3 | G49: 0.593069 | H49: 0 | I49: 0 | J49: 28.83 | K49: 0.06 | L49: 0.869 | M49: 3.944 | N49: 9.67 | O49: 14.3 | P49: 0 | Q49: 0.003 | R49: 0.12 | S49: 2.92 | T49: 25.787 | U49: 0.928 | V49: 0 | W49: 3.937 | X49: 0.003 | Y49: 23.842 | Z49: 0.121 | AA49: 18 | AB49: 190 | AC49: Trocha | AE49: No | AF49: =IF(E49=0,0,(K49+L49+M49)/(K49+L49+M49+N49+O49)) -> 0.16894914 | AG49: =IF(J49>=MAX(H49,I49),"MOSAICO",IF(H49>=I49,"BES","ANDINO")) -> MOSAICO | AH49: =IF(AF49>=P_CORTE,"Alta","Moderada") -> Moderada | AI49: =INDEX(PAQ_T,MATCH(AG49&"|"&AH49,PAQ_KEY,0)) -> T6 | AJ49: 43 | AK49: 200304 | AM49: Microcuenca sin codigo M asignado
A50: 34 | B50: HUANCABAMBA | C50: LALAQUIZ | D50: C1081-Q9590 | E50: 28.45 | F50: 2570 | G50: 0.648975 | H50: 0 | I50: 1.517 | J50: 26.933 | K50: 0 | L50: 0 | M50: 0.05 | N50: 10.448 | O50: 17.966 | P50: 0 | Q50: 0.007 | R50: 0.857 | S50: 7.753 | T50: 19.833 | U50: 0 | V50: 0 | W50: 0.049 | X50: 0 | Y50: 27.536 | Z50: 0.865 | AA50: 0 | AB50: 187 | AC50: Trocha | AE50: No | AF50: =IF(E50=0,0,(K50+L50+M50)/(K50+L50+M50+N50+O50)) -> 0.0017566048 | AG50: =IF(J50>=MAX(H50,I50),"MOSAICO",IF(H50>=I50,"BES","ANDINO")) -> MOSAICO | AH50: =IF(AF50>=P_CORTE,"Alta","Moderada") -> Moderada | AI50: =INDEX(PAQ_T,MATCH(AG50&"|"&AH50,PAQ_KEY,0)) -> T6 | AJ50: 44 | AK50: 200305 | AM50: Microcuenca sin codigo M asignado
A51: 38 | B51: HUANCABAMBA | C51: LALAQUIZ | D51: C1081-Q9590 | E51: 44.201 | F51: 3297.4 | G51: 0.672487 | H51: 3.885 | I51: 0.622 | J51: 39.693 | K51: 0 | L51: 0 | M51: 0.181 | N51: 11.551 | O51: 32.486 | P51: 0 | Q51: 0.003 | R51: 1.229 | S51: 21.519 | T51: 21.449 | U51: 0 | V51: 0 | W51: 0.166 | X51: 0.015 | Y51: 42.803 | Z51: 1.217 | AA51: 13 | AB51: 166 | AC51: Trocha | AE51: No | AF51: =IF(E51=0,0,(K51+L51+M51)/(K51+L51+M51+N51+O51)) -> 0.0040933556 | AG51: =IF(J51>=MAX(H51,I51),"MOSAICO",IF(H51>=I51,"BES","ANDINO")) -> MOSAICO | AH51: =IF(AF51>=P_CORTE,"Alta","Moderada") -> Moderada | AI51: =INDEX(PAQ_T,MATCH(AG51&"|"&AH51,PAQ_KEY,0)) -> T6 | AJ51: 45 | AK51: 200305 | AM51: Microcuenca sin codigo M asignado
A52: 50 | B52: HUANCABAMBA | C52: LALAQUIZ | D52: C1081-Q9590 | E52: 19.266 | F52: 1917.2 | G52: 0.68307 | H52: 0 | I52: 18.45 | J52: 0.817 | K52: 0 | L52: 0 | M52: 0.069 | N52: 3.557 | O52: 15.647 | P52: 0.016 | Q52: 0.091 | R52: 0.445 | S52: 3.254 | T52: 15.461 | U52: 0 | V52: 0 | W52: 0.069 | X52: 0 | Y52: 18.646 | Z52: 0.552 | AA52: 0 | AB52: 129 | AC52: Trocha | AE52: No | AF52: =IF(E52=0,0,(K52+L52+M52)/(K52+L52+M52+N52+O52)) -> 0.003580138 | AG52: =IF(J52>=MAX(H52,I52),"MOSAICO",IF(H52>=I52,"BES","ANDINO")) -> ANDINO | AH52: =IF(AF52>=P_CORTE,"Alta","Moderada") -> Moderada | AI52: =INDEX(PAQ_T,MATCH(AG52&"|"&AH52,PAQ_KEY,0)) -> T4 | AJ52: 46 | AK52: 200305 | AM52: Microcuenca sin codigo M asignado
A53: 61 | B53: HUANCABAMBA | C53: LALAQUIZ | D53: C1081-Q9590 | E53: 26.826 | F53: 1957.6 | G53: 0.611186 | H53: 0 | I53: 12.838 | J53: 13.988 | K53: 0 | L53: 0.219 | M53: 5.443 | N53: 8.822 | O53: 12.352 | P53: 0.028 | Q53: 0.087 | R53: 1.298 | S53: 14.728 | T53: 10.685 | U53: 0.218 | V53: 0 | W53: 5.309 | X53: 0.133 | Y53: 19.886 | Z53: 1.28 | AA53: 0 | AB53: 154 | AC53: Afirmado | AE53: No | AF53: =IF(E53=0,0,(K53+L53+M53)/(K53+L53+M53+N53+O53)) -> 0.21098524 | AG53: =IF(J53>=MAX(H53,I53),"MOSAICO",IF(H53>=I53,"BES","ANDINO")) -> MOSAICO | AH53: =IF(AF53>=P_CORTE,"Alta","Moderada") -> Moderada | AI53: =INDEX(PAQ_T,MATCH(AG53&"|"&AH53,PAQ_KEY,0)) -> T6 | AJ53: 47 | AK53: 200305 | AM53: Microcuenca sin codigo M asignado
A54: 26 | B54: HUANCABAMBA | C54: LALAQUIZ | D54: C1081-Q9591 | E54: 46.962 | F54: 3375.3 | G54: 0.673303 | H54: 0 | I54: 0 | J54: 46.962 | K54: 0 | L54: 0 | M54: 1.107 | N54: 9.75 | O54: 36.125 | P54: 0.016 | Q54: 0 | R54: 0.197 | S54: 6.697 | T54: 40.052 | U54: 0 | V54: 0 | W54: 1.102 | X54: 0 | Y54: 45.647 | Z54: 0.212 | AA54: 25 | AB54: 389 | AC54: Sin afirmar | AE54: No | AF54: =IF(E54=0,0,(K54+L54+M54)/(K54+L54+M54+N54+O54)) -> 0.023562215 | AG54: =IF(J54>=MAX(H54,I54),"MOSAICO",IF(H54>=I54,"BES","ANDINO")) -> MOSAICO | AH54: =IF(AF54>=P_CORTE,"Alta","Moderada") -> Moderada | AI54: =INDEX(PAQ_T,MATCH(AG54&"|"&AH54,PAQ_KEY,0)) -> T6 | AJ54: 48 | AK54: 200305
A55: 37 | B55: HUANCABAMBA | C55: LALAQUIZ | D55: C1081-Q9591 | E55: 35.491 | F55: 2357.2 | G55: 0.658846 | H55: 0 | I55: 21.286 | J55: 14.205 | K55: 0 | L55: 0 | M55: 0.682 | N55: 8.054 | O55: 26.772 | P55: 0 | Q55: 0.07 | R55: 2.061 | S55: 17.296 | T55: 16.064 | U55: 0 | V55: 0 | W55: 0.68 | X55: 0 | Y55: 32.679 | Z55: 2.131 | AA55: 27 | AB55: 311 | AC55: Sin afirmar | AE55: No | AF55: =IF(E55=0,0,(K55+L55+M55)/(K55+L55+M55+N55+O55)) -> 0.019206939 | AG55: =IF(J55>=MAX(H55,I55),"MOSAICO",IF(H55>=I55,"BES","ANDINO")) -> ANDINO | AH55: =IF(AF55>=P_CORTE,"Alta","Moderada") -> Moderada | AI55: =INDEX(PAQ_T,MATCH(AG55&"|"&AH55,PAQ_KEY,0)) -> T4 | AJ55: 49 | AK55: 200305
A56: M2B8 | B56: HUANCABAMBA | C56: SAN MIGUEL DE EL FAIQUE | D56: C1076-Q9584 | E56: 116.099 | F56: 4620.1 | G56: 0.375171 | H56: 116.099 | I56: 0 | J56: 0 | K56: 8.748 | L56: 54.47 | M56: 44.02 | N56: 8.917 | O56: 0.02 | P56: 5.016 | Q56: 24.966 | R56: 11.082 | S56: 30.248 | T56: 44.786 | U56: 24.744 | V56: 38.43 | W56: 41.545 | X56: 2.454 | Y56: 8.745 | Z56: 0.181 | AA56: 1006 | AB56: 1783 | AC56: Trocha | AE56: No | AF56: =IF(E56=0,0,(K56+L56+M56)/(K56+L56+M56+N56+O56)) -> 0.92307295 | AG56: =IF(J56>=MAX(H56,I56),"MOSAICO",IF(H56>=I56,"BES","ANDINO")) -> BES | AH56: =IF(AF56>=P_CORTE,"Alta","Moderada") -> Alta | AI56: =INDEX(PAQ_T,MATCH(AG56&"|"&AH56,PAQ_KEY,0)) -> T1 | AJ56: 50 | AK56: 200306
A57: M20B1 | B57: HUANCABAMBA | C57: SAN MIGUEL DE EL FAIQUE | D57: C1076-Q9585 | E57: 279.68 | F57: 11210.1 | G57: 0.355329 | H57: 277.098 | I57: 0 | J57: 2.582 | K57: 15.58 | L57: 174.778 | M57: 81.598 | N57: 7.619 | O57: 0.269 | P57: 9.824 | Q57: 56.265 | R57: 63.958 | S57: 102.974 | T57: 46.659 | U57: 79.494 | V57: 110.762 | W57: 64.404 | X57: 17.144 | Y57: 5.734 | Z57: 2.142 | AA57: 1316 | AB57: 1966 | AC57: Trocha | AE57: No | AF57: =IF(E57=0,0,(K57+L57+M57)/(K57+L57+M57+N57+O57)) -> 0.97181287 | AG57: =IF(J57>=MAX(H57,I57),"MOSAICO",IF(H57>=I57,"BES","ANDINO")) -> BES | AH57: =IF(AF57>=P_CORTE,"Alta","Moderada") -> Alta | AI57: =INDEX(PAQ_T,MATCH(AG57&"|"&AH57,PAQ_KEY,0)) -> T1 | AJ57: 51 | AK57: 200306
A58: 9 | B58: HUANCABAMBA | C58: SAN MIGUEL DE EL FAIQUE | D58: C1076-Q9586 | E58: 109.861 | F58: 4834.7 | G58: 0.574527 | H58: 0 | I58: 0 | J58: 109.861 | K58: 0 | L58: 0.418 | M58: 12.43 | N58: 67.203 | O58: 29.853 | P58: 0 | Q58: 0.016 | R58: 0.764 | S58: 9.277 | T58: 99.804 | U58: 0.415 | V58: 0 | W58: 12.344 | X58: 0.077 | Y58: 96.323 | Z58: 0.703 | AA58: 831 | AB58: 1410 | AC58: Trocha | AE58: No | AF58: =IF(E58=0,0,(K58+L58+M58)/(K58+L58+M58+N58+O58)) -> 0.11690202 | AG58: =IF(J58>=MAX(H58,I58),"MOSAICO",IF(H58>=I58,"BES","ANDINO")) -> MOSAICO | AH58: =IF(AF58>=P_CORTE,"Alta","Moderada") -> Moderada | AI58: =INDEX(PAQ_T,MATCH(AG58&"|"&AH58,PAQ_KEY,0)) -> T6 | AJ58: 52 | AK58: 200306
A59: 35 | B59: HUANCABAMBA | C59: SAN MIGUEL DE EL FAIQUE | D59: C1076-Q9586 | E59: 30.804 | F59: 2903.6 | G59: 0.624477 | H59: 0 | I59: 0 | J59: 30.804 | K59: 0 | L59: 0.008 | M59: 0.358 | N59: 12.588 | O59: 17.859 | P59: 0 | Q59: 0.062 | R59: 0.25 | S59: 2.266 | T59: 28.226 | U59: 0.007 | V59: 0 | W59: 0.353 | X59: 0.006 | Y59: 30.132 | Z59: 0.306 | AA59: 472 | AB59: 850 | AC59: Trocha | AE59: No | AF59: =IF(E59=0,0,(K59+L59+M59)/(K59+L59+M59+N59+O59)) -> 0.011878103 | AG59: =IF(J59>=MAX(H59,I59),"MOSAICO",IF(H59>=I59,"BES","ANDINO")) -> MOSAICO | AH59: =IF(AF59>=P_CORTE,"Alta","Moderada") -> Moderada | AI59: =INDEX(PAQ_T,MATCH(AG59&"|"&AH59,PAQ_KEY,0)) -> T6 | AJ59: 53 | AK59: 200306
A60: 43 | B60: HUANCABAMBA | C60: SAN MIGUEL DE EL FAIQUE | D60: C1076-Q9586 | E60: 23.171 | F60: 2284.3 | G60: 0.551525 | H60: 0 | I60: 0 | J60: 23.171 | K60: 0.139 | L60: 0.753 | M60: 4.047 | N60: 13.434 | O60: 4.817 | P60: 0 | Q60: 0.325 | R60: 0.42 | S60: 2.39 | T60: 20.037 | U60: 0.891 | V60: 0 | W60: 3.75 | X60: 0.29 | Y60: 17.785 | Z60: 0.455 | AA60: 0 | AB60: 46 | AC60: Trocha | AE60: No | AF60: =IF(E60=0,0,(K60+L60+M60)/(K60+L60+M60+N60+O60)) -> 0.21297973 | AG60: =IF(J60>=MAX(H60,I60),"MOSAICO",IF(H60>=I60,"BES","ANDINO")) -> MOSAICO | AH60: =IF(AF60>=P_CORTE,"Alta","Moderada") -> Moderada | AI60: =INDEX(PAQ_T,MATCH(AG60&"|"&AH60,PAQ_KEY,0)) -> T6 | AJ60: 54 | AK60: 200306
A61: 44 | B61: HUANCABAMBA | C61: SAN MIGUEL DE EL FAIQUE | D61: C1076-Q9586 | E61: 28.234 | F61: 2377.1 | G61: 0.511324 | H61: 0 | I61: 28.234 | J61: 0 | K61: 0 | L61: 0 | M61: 14.704 | N61: 11.392 | O61: 2.147 | P61: 0.03 | Q61: 0.872 | R61: 2.868 | S61: 12.798 | T61: 11.666 | U61: 0 | V61: 0 | W61: 12.658 | X61: 2.041 | Y61: 11.806 | Z61: 1.729 | AA61: 0 | AB61: 113 | AC61: Trocha | AE61: No | AF61: =IF(E61=0,0,(K61+L61+M61)/(K61+L61+M61+N61+O61)) -> 0.52062458 | AG61: =IF(J61>=MAX(H61,I61),"MOSAICO",IF(H61>=I61,"BES","ANDINO")) -> ANDINO | AH61: =IF(AF61>=P_CORTE,"Alta","Moderada") -> Alta | AI61: =INDEX(PAQ_T,MATCH(AG61&"|"&AH61,PAQ_KEY,0)) -> T3 | AJ61: 55 | AK61: 200306
A62: 47 | B62: HUANCABAMBA | C62: SAN MIGUEL DE EL FAIQUE | D62: C1076-Q9586 | E62: 13.551 | F62: 1783.1 | G62: 0.593628 | H62: 0 | I62: 7.326 | J62: 6.225 | K62: 0 | L62: 0 | M62: 1.336 | N62: 6.629 | O62: 5.591 | P62: 0 | Q62: 0.094 | R62: 0.219 | S62: 2.218 | T62: 11.02 | U62: 0 | V62: 0 | W62: 1.277 | X62: 0.057 | Y62: 11.961 | Z62: 0.257 | AA62: 348 | AB62: 580 | AC62: Sin afirmar | AE62: No | AF62: =IF(E62=0,0,(K62+L62+M62)/(K62+L62+M62+N62+O62)) -> 0.098554146 | AG62: =IF(J62>=MAX(H62,I62),"MOSAICO",IF(H62>=I62,"BES","ANDINO")) -> ANDINO | AH62: =IF(AF62>=P_CORTE,"Alta","Moderada") -> Moderada | AI62: =INDEX(PAQ_T,MATCH(AG62&"|"&AH62,PAQ_KEY,0)) -> T4 | AJ62: 56 | AK62: 200306
A63: 67 | B63: HUANCABAMBA | C63: SAN MIGUEL DE EL FAIQUE | D63: C1076-Q9586 | E63: 13.184 | F63: 1713.1 | G63: 0.605293 | H63: 0.919 | I63: 0 | J63: 12.265 | K63: 0 | L63: 0 | M63: 0.281 | N63: 6.398 | O63: 6.509 | P63: 0 | Q63: 0.005 | R63: 0.096 | S63: 1.725 | T63: 11.358 | U63: 0 | V63: 0 | W63: 0.279 | X63: 0 | Y63: 12.804 | Z63: 0.101 | AA63: 137 | AB63: 505 | AC63: Trocha | AE63: No | AF63: =IF(E63=0,0,(K63+L63+M63)/(K63+L63+M63+N63+O63)) -> 0.021307249 | AG63: =IF(J63>=MAX(H63,I63),"MOSAICO",IF(H63>=I63,"BES","ANDINO")) -> MOSAICO | AH63: =IF(AF63>=P_CORTE,"Alta","Moderada") -> Moderada | AI63: =INDEX(PAQ_T,MATCH(AG63&"|"&AH63,PAQ_KEY,0)) -> T6 | AJ63: 57 | AK63: 200306
A64: M22B1 | B64: HUANCABAMBA | C64: SAN MIGUEL DE EL FAIQUE | D64: C1076-Q9586 | E64: 55.17 | F64: 3481.5 | G64: 0.594025 | H64: 0 | I64: 55.17 | J64: 0 | K64: 0 | L64: 0 | M64: 2.269 | N64: 34.503 | O64: 18.414 | P64: 0.045 | Q64: 2.188 | R64: 8.868 | S64: 29.086 | T64: 14.982 | U64: 0 | V64: 0 | W64: 1.272 | X64: 0.992 | Y64: 42.796 | Z64: 10.109 | AA64: 28 | AB64: 360 | AC64: Sin afirmar | AE64: No | AF64: =IF(E64=0,0,(K64+L64+M64)/(K64+L64+M64+N64+O64)) -> 0.0411155 | AG64: =IF(J64>=MAX(H64,I64),"MOSAICO",IF(H64>=I64,"BES","ANDINO")) -> ANDINO | AH64: =IF(AF64>=P_CORTE,"Alta","Moderada") -> Moderada | AI64: =INDEX(PAQ_T,MATCH(AG64&"|"&AH64,PAQ_KEY,0)) -> T4 | AJ64: 58 | AK64: 200306
A65: 5 | B65: MORROPON | C65: BUENOS AIRES | D65: C1077-Q9566 | E65: 295.726 | F65: 8425 | G65: 0.3394 | H65: 295.726 | I65: 0 | J65: 0 | K65: 33.518 | L65: 187.064 | M65: 74.931 | N65: 0.447 | O65: 0 | P65: 8.336 | Q65: 27.519 | R65: 38.983 | S65: 151.273 | T65: 69.615 | U65: 151.941 | V65: 68.484 | W65: 68.502 | X65: 6.353 | Y65: 0.445 | Z65: 0 | AA65: 3690 | AB65: 5228 | AC65: Sin afirmar | AE65: No | AF65: =IF(E65=0,0,(K65+L65+M65)/(K65+L65+M65+N65+O65)) -> 0.99848966 | AG65: =IF(J65>=MAX(H65,I65),"MOSAICO",IF(H65>=I65,"BES","ANDINO")) -> BES | AH65: =IF(AF65>=P_CORTE,"Alta","Moderada") -> Alta | AI65: =INDEX(PAQ_T,MATCH(AG65&"|"&AH65,PAQ_KEY,0)) -> T1 | AJ65: 59 | AK65: 200402 | AL65: 10.986 | AM65: Superposición con Zona de Arqueología 10.986 ha: Sitio Arqueológico Juan Velasco Alvarado 4 (RD N° 152, 16-10-2024)
A66: M6B10 | B66: MORROPON | C66: BUENOS AIRES | D66: C1077-Q9566 | E66: 249.89 | F66: 8894.1 | G66: 0.30989 | H66: 249.89 | I66: 0 | J66: 0 | K66: 75.879 | L66: 127.27 | M66: 46.495 | N66: 0.439 | O66: 0 | P66: 0.25 | Q66: 9.527 | R66: 33.576 | S66: 132.301 | T66: 74.237 | U66: 162.308 | V66: 40.697 | W66: 43.793 | X66: 2.655 | Y66: 0.436 | Z66: 0 | AA66: 210 | AB66: 1200 | AC66: Sin afirmar | AE66: Sí | AF66: =IF(E66=0,0,(K66+L66+M66)/(K66+L66+M66+N66+O66)) -> 0.99824458 | AG66: =IF(J66>=MAX(H66,I66),"MOSAICO",IF(H66>=I66,"BES","ANDINO")) -> BES | AH66: =IF(AF66>=P_CORTE,"Alta","Moderada") -> Alta | AI66: =INDEX(PAQ_T,MATCH(AG66&"|"&AH66,PAQ_KEY,0)) -> T1 | AJ66: 60 | AK66: 200402
A67: M6B2-1 | B67: MORROPON | C67: BUENOS AIRES | D67: C1077-Q9566 | E67: 514.359 | F67: 14413.3 | G67: 0.3381 | H67: 514.359 | I67: 0 | J67: 0 | K67: 63.507 | L67: 328.894 | M67: 117.108 | N67: 5.073 | O67: 0.149 | P67: 3.174 | Q67: 38.186 | R67: 126.599 | S67: 290.179 | T67: 56.22 | U67: 239.025 | V67: 153.115 | W67: 103.151 | X67: 13.856 | Y67: 4.223 | Z67: 0.988 | AA67: 3138 | AB67: 4875 | AC67: Sin afirmar | AE67: No | AF67: =IF(E67=0,0,(K67+L67+M67)/(K67+L67+M67+N67+O67)) -> 0.9898549 | AG67: =IF(J67>=MAX(H67,I67),"MOSAICO",IF(H67>=I67,"BES","ANDINO")) -> BES | AH67: =IF(AF67>=P_CORTE,"Alta","Moderada") -> Alta | AI67: =INDEX(PAQ_T,MATCH(AG67&"|"&AH67,PAQ_KEY,0)) -> T1 | AJ67: 61 | AK67: 200402
A68: M6B2-2 | B68: MORROPON | C68: BUENOS AIRES | D68: C1077-Q9566 | E68: 333.011 | F68: 9253.1 | G68: 0.302636 | H68: 333.011 | I68: 0 | J68: 0 | K68: 90.339 | L68: 214.57 | M68: 25.061 | N68: 2.583 | O68: 0.742 | P68: 3.374 | Q68: 48.038 | R68: 111.432 | S68: 153.273 | T68: 16.894 | U68: 150.324 | V68: 154.348 | W68: 19.206 | X68: 5.812 | Y68: 0.637 | Z68: 2.684 | AA68: 2694 | AB68: 3606 | AC68: Trocha | AE68: No | AF68: =IF(E68=0,0,(K68+L68+M68)/(K68+L68+M68+N68+O68)) -> 0.99002385 | AG68: =IF(J68>=MAX(H68,I68),"MOSAICO",IF(H68>=I68,"BES","ANDINO")) -> BES | AH68: =IF(AF68>=P_CORTE,"Alta","Moderada") -> Alta | AI68: =INDEX(PAQ_T,MATCH(AG68&"|"&AH68,PAQ_KEY,0)) -> T1 | AJ68: 62 | AK68: 200402
A69: M6B2-3 | B69: MORROPON | C69: BUENOS AIRES | D69: C1077-Q9566 | E69: 160.978 | F69: 5607.9 | G69: 0.406259 | H69: 160.978 | I69: 0 | J69: 0 | K69: 4.691 | L69: 53.891 | M69: 87.193 | N69: 14.944 | O69: 0.377 | P69: 0.437 | Q69: 6.33 | R69: 24.992 | S69: 91.374 | T69: 37.899 | U69: 37.219 | V69: 21.355 | W69: 77.862 | X69: 9.293 | Y69: 14.193 | Z69: 1.111 | AA69: 992 | AB69: 1703 | AC69: Trocha | AE69: No | AF69: =IF(E69=0,0,(K69+L69+M69)/(K69+L69+M69+N69+O69)) -> 0.90489522 | AG69: =IF(J69>=MAX(H69,I69),"MOSAICO",IF(H69>=I69,"BES","ANDINO")) -> BES | AH69: =IF(AF69>=P_CORTE,"Alta","Moderada") -> Alta | AI69: =INDEX(PAQ_T,MATCH(AG69&"|"&AH69,PAQ_KEY,0)) -> T1 | AJ69: 63 | AK69: 200402
A70: M18B1 | B70: MORROPON | C70: BUENOS AIRES | D70: C1077-Q9579 | E70: 160.36 | F70: 5765.2 | G70: 0.334299 | H70: 159.141 | I70: 0 | J70: 1.219 | K70: 25.962 | L70: 95.804 | M70: 38.181 | N70: 0.525 | O70: 0 | P70: 0.441 | Q70: 6.632 | R70: 18.798 | S70: 91.766 | T70: 42.723 | U70: 99.639 | V70: 22.046 | W70: 34.328 | X70: 3.822 | Y70: 0.522 | Z70: 0.002 | AA70: 4753 | AB70: 5673 | AC70: Trocha | AE70: No | AF70: =IF(E70=0,0,(K70+L70+M70)/(K70+L70+M70+N70+O70)) -> 0.9967284 | AG70: =IF(J70>=MAX(H70,I70),"MOSAICO",IF(H70>=I70,"BES","ANDINO")) -> BES | AH70: =IF(AF70>=P_CORTE,"Alta","Moderada") -> Alta | AI70: =INDEX(PAQ_T,MATCH(AG70&"|"&AH70,PAQ_KEY,0)) -> T1 | AJ70: 64 | AK70: 200402
A71: M1B1 | B71: MORROPON | C71: BUENOS AIRES | D71: C1077-Q9580 | E71: 188.797 | F71: 7209.7 | G71: 0.319305 | H71: 188.797 | I71: 0 | J71: 0 | K71: 38.939 | L71: 124.834 | M71: 24.003 | N71: 1.053 | O71: 0.119 | P71: 0.361 | Q71: 7.099 | R71: 34.496 | S71: 114.064 | T71: 32.777 | U71: 123.581 | V71: 40.076 | W71: 22.243 | X71: 1.727 | Y71: 1.017 | Z71: 0.153 | AA71: 6562 | AB71: 7777 | AC71: Sin afirmar | AE71: No | AF71: =IF(E71=0,0,(K71+L71+M71)/(K71+L71+M71+N71+O71)) -> 0.99379724 | AG71: =IF(J71>=MAX(H71,I71),"MOSAICO",IF(H71>=I71,"BES","ANDINO")) -> BES | AH71: =IF(AF71>=P_CORTE,"Alta","Moderada") -> Alta | AI71: =INDEX(PAQ_T,MATCH(AG71&"|"&AH71,PAQ_KEY,0)) -> T1 | AJ71: 65 | AK71: 200402
A72: 59 | B72: MORROPON | C72: CHALACO | D72: C1086-Q9570 | E72: 13.554 | F72: 1664.2 | G72: 0.614739 | H72: 0 | I72: 8.127 | J72: 5.427 | K72: 0.248 | L72: 0.487 | M72: 1.131 | N72: 3.997 | O72: 7.707 | P72: 0 | Q72: 0.001 | R72: 0.012 | S72: 1.782 | T72: 11.76 | U72: 0.732 | V72: 0 | W72: 1.127 | X72: 0 | Y72: 11.682 | Z72: 0.012 | AA72: 1117 | AB72: 1321 | AC72: Trocha | AE72: No | AF72: =IF(E72=0,0,(K72+L72+M72)/(K72+L72+M72+N72+O72)) -> 0.13750921 | AG72: =IF(J72>=MAX(H72,I72),"MOSAICO",IF(H72>=I72,"BES","ANDINO")) -> ANDINO | AH72: =IF(AF72>=P_CORTE,"Alta","Moderada") -> Moderada | AI72: =INDEX(PAQ_T,MATCH(AG72&"|"&AH72,PAQ_KEY,0)) -> T4 | AJ72: 66 | AK72: 200403
A73: 57 | B73: MORROPON | C73: CHALACO | D73: C1086-Q9576 | E73: 25.668 | F73: 2382.2 | G73: 0.603055 | H73: 0 | I73: 21.261 | J73: 4.407 | K73: 0 | L73: 0 | M73: 1.18 | N73: 14.35 | O73: 10.156 | P73: 0 | Q73: 0.027 | R73: 0.272 | S73: 4.545 | T73: 20.823 | U73: 0 | V73: 0 | W73: 1.065 | X73: 0.111 | Y73: 24.303 | Z73: 0.189 | AA73: 1054 | AB73: 1260 | AC73: Trocha | AE73: No | AF73: =IF(E73=0,0,(K73+L73+M73)/(K73+L73+M73+N73+O73)) -> 0.045939422 | AG73: =IF(J73>=MAX(H73,I73),"MOSAICO",IF(H73>=I73,"BES","ANDINO")) -> ANDINO | AH73: =IF(AF73>=P_CORTE,"Alta","Moderada") -> Moderada | AI73: =INDEX(PAQ_T,MATCH(AG73&"|"&AH73,PAQ_KEY,0)) -> T4 | AJ73: 67 | AK73: 200403
A74: M9B1 | B74: MORROPON | C74: CHULUCANAS | D74: C1096-Q9545 | E74: 355.364 | F74: 8287.3 | G74: 0.314312 | H74: 355.364 | I74: 0 | J74: 0 | K74: 77.826 | L74: 232.802 | M74: 42.661 | N74: 2.15 | O74: 0.233 | P74: 33.633 | Q74: 133.214 | R74: 99.008 | S74: 77.853 | T74: 11.655 | U74: 65.933 | V74: 244.448 | W74: 22.524 | X74: 20.076 | Y74: 1.05 | Z74: 1.331 | AA74: 141 | AB74: 1352 | AC74: Afirmado | AE74: No | AF74: =IF(E74=0,0,(K74+L74+M74)/(K74+L74+M74+N74+O74)) -> 0.99330001 | AG74: =IF(J74>=MAX(H74,I74),"MOSAICO",IF(H74>=I74,"BES","ANDINO")) -> BES | AH74: =IF(AF74>=P_CORTE,"Alta","Moderada") -> Alta | AI74: =INDEX(PAQ_T,MATCH(AG74&"|"&AH74,PAQ_KEY,0)) -> T1 | AJ74: 68 | AK74: 200401
A75: M10B4 | B75: MORROPON | C75: CHULUCANAS | D75: C1096-Q9547 | E75: 68.887 | F75: 4844.1 | G75: 0.313301 | H75: 68.887 | I75: 0 | J75: 0 | K75: 11.562 | L75: 51.495 | M75: 5.759 | N75: 0.129 | O75: 0 | P75: 0.913 | Q75: 11.383 | R75: 26.777 | S75: 25.863 | T75: 3.95 | U75: 26.58 | V75: 36.431 | W75: 3.11 | X75: 2.637 | Y75: 0.123 | Z75: 0.005 | AA75: 290 | AB75: 859 | AC75: Sin afirmar | AE75: No | AF75: =IF(E75=0,0,(K75+L75+M75)/(K75+L75+M75+N75+O75)) -> 0.99812894 | AG75: =IF(J75>=MAX(H75,I75),"MOSAICO",IF(H75>=I75,"BES","ANDINO")) -> BES | AH75: =IF(AF75>=P_CORTE,"Alta","Moderada") -> Alta | AI75: =INDEX(PAQ_T,MATCH(AG75&"|"&AH75,PAQ_KEY,0)) -> T1 | AJ75: 69 | AK75: 200401
A76: 22 | B76: MORROPON | C76: CHULUCANAS | D76: C1096-Q9556 | E76: 79.33 | F76: 3972.6 | G76: 0.42317 | H76: 79.33 | I76: 0 | J76: 0 | K76: 0 | L76: 15.694 | M76: 58.365 | N76: 5.236 | O76: 0.099 | P76: 0.141 | Q76: 2.938 | R76: 10.342 | S76: 32.042 | T76: 33.868 | U76: 11.207 | V76: 4.471 | W76: 49.9 | X76: 8.43 | Y76: 4.802 | Z76: 0.52 | AA76: 111 | AB76: 747 | AC76: Sin afirmar | AE76: No | AF76: =IF(E76=0,0,(K76+L76+M76)/(K76+L76+M76+N76+O76)) -> 0.93280349 | AG76: =IF(J76>=MAX(H76,I76),"MOSAICO",IF(H76>=I76,"BES","ANDINO")) -> BES | AH76: =IF(AF76>=P_CORTE,"Alta","Moderada") -> Alta | AI76: =INDEX(PAQ_T,MATCH(AG76&"|"&AH76,PAQ_KEY,0)) -> T1 | AJ76: 70 | AK76: 200401 | AL76: 2.756 | AM76: Reporte de superposición de área 2.756 ha con Catastro minero: Hugo Armando Zapata Oña – FRIAS 5 (700001126)
A77: M17B1 | B77: MORROPON | C77: CHULUCANAS | D77: C1096-Q9556 | E77: 42.449 | F77: 3721 | G77: 0.332263 | H77: 42.449 | I77: 0 | J77: 0 | K77: 4 | L77: 30.76 | M77: 7.656 | N77: 0.07 | O77: 0 | P77: 0.25 | Q77: 4.536 | R77: 14.994 | S77: 21.172 | T77: 1.497 | U77: 17.214 | V77: 17.519 | W77: 5.398 | X77: 2.249 | Y77: 0.057 | Z77: 0.012 | AA77: 8 | AB77: 189 | AC77: Sin afirmar | AE77: No | AF77: =IF(E77=0,0,(K77+L77+M77)/(K77+L77+M77+N77+O77)) -> 0.9983524 | AG77: =IF(J77>=MAX(H77,I77),"MOSAICO",IF(H77>=I77,"BES","ANDINO")) -> BES | AH77: =IF(AF77>=P_CORTE,"Alta","Moderada") -> Alta | AI77: =INDEX(PAQ_T,MATCH(AG77&"|"&AH77,PAQ_KEY,0)) -> T1 | AJ77: 71 | AK77: 200401 | AL77: 0.072 | AM77: Reporte de superposición de área 0.072 ha con Catastro minero: Hugo Armando Zapata Oña – FRIAS 3 (700000926)
A78: M17B4 | B78: MORROPON | C78: CHULUCANAS | D78: C1096-Q9556 | E78: 124.709 | F78: 8583.3 | G78: 0.423543 | H78: 124.709 | I78: 0 | J78: 0 | K78: 0.01 | L78: 28.925 | M78: 85.809 | N78: 8.264 | O78: 1.808 | P78: 0.172 | Q78: 6.833 | R78: 26.235 | S78: 65.212 | T78: 26.257 | U78: 17.14 | V78: 11.763 | W78: 66.838 | X78: 18.917 | Y78: 7.492 | Z78: 2.559 | AA78: 34 | AB78: 387 | AC78: Afirmado | AE78: No | AF78: =IF(E78=0,0,(K78+L78+M78)/(K78+L78+M78+N78+O78)) -> 0.91930522 | AG78: =IF(J78>=MAX(H78,I78),"MOSAICO",IF(H78>=I78,"BES","ANDINO")) -> BES | AH78: =IF(AF78>=P_CORTE,"Alta","Moderada") -> Alta | AI78: =INDEX(PAQ_T,MATCH(AG78&"|"&AH78,PAQ_KEY,0)) -> T1 | AJ78: 72 | AK78: 200401
A79: M27B1 | B79: MORROPON | C79: CHULUCANAS | D79: C1096-Q9557 | E79: 448.804 | F79: 11357.6 | G79: 0.363228 | H79: 443.83 | I79: 0 | J79: 4.974 | K79: 39.032 | L79: 224.828 | M79: 171.589 | N79: 13.689 | O79: 0.04 | P79: 3.734 | Q79: 48.429 | R79: 97.606 | S79: 203.461 | T79: 95.575 | U79: 150.77 | V79: 112.871 | W79: 137.027 | X79: 34.437 | Y79: 11.238 | Z79: 2.46 | AA79: 34 | AB79: 913 | AC79: Trocha | AE79: No | AF79: =IF(E79=0,0,(K79+L79+M79)/(K79+L79+M79+N79+O79)) -> 0.96943528 | AG79: =IF(J79>=MAX(H79,I79),"MOSAICO",IF(H79>=I79,"BES","ANDINO")) -> BES | AH79: =IF(AF79>=P_CORTE,"Alta","Moderada") -> Alta | AI79: =INDEX(PAQ_T,MATCH(AG79&"|"&AH79,PAQ_KEY,0)) -> T1 | AJ79: 73 | AK79: 200401
A80: 2 | B80: MORROPON | C80: CHULUCANAS | D80: C1096-Q9558 | E80: 330.599 | F80: 7611.1 | G80: 0.358601 | H80: 330.599 | I80: 0 | J80: 0 | K80: 9.851 | L80: 213.579 | M80: 104.721 | N80: 2.665 | O80: 0.058 | P80: 9.555 | Q80: 82.076 | R80: 104.083 | S80: 108.61 | T80: 26.275 | U80: 73.796 | V80: 149.469 | W80: 60.23 | X80: 44.393 | Y80: 0.859 | Z80: 1.852 | AA80: 60 | AB80: 1261 | AC80: Trocha | AE80: No | AF80: =IF(E80=0,0,(K80+L80+M80)/(K80+L80+M80+N80+O80)) -> 0.99177028 | AG80: =IF(J80>=MAX(H80,I80),"MOSAICO",IF(H80>=I80,"BES","ANDINO")) -> BES | AH80: =IF(AF80>=P_CORTE,"Alta","Moderada") -> Alta | AI80: =INDEX(PAQ_T,MATCH(AG80&"|"&AH80,PAQ_KEY,0)) -> T1 | AJ80: 74 | AK80: 200401
A81: M32B3 | B81: MORROPON | C81: MORROPON | D81: C1086-Q9569 | E81: 50.972 | F81: 3197 | G81: 0.385213 | H81: 50.972 | I81: 0 | J81: 0 | K81: 1.17 | L81: 23.33 | M81: 23.392 | N81: 3.128 | O81: 0 | P81: 0 | Q81: 2.886 | R81: 12.608 | S81: 22.54 | T81: 12.938 | U81: 11.914 | V81: 12.563 | W81: 20.756 | X81: 2.618 | Y81: 2.808 | Z81: 0.313 | AA81: 0 | AB81: 357 | AC81: Sin afirmar | AE81: No | AF81: =IF(E81=0,0,(K81+L81+M81)/(K81+L81+M81+N81+O81)) -> 0.93869071 | AG81: =IF(J81>=MAX(H81,I81),"MOSAICO",IF(H81>=I81,"BES","ANDINO")) -> BES | AH81: =IF(AF81>=P_CORTE,"Alta","Moderada") -> Alta | AI81: =INDEX(PAQ_T,MATCH(AG81&"|"&AH81,PAQ_KEY,0)) -> T1 | AJ81: 75 | AK81: 200405
A82: M19B2 | B82: MORROPON | C82: MORROPON | D82: C1086-Q9570 | E82: 74.372 | F82: 3960.4 | G82: 0.401185 | H82: 74.372 | I82: 0 | J82: 0 | K82: 0.333 | L82: 23.42 | M82: 47.879 | N82: 2.804 | O82: 0 | P82: 0.141 | Q82: 3.172 | R82: 12.022 | S82: 30.474 | T82: 28.565 | U82: 15.161 | V82: 8.563 | W82: 41.467 | X82: 6.383 | Y82: 2.411 | Z82: 0.388 | AA82: 0 | AB82: 371 | AC82: Sin afirmar | AE82: No | AF82: =IF(E82=0,0,(K82+L82+M82)/(K82+L82+M82+N82+O82)) -> 0.96233006 | AG82: =IF(J82>=MAX(H82,I82),"MOSAICO",IF(H82>=I82,"BES","ANDINO")) -> BES | AH82: =IF(AF82>=P_CORTE,"Alta","Moderada") -> Alta | AI82: =INDEX(PAQ_T,MATCH(AG82&"|"&AH82,PAQ_KEY,0)) -> T1 | AJ82: 76 | AK82: 200405
A83: M7B1 | B83: MORROPON | C83: SALITRAL | D83: C1076-Q9581 | E83: 130.425 | F83: 11770 | G83: 0.313647 | H83: 130.425 | I83: 0 | J83: 0 | K83: 21.076 | L83: 98.021 | M83: 11.118 | N83: 0.295 | O83: 0 | P83: 6.773 | Q83: 8.327 | R83: 17.097 | S83: 79.654 | T83: 18.575 | U83: 91.877 | V83: 27.154 | W83: 6.343 | X83: 4.759 | Y83: 0.01 | Z83: 0.283 | AA83: 57 | AB83: 1537 | AC83: Sin afirmar | AE83: No | AF83: =IF(E83=0,0,(K83+L83+M83)/(K83+L83+M83+N83+O83)) -> 0.99773964 | AG83: =IF(J83>=MAX(H83,I83),"MOSAICO",IF(H83>=I83,"BES","ANDINO")) -> BES | AH83: =IF(AF83>=P_CORTE,"Alta","Moderada") -> Alta | AI83: =INDEX(PAQ_T,MATCH(AG83&"|"&AH83,PAQ_KEY,0)) -> T1 | AJ83: 77 | AK83: 200406
A84: M7B2 | B84: MORROPON | C84: SALITRAL | D84: C1076-Q9581 | E84: 115.379 | F84: 9401.6 | G84: 0.287689 | H84: 114.41 | I84: 0 | J84: 0.969 | K84: 34.555 | L84: 78.234 | M84: 2.185 | N84: 0.481 | O84: 0 | P84: 6.096 | Q84: 20.231 | R84: 30.123 | S84: 50.615 | T84: 8.315 | U84: 57.388 | V84: 55.332 | W84: 1.513 | X84: 0.667 | Y84: 0.029 | Z84: 0.451 | AA84: 4272 | AB84: 5063 | AC84: Sin afirmar | AE84: No | AF84: =IF(E84=0,0,(K84+L84+M84)/(K84+L84+M84+N84+O84)) -> 0.99583387 | AG84: =IF(J84>=MAX(H84,I84),"MOSAICO",IF(H84>=I84,"BES","ANDINO")) -> BES | AH84: =IF(AF84>=P_CORTE,"Alta","Moderada") -> Alta | AI84: =INDEX(PAQ_T,MATCH(AG84&"|"&AH84,PAQ_KEY,0)) -> T1 | AJ84: 78 | AK84: 200406
A85: M7B3 | B85: MORROPON | C85: SALITRAL | D85: C1076-Q9581 | E85: 65.745 | F85: 7236.4 | G85: 0.298017 | H85: 65.476 | I85: 0 | J85: 0.269 | K85: 14.521 | L85: 47.908 | M85: 3.264 | N85: 0.1 | O85: 0 | P85: 0.388 | Q85: 2.719 | R85: 9.892 | S85: 36.994 | T85: 15.751 | U85: 49.836 | V85: 12.549 | W85: 2.829 | X85: 0.43 | Y85: 0.08 | Z85: 0.02 | AA85: 1759 | AB85: 2911 | AC85: Trocha | AE85: No | AF85: =IF(E85=0,0,(K85+L85+M85)/(K85+L85+M85+N85+O85)) -> 0.99848008 | AG85: =IF(J85>=MAX(H85,I85),"MOSAICO",IF(H85>=I85,"BES","ANDINO")) -> BES | AH85: =IF(AF85>=P_CORTE,"Alta","Moderada") -> Alta | AI85: =INDEX(PAQ_T,MATCH(AG85&"|"&AH85,PAQ_KEY,0)) -> T1 | AJ85: 79 | AK85: 200406
A86: M7B6 | B86: MORROPON | C86: SALITRAL | D86: C1076-Q9581 | E86: 91.285 | F86: 5675.2 | G86: 0.287833 | H86: 91.285 | I86: 0 | J86: 0 | K86: 34.374 | L86: 52.271 | M86: 4.663 | N86: 0.033 | O86: 0 | P86: 0.152 | Q86: 7.443 | R86: 24.455 | S86: 48.261 | T86: 10.974 | U86: 54.565 | V86: 32.032 | W86: 4.638 | X86: 0.018 | Y86: 0.032 | Z86: 0 | AA86: 0 | AB86: 640 | AC86: Trocha | AE86: No | AF86: =IF(E86=0,0,(K86+L86+M86)/(K86+L86+M86+N86+O86)) -> 0.99963872 | AG86: =IF(J86>=MAX(H86,I86),"MOSAICO",IF(H86>=I86,"BES","ANDINO")) -> BES | AH86: =IF(AF86>=P_CORTE,"Alta","Moderada") -> Alta | AI86: =INDEX(PAQ_T,MATCH(AG86&"|"&AH86,PAQ_KEY,0)) -> T1 | AJ86: 80 | AK86: 200406
A87: M2B1 | B87: MORROPON | C87: SALITRAL | D87: C1076-Q9584 | E87: 81.795 | F87: 5202.3 | G87: 0.29836 | H87: 81.795 | I87: 0 | J87: 0 | K87: 22.229 | L87: 56.147 | M87: 3.473 | N87: 0 | O87: 0 | P87: 1.055 | Q87: 6.025 | R87: 15.539 | S87: 48.187 | T87: 10.988 | U87: 56.076 | V87: 22.255 | W87: 3.099 | X87: 0.365 | Y87: 0 | Z87: 0 | AA87: 52 | AB87: 597 | AC87: Trocha | AE87: No | AF87: =IF(E87=0,0,(K87+L87+M87)/(K87+L87+M87+N87+O87)) -> 1 | AG87: =IF(J87>=MAX(H87,I87),"MOSAICO",IF(H87>=I87,"BES","ANDINO")) -> BES | AH87: =IF(AF87>=P_CORTE,"Alta","Moderada") -> Alta | AI87: =INDEX(PAQ_T,MATCH(AG87&"|"&AH87,PAQ_KEY,0)) -> T1 | AJ87: 81 | AK87: 200406
A88: M2B5 | B88: MORROPON | C88: SALITRAL | D88: C1076-Q9584 | E88: 30.909 | F88: 3944.2 | G88: 0.304733 | H88: 30.37 | I88: 0 | J88: 0.538 | K88: 9.087 | L88: 18.32 | M88: 3.22 | N88: 0.301 | O88: 0 | P88: 1.503 | Q88: 15.358 | R88: 11.879 | S88: 2.168 | T88: 0 | U88: 2.085 | V88: 25.307 | W88: 0.08 | X88: 3.138 | Y88: 0.003 | Z88: 0.296 | AA88: 3 | AB88: 187 | AC88: Trocha | AE88: No | AF88: =IF(E88=0,0,(K88+L88+M88)/(K88+L88+M88+N88+O88)) -> 0.99026772 | AG88: =IF(J88>=MAX(H88,I88),"MOSAICO",IF(H88>=I88,"BES","ANDINO")) -> BES | AH88: =IF(AF88>=P_CORTE,"Alta","Moderada") -> Alta | AI88: =INDEX(PAQ_T,MATCH(AG88&"|"&AH88,PAQ_KEY,0)) -> T1 | AJ88: 82 | AK88: 200406
A89: M18B3 | B89: MORROPON | C89: SALITRAL | D89: C1077-Q9579 | E89: 373.807 | F89: 14555.6 | G89: 0.369424 | H89: 373.699 | I89: 0 | J89: 0.108 | K89: 18.019 | L89: 193.442 | M89: 156.546 | N89: 5.982 | O89: 0.107 | P89: 2.359 | Q89: 23.635 | R89: 47.959 | S89: 156.032 | T89: 143.821 | U89: 147.005 | V89: 64.299 | W89: 147.481 | X89: 8.954 | Y89: 5.367 | Z89: 0.701 | AA89: 302 | AB89: 1905 | AC89: Trocha | AE89: No | AF89: =IF(E89=0,0,(K89+L89+M89)/(K89+L89+M89+N89+O89)) -> 0.98372343 | AG89: =IF(J89>=MAX(H89,I89),"MOSAICO",IF(H89>=I89,"BES","ANDINO")) -> BES | AH89: =IF(AF89>=P_CORTE,"Alta","Moderada") -> Alta | AI89: =INDEX(PAQ_T,MATCH(AG89&"|"&AH89,PAQ_KEY,0)) -> T1 | AJ89: 83 | AK89: 200406
... A116: M8B2 | B116: MORROPON | C116: SANTO DOMINGO | D116: C1096-Q9558 | E116: 35.347 | F116: 3466.1 | G116: 0.530453 | H116: 20.424 | I116: 0 | J116: 14.923 | K116: 0.03 | L116: 1.647 | M116: 9.373 | N116: 19.102 | O116: 5.226 | P116: 0 | Q116: 0.141 | R116: 1.531 | S116: 13.819 | T116: 19.857 | U116: 1.611 | V116: 0.062 | W116: 8.874 | X116: 0.489 | Y116: 23.19 | Z116: 1.12 | AA116: 268 | AB116: 537 | AC116: Trocha | AE116: No | AF116: =IF(E116=0,0,(K116+L116+M116)/(K116+L116+M116+N116+O116)) -> 0.312341 | AG116: =IF(J116>=MAX(H116,I116),"MOSAICO",IF(H116>=I116,"BES","ANDINO")) -> BES | AH116: =IF(AF116>=P_CORTE,"Alta","Moderada") -> Moderada | AI116: =INDEX(PAQ_T,MATCH(AG116&"|"&AH116,PAQ_KEY,0)) -> T2 | AJ116: 110 | AK116: 200409
A117: 13 | B117: MORROPON | C117: SANTO DOMINGO | D117: C1096-Q9564 | E117: 100.514 | F117: 3901.1 | G117: 0.671094 | H117: 0 | I117: 86.575 | J117: 13.939 | K117: 0 | L117: 0 | M117: 5.246 | N117: 24.038 | O117: 71.291 | P117: 0.312 | Q117: 1.104 | R117: 4.5 | S117: 27.147 | T117: 67.45 | U117: 0 | V117: 0 | W117: 5.155 | X117: 0.084 | Y117: 89.442 | Z117: 5.832 | AA117: 265 | AB117: 974 | AC117: Trocha | AE117: No | AF117: =IF(E117=0,0,(K117+L117+M117)/(K117+L117+M117+N117+O117)) -> 0.05216008 | AG117: =IF(J117>=MAX(H117,I117),"MOSAICO",IF(H117>=I117,"BES","ANDINO")) -> ANDINO | AH117: =IF(AF117>=P_CORTE,"Alta","Moderada") -> Moderada | AI117: =INDEX(PAQ_T,MATCH(AG117&"|"&AH117,PAQ_KEY,0)) -> T4 | AJ117: 111 | AK117: 200409 | AM117: Microcuenca sin codigo M asignado
A118: 49 | B118: MORROPON | C118: YAMANGO | D118: C1086-Q9575 | E118: 15.839 | F118: 1559.2 | G118: 0.686036 | H118: 0 | I118: 4.804 | J118: 11.035 | K118: 0 | L118: 0 | M118: 0.578 | N118: 2.806 | O118: 12.465 | P118: 0.005 | Q118: 0.016 | R118: 0.29 | S118: 5.486 | T118: 10.043 | U118: 0 | V118: 0 | W118: 0.526 | X118: 0.051 | Y118: 15.003 | Z118: 0.259 | AA118: 548 | AB118: 814 | AC118: Sin afirmar | AE118: No | AF118: =IF(E118=0,0,(K118+L118+M118)/(K118+L118+M118+N118+O118)) -> 0.036469178 | AG118: =IF(J118>=MAX(H118,I118),"MOSAICO",IF(H118>=I118,"BES","ANDINO")) -> MOSAICO | AH118: =IF(AF118>=P_CORTE,"Alta","Moderada") -> Moderada | AI118: =INDEX(PAQ_T,MATCH(AG118&"|"&AH118,PAQ_KEY,0)) -> T6 | AJ118: 112 | AK118: 200410
A119: 52 | B119: MORROPON | C119: YAMANGO | D119: C1086-Q9575 | E119: 11.059 | F119: 1599.3 | G119: 0.66855 | H119: 0 | I119: 4.33 | J119: 6.73 | K119: 0 | L119: 0 | M119: 0.421 | N119: 2.915 | O119: 7.732 | P119: 0 | Q119: 0.01 | R119: 0.119 | S119: 3.375 | T119: 7.555 | U119: 0 | V119: 0 | W119: 0.419 | X119: 0.001 | Y119: 10.511 | Z119: 0.128 | AA119: 1247 | AB119: 1532 | AC119: Sin afirmar | AE119: No | AF119: =IF(E119=0,0,(K119+L119+M119)/(K119+L119+M119+N119+O119)) -> 0.038037586 | AG119: =IF(J119>=MAX(H119,I119),"MOSAICO",IF(H119>=I119,"BES","ANDINO")) -> MOSAICO | AH119: =IF(AF119>=P_CORTE,"Alta","Moderada") -> Moderada | AI119: =INDEX(PAQ_T,MATCH(AG119&"|"&AH119,PAQ_KEY,0)) -> T6 | AJ119: 113 | AK119: 200410
A120: 55 | B120: MORROPON | C120: YAMANGO | D120: C1086-Q9575 | E120: 0.859 | F120: 404.7 | G120: 0.630032 | H120: 0 | I120: 0 | J120: 0.859 | K120: 0 | L120: 0 | M120: 0.015 | N120: 0.367 | O120: 0.477 | P120: 0 | Q120: 0 | R120: 0 | S120: 0.039 | T120: 0.82 | U120: 0 | V120: 0 | W120: 0.015 | X120: 0 | Y120: 0.844 | Z120: 0 | AA120: 469 | AB120: 531 | AC120: Sin afirmar | AE120: No | AF120: =IF(E120=0,0,(K120+L120+M120)/(K120+L120+M120+N120+O120)) -> 0.017462165 | AG120: =IF(J120>=MAX(H120,I120),"MOSAICO",IF(H120>=I120,"BES","ANDINO")) -> MOSAICO | AH120: =IF(AF120>=P_CORTE,"Alta","Moderada") -> Moderada | AI120: =INDEX(PAQ_T,MATCH(AG120&"|"&AH120,PAQ_KEY,0)) -> T6 | AJ120: 114 | AK120: 200410
A121: M28B2 | B121: MORROPON | C121: YAMANGO | D121: C1086-Q9575 | E121: 90.197 | F121: 7122.5 | G121: 0.475342 | H121: 89.433 | I121: 0 | J121: 0.764 | K121: 1.29 | L121: 7.944 | M121: 46.91 | N121: 30.443 | O121: 3.691 | P121: 0.326 | Q121: 3.497 | R121: 11.609 | S121: 46.833 | T121: 27.932 | U121: 5.405 | V121: 3.812 | W121: 39.775 | X121: 7.102 | Y121: 29.584 | Z121: 4.518 | AA121: 0 | AB121: 167 | AC121: Sin afirmar | AE121: No | AF121: =IF(E121=0,0,(K121+L121+M121)/(K121+L121+M121+N121+O121)) -> 0.62190124 | AG121: =IF(J121>=MAX(H121,I121),"MOSAICO",IF(H121>=I121,"BES","ANDINO")) -> BES | AH121: =IF(AF121>=P_CORTE,"Alta","Moderada") -> Alta | AI121: =INDEX(PAQ_T,MATCH(AG121&"|"&AH121,PAQ_KEY,0)) -> T1 | AJ121: 115 | AK121: 200410
A122: M28B3 | B122: MORROPON | C122: YAMANGO | D122: C1086-Q9575 | E122: 58.292 | F122: 4146.1 | G122: 0.507529 | H122: 54.721 | I122: 0 | J122: 3.571 | K122: 0.088 | L122: 6.041 | M122: 22.839 | N122: 20.39 | O122: 8.974 | P122: 0 | Q122: 0.868 | R122: 4.706 | S122: 31.443 | T122: 21.275 | U122: 5.459 | V122: 0.665 | W122: 21.516 | X122: 1.312 | Y122: 25.742 | Z122: 3.597 | AA122: 7 | AB122: 244 | AC122: Sin afirmar | AE122: No | AF122: =IF(E122=0,0,(K122+L122+M122)/(K122+L122+M122+N122+O122)) -> 0.49660564 | AG122: =IF(J122>=MAX(H122,I122),"MOSAICO",IF(H122>=I122,"BES","ANDINO")) -> BES | AH122: =IF(AF122>=P_CORTE,"Alta","Moderada") -> Moderada | AI122: =INDEX(PAQ_T,MATCH(AG122&"|"&AH122,PAQ_KEY,0)) -> T2 | AJ122: 116 | AK122: 200410
A123: M28B4 | B123: MORROPON | C123: YAMANGO | D123: C1086-Q9575 | E123: 283.428 | F123: 8181.3 | G123: 0.42751 | H123: 283.428 | I123: 0 | J123: 0 | K123: 0.44 | L123: 104.053 | M123: 107.681 | N123: 69.294 | O123: 2.172 | P123: 1.078 | Q123: 71.385 | R123: 105.904 | S123: 71.71 | T123: 33.351 | U123: 9.649 | V123: 94.777 | W123: 48.681 | X123: 58.917 | Y123: 46.731 | Z123: 24.674 | AA123: 43 | AB123: 776 | AC123: Trocha | AE123: No | AF123: =IF(E123=0,0,(K123+L123+M123)/(K123+L123+M123+N123+O123)) -> 0.74803977 | AG123: =IF(J123>=MAX(H123,I123),"MOSAICO",IF(H123>=I123,"BES","ANDINO")) -> BES | AH123: =IF(AF123>=P_CORTE,"Alta","Moderada") -> Alta | AI123: =INDEX(PAQ_T,MATCH(AG123&"|"&AH123,PAQ_KEY,0)) -> T1 | AJ123: 117 | AK123: 200410
A124: TOTAL | E124: =SUM(E7:E123) -> 12270.235 | F124: =SUM(F7:F123) -> 577845.6 | H124: =SUM(H7:H123) -> 8347.407 | I124: =SUM(I7:I123) -> 1121.63 | J124: =SUM(J7:J123) -> 2801.197 | K124: =SUM(K7:K123) -> 1247.386 | L124: =SUM(L7:L123) -> 4259.877 | M124: =SUM(M7:M123) -> 2840.612 | N124: =SUM(N7:N123) -> 1968.362 | O124: =SUM(O7:O123) -> 1962.309 | ... Z124: =SUM(Z7:Z123) -> 203.886 | AL124: =SUM(AL7:AL123) -> 112.765

Sheet CALCULO
A1: AUTORIDAD NACIONAL DE INFRAESTRUCTURA - ANIN
A2: DIRECCIÓN DE INTERVENCIONES MULTISECTORIALES Y DE EMERGENCIA - DIME
A3: SUBDIRECCIÓN DE ESTUDIOS DE INVERSIÓN
A4: PROYECTO IN PIURA – CUI 2669244 · Metas físicas, costos de inversión y costo social por bloque
A5: Todas las celdas son fórmulas. Precios de mercado 2026 (S/). CD = costo directo. Social = MO NC × 0.42 + MO C × 0.79 + bienes y servicios ÷ 1.18.
A6: Bloque | B6: Tipología | C6: Piloto | D6: Área (ha) | E6: R1 (ha) | F6: R2 (ha) | G6: C protección (ha) | H6: Plantas R1 | I6: Plantas R2 | J6: Plantas totales | K6: Zanjas (km) | L6: Terrazas (km) | M6: Cerco (m) | N6: Cárcavas (km) | O6: Flete rural (S/ por kg) | P6: Plantón vivero (S/) | Q6: Plantación y labores (S/) | R6: Labores por ha (S/) | S6: Flete rural (S/) | T6: Flete terrestre insumos (S/) | U6: Zanjas (S/) | V6: Terrazas (S/) | W6: Cerco (S/) | X6: Cárcavas (S/) | Y6: Costo directo (S/) | Z6: GG + supervisión + ET (S/) | AA6: Inversión total (S/) | AB6: Inversión por ha de bloque (S/) | AC6: CD · MO no calificada (S/) | AD6: CD · MO calificada (S/) | AE6: CD · bienes y servicios (S/) | AF6: Inversión a precios sociales (S/) | AG6: Inversión verde (S/) | AH6: Inversión marrón (S/)
A7: =BLOQUES!A7 -> 3 | B7: =BLOQUES!AI7 -> T6 | C7: =BLOQUES!AE7 -> No | D7: =BLOQUES!E7 -> 459.295 | E7: =BLOQUES!U7+BLOQUES!V7 -> 5.623 | F7: =BLOQUES!W7+BLOQUES!X7 -> 127.858 | G7: =BLOQUES!Y7+BLOQUES!Z7 -> 325.813 | H7: =E7*INDEX(PAQ_R1,MATCH(B7,PAQ_T,0)) -> 3654.95 | I7: =F7*INDEX(PAQ_R2,MATCH(B7,PAQ_T,0)) -> 41553.85 | J7: =H7+I7 -> 45208.8 | K7: =(BLOQUES!U7+BLOQUES!W7)*INDEX(PAQ_MZ,MATCH(B7,PAQ_T,0))/1000 -> 0 | L7: =(BLOQUES!U7+BLOQUES!W7)*INDEX(PAQ_MT,MATCH(B7,PAQ_T,0))/1000 -> 151.97941 | M7: =BLOQUES!F7*INDEX(PAQ_CERCO,MATCH(B7,PAQ_T,0)) -> 11633.7 | N7: =IF(ISNUMBER(BLOQUES!AD7),BLOQUES!AD7/1000,0) -> 0 | O7: =P_JORNAL/(P_CARGA*(P_HORAS*P_EFIC/((BLOQUES!AB7/1000*P_SINUOS)/P_VIDA+(BLOQUES!AB7/1000*P_SINUOS)/P_VVUELTA+P_TCD/60))) -> 0.11024945 | P7: =J7*(1+P_RECALCE)*CU_PLANTON -> 66308.877 | Q7: =J7*CU_PLANTA -> 310172.24 | R7: =(E7+F7)*CU_HA -> 149532.85 | S7: =J7*(1+P_RECALCE)*(P_PESO_PLANTON+P_PESO_INS)*O7 -> 9156.0588 | T7: =J7*(1+P_RECALCE)*P_PESO_INS*P_FT_KG -> 1812.4006 | U7: =K7*CU_ZANJA -> 0 | V7: =L7*CU_TERRAZA -> 13706201 | W7: =M7*CU_CERCO -> 255590.09 | X7: =N7*CU_CARCAVA -> 0 | Y7: =SUM(P7:X7) -> 14498773 | Z7: =Y7*(P_GG+P_SUP+P_ET) -> 2186031 | AA7: =Y7+Z7 -> 16684804 | AB7: =IF(D7=0,0,AA7/D7) -> 36326.989 | AC7: =J7*(1+P_RECALCE)*CU_PLANTON_NC+J7*CU_PLANTA_NC+(E7+F7)*CU_HA_NC+S7+K7*CU_ZANJA_NC+L7*CU_TERRAZA_NC+M7*CU_CERCO_NC+N7*CU_CARCAVA_NC -> 8523684.8 | AD7: =J7*(1+P_RECALCE)*CU_PLANTON_C+J7*CU_PLANTA_C+(E7+F7)*CU_HA_C+K7*CU_ZANJA_C+L7*CU_TERRAZA_C+M7*CU_CERCO_C+N7*CU_CARCAVA_C -> 1316212 | AE7: =Y7-AC7-AD7 -> 4658876.7 | AF7: =AC7*P_FC_MONC+AD7*P_FC_MOC+(AE7+Z7)*P_FC_BIEN -> 10420524 | AG7: =(SUM(P7:T7)+W7)*(1+P_GG+P_SUP+P_ET) -> 912071.46 | AH7: =(U7+V7+X7)*(1+P_GG+P_SUP+P_ET) -> 15772733
A8: =BLOQUES!A8 -> 6 | B8: =BLOQUES!AI8 -> T6 | C8: =BLOQUES!AE8 -> No | D8: =BLOQUES!E8 -> 168.411 | E8: =BLOQUES!U8+BLOQUES!V8 -> 4.281 | F8: =BLOQUES!W8+BLOQUES!X8 -> 55.353 | G8: =BLOQUES!Y8+BLOQUES!Z8 -> 108.776 | H8: =E8*INDEX(PAQ_R1,MATCH(B8,PAQ_T,0)) -> 2782.65 | I8: =F8*INDEX(PAQ_R2,MATCH(B8,PAQ_T,0)) -> 17989.725 | J8: =H8+I8 -> 20772.375 | K8: =(BLOQUES!U8+BLOQUES!W8)*INDEX(PAQ_MZ,MATCH(B8,PAQ_T,0))/1000 -> 0 | L8: =(BLOQUES!U8+BLOQUES!W8)*INDEX(PAQ_MT,MATCH(B8,PAQ_T,0))/1000 -> 67.52427 | M8: =BLOQUES!F8*INDEX(PAQ_CERCO,MATCH(B8,PAQ_T,0)) -> 8376.1 | N8: =IF(ISNUMBER(BLOQUES!AD8),BLOQUES!AD8/1000,0) -> 0 | O8: =P_JORNAL/(P_CARGA*(P_HORAS*P_EFIC/((BLOQUES!AB8/1000*P_SINUOS)/P_VIDA+(BLOQUES!AB8/1000*P_SINUOS)/P_VVUELTA+P_TCD/60))) -> 0.090150768 | P8: =J8*(1+P_RECALCE)*CU_PLANTON -> 30467.362 | Q8: =J8*CU_PLANTA -> 142516.81 | R8: =(E8+F8)*CU_HA -> 66805.327 | S8: =J8*(1+P_RECALCE)*(P_PESO_PLANTON+P_PESO_INS)*O8 -> 3440.0499 | T8: =J8*(1+P_RECALCE)*P_PESO_INS*P_FT_KG -> 832.75524 | U8: =K8*CU_ZANJA -> 0 | V8: =L8*CU_TERRAZA -> 6089648.8 | W8: =M8*CU_CERCO -> 184021.26 | X8: =N8*CU_CARCAVA -> 0 | Y8: =SUM(P8:X8) -> 6517732.3 | Z8: =Y8*(P_GG+P_SUP+P_ET) -> 982701.38 | AA8: =Y8+Z8 -> 7500433.7 | AB8: =IF(D8=0,0,AA8/D8) -> 44536.483 | AC8: =J8*(1+P_RECALCE)*CU_PLANTON_NC+J8*CU_PLANTA_NC+(E8+F8)*CU_HA_NC+S8+K8*CU_ZANJA_NC+L8*CU_TERRAZA_NC+M8*CU_CERCO_NC+N8*CU_CARCAVA_NC -> 3790003 | AD8: =J8*(1+P_RECALCE)*CU_PLANTON_C+J8*CU_PLANTA_C+(E8+F8)*CU_HA_C+K8*CU_ZANJA_C+L8*CU_TERRAZA_C+M8*CU_CERCO_C+N8*CU_CARCAVA_C -> 585065.26 | AE8: =Y8-AC8-AD8 -> 2142664.1 | AF8: =AC8*P_FC_MONC+AD8*P_FC_MOC+(AE8+Z8)*P_FC_BIEN -> 4702617.6 | AG8: =(SUM(P8:T8)+W8)*(1+P_GG+P_SUP+P_ET) -> 492627.23 | AH8: =(U8+V8+X8)*(1+P_GG+P_SUP+P_ET) -> 7007806.5
A9: =BLOQUES!A9 -> 36 | B9: =BLOQUES!AI9 -> T6 | C9: =BLOQUES!AE9 -> No | D9: =BLOQUES!E9 -> 24.843 | E9: =BLOQUES!U9+BLOQUES!V9 -> 0.347 | F9: =BLOQUES!W9+BLOQUES!X9 -> 8.505 | G9: =BLOQUES!Y9+BLOQUES!Z9 -> 15.991 | H9: =E9*INDEX(PAQ_R1,MATCH(B9,PAQ_T,0)) -> 225.55 | I9: =F9*INDEX(PAQ_R2,MATCH(B9,PAQ_T,0)) -> 2764.125 | J9: =H9+I9 -> 2989.675 | K9: =(BLOQUES!U9+BLOQUES!W9)*INDEX(PAQ_MZ,MATCH(B9,PAQ_T,0))/1000 -> 0 | L9: =(BLOQUES!U9+BLOQUES!W9)*INDEX(PAQ_MT,MATCH(B9,PAQ_T,0))/1000 -> 10.622442 | M9: =BLOQUES!F9*INDEX(PAQ_CERCO,MATCH(B9,PAQ_T,0)) -> 2675.4 | N9: =IF(ISNUMBER(BLOQUES!AD9),BLOQUES!AD9/1000,0) -> 0 | O9: =P_JORNAL/(P_CARGA*(P_HORAS*P_EFIC/((BLOQUES!AB9/1000*P_SINUOS)/P_VIDA+(BLOQUES!AB9/1000*P_SINUOS)/P_VVUELTA+P_TCD/60))) -> 0.061820175 | P9: =J9*(1+P_RECALCE)*CU_PLANTON -> 4385.0311 | Q9: =J9*CU_PLANTA -> 20511.807 | R9: =(E9+F9)*CU_HA -> 9916.5032 | S9: =J9*(1+P_RECALCE)*(P_PESO_PLANTON+P_PESO_INS)*O9 -> 339.51844 | T9: =J9*(1+P_RECALCE)*P_PESO_INS*P_FT_KG -> 119.85474 | U9: =K9*CU_ZANJA -> 0 | V9: =L9*CU_TERRAZA -> 957980.64 | W9: =M9*CU_CERCO -> 58778.01 | X9: =N9*CU_CARCAVA -> 0 | Y9: =SUM(P9:X9) -> 1052031.4 | Z9: =Y9*(P_GG+P_SUP+P_ET) -> 158618.46 | AA9: =Y9+Z9 -> 1210649.8 | AB9: =IF(D9=0,0,AA9/D9) -> 48732.03 | AC9: =J9*(1+P_RECALCE)*CU_PLANTON_NC+J9*CU_PLANTA_NC+(E9+F9)*CU_HA_NC+S9+K9*CU_ZANJA_NC+L9*CU_TERRAZA_NC+M9*CU_CERCO_NC+N9*CU_CARCAVA_NC -> 594255.35 | AD9: =J9*(1+P_RECALCE)*CU_PLANTON_C+J9*CU_PLANTA_C+(E9+F9)*CU_HA_C+K9*CU_ZANJA_C+L9*CU_TERRAZA_C+M9*CU_CERCO_C+N9*CU_CARCAVA_C -> 91864.649 | AE9: =Y9-AC9-AD9 -> 365911.37 | AF9: =AC9*P_FC_MONC+AD9*P_FC_MOC+(AE9+Z9)*P_FC_BIEN -> 766677.13 | AG9: =(SUM(P9:T9)+W9)*(1+P_GG+P_SUP+P_ET) -> 108231.08 | AH9: =(U9+V9+X9)*(1+P_GG+P_SUP+P_ET) -> 1102418.7
A10: =BLOQUES!A10 -> 27 | B10: =BLOQUES!AI10 -> T6 | C10: =BLOQUES!AE10 -> No | D10: =BLOQUES!E10 -> 78.154 | E10: =BLOQUES!U10+BLOQUES!V10 -> 0.804 | F10: =BLOQUES!W10+BLOQUES!X10 -> 28.502 | G10: =BLOQUES!Y10+BLOQUES!Z10 -> 48.848 | H10: =E10*INDEX(PAQ_R1,MATCH(B10,PAQ_T,0)) -> 522.6 | I10: =F10*INDEX(PAQ_R2,MATCH(B10,PAQ_T,0)) -> 9263.15 | J10: =H10+I10 -> 9785.75 | K10: =(BLOQUES!U10+BLOQUES!W10)*INDEX(PAQ_MZ,MATCH(B10,PAQ_T,0))/1000 -> 0 | L10: =(BLOQUES!U10+BLOQUES!W10)*INDEX(PAQ_MT,MATCH(B10,PAQ_T,0))/1000 -> 31.531326 | M10: =BLOQUES!F10*INDEX(PAQ_CERCO,MATCH(B10,PAQ_T,0)) -> 4228.3 | N10: =IF(ISNUMBER(BLOQUES!AD10),BLOQUES!AD10/1000,0) -> 0 | O10: =P_JORNAL/(P_CARGA*(P_HORAS*P_EFIC/((BLOQUES!AB10/1000*P_SINUOS)/P_VIDA+(BLOQUES!AB10/1000*P_SINUOS)/P_VVUELTA+P_TCD/60))) -> 0.12949287 | P10: =J10*(1+P_RECALCE)*CU_PLANTON -> 14353.004 | Q10: =J10*CU_PLANTA -> 67138.876 | R10: =(E10+F10)*CU_HA -> 32830.213 | S10: =J10*(1+P_RECALCE)*(P_PESO_PLANTON+P_PESO_INS)*O10 -> 2327.8186 | T10: =J10*(1+P_RECALCE)*P_PESO_INS*P_FT_KG -> 392.30635 | U10: =K10*CU_ZANJA -> 0 | V10: =L10*CU_TERRAZA -> 2843639.8 | W10: =M10*CU_CERCO -> 92894.916 | X10: =N10*CU_CARCAVA -> 0 | Y10: =SUM(P10:X10) -> 3053576.9 | Z10: =Y10*(P_GG+P_SUP+P_ET) -> 460398.51 | AA10: =Y10+Z10 -> 3513975.4 | AB10: =IF(D10=0,0,AA10/D10) -> 44962.196 | AC10: =J10*(1+P_RECALCE)*CU_PLANTON_NC+J10*CU_PLANTA_NC+(E10+F10)*CU_HA_NC+S10+K10*CU_ZANJA_NC+L10*CU_TERRAZA_NC+M10*CU_CERCO_NC+N10*CU_CARCAVA_NC -> 1772081 | AD10: =J10*(1+P_RECALCE)*CU_PLANTON_C+J10*CU_PLANTA_C+(E10+F10)*CU_HA_C+K10*CU_ZANJA_C+L10*CU_TERRAZA_C+M10*CU_CERCO_C+N10*CU_CARCAVA_C -> 273462.54 | AE10: =Y10-AC10-AD10 -> 1008033.4 | AF10: =AC10*P_FC_MONC+AD10*P_FC_MOC+(AE10+Z10)*P_FC_BIEN -> 2204743.3 | AG10: =(SUM(P10:T10)+W10)*(1+P_GG+P_SUP+P_ET) -> 241590.09 | AH10: =(U10+V10+X10)*(1+P_GG+P_SUP+P_ET) -> 3272385.3
A11: =BLOQUES!A11 -> M17B10 | B11: =BLOQUES!AI11 -> T5 | C11: =BLOQUES!AE11 -> No | D11: =BLOQUES!E11 -> 75.363 | E11: =BLOQUES!U11+BLOQUES!V11 -> 2.346 | F11: =BLOQUES!W11+BLOQUES!X11 -> 52.919 | G11: =BLOQUES!Y11+BLOQUES!Z11 -> 20.099 | H11: =E11*INDEX(PAQ_R1,MATCH(B11,PAQ_T,0)) -> 1524.9 | I11: =F11*INDEX(PAQ_R2,MATCH(B11,PAQ_T,0)) -> 17198.675 | J11: =H11+I11 -> 18723.575 | K11: =(BLOQUES!U11+BLOQUES!W11)*INDEX(PAQ_MZ,MATCH(B11,PAQ_T,0))/1000 -> 0 | L11: =(BLOQUES!U11+BLOQUES!W11)*INDEX(PAQ_MT,MATCH(B11,PAQ_T,0))/1000 -> 63.661455 | M11: =BLOQUES!F11*INDEX(PAQ_CERCO,MATCH(B11,PAQ_T,0)) -> 3644.3 | N11: =IF(ISNUMBER(BLOQUES!AD11),BLOQUES!AD11/1000,0) -> 0 | O11: =P_JORNAL/(P_CARGA*(P_HORAS*P_EFIC/((BLOQUES!AB11/1000*P_SINUOS)/P_VIDA+(BLOQUES!AB11/1000*P_SINUOS)/P_VVUELTA+P_TCD/60))) -> 0.12778235 | P11: =J11*(1+P_RECALCE)*CU_PLANTON -> 27462.336 | Q11: =J11*CU_PLANTA -> 128460.24 | R11: =(E11+F11)*CU_HA -> 61910.93 | S11: =J11*(1+P_RECALCE)*(P_PESO_PLANTON+P_PESO_INS)*O11 -> 4395.1003 | T11: =J11*(1+P_RECALCE)*P_PESO_INS*P_FT_KG -> 750.61977 | U11: =K11*CU_ZANJA -> 0 | V11: =L11*CU_TERRAZA -> 5741282.3 | W11: =M11*CU_CERCO -> 80064.552 | X11: =N11*CU_CARCAVA -> 0 | Y11: =SUM(P11:X11) -> 6044326.1 | Z11: =Y11*(P_GG+P_SUP+P_ET) -> 911324.26 | AA11: =Y11+Z11 -> 6955650.4 | AB11: =IF(D11=0,0,AA11/D11) -> 92295.296 | AC11: =J11*(1+P_RECALCE)*CU_PLANTON_NC+J11*CU_PLANTA_NC+(E11+F11)*CU_HA_NC+S11+K11*CU_ZANJA_NC+L11*CU_TERRAZA_NC+M11*CU_CERCO_NC+N11*CU_CARCAVA_NC -> 3569436.3 | AD11: =J11*(1+P_RECALCE)*CU_PLANTON_C+J11*CU_PLANTA_C+(E11+F11)*CU_HA_C+K11*CU_ZANJA_C+L11*CU_TERRAZA_C+M11*CU_CERCO_C+N11*CU_CARCAVA_C -> 551166.02 | AE11: =Y11-AC11-AD11 -> 1923723.7 | AF11: =AC11*P_FC_MONC+AD11*P_FC_MOC+(AE11+Z11)*P_FC_BIEN -> 4337167.5 | AG11: =(SUM(P11:T11)+W11)*(1+P_GG+P_SUP+P_ET) -> 348734.75 | AH11: =(U11+V11+X11)*(1+P_GG+P_SUP+P_ET) -> 6606915.6
A12: =BLOQUES!A12 -> M17B5 | B12: =BLOQUES!AI12 -> T2 | C12: =BLOQUES!AE12 -> No | D12: =BLOQUES!E12 -> 74.028 | E12: =BLOQUES!U12+BLOQUES!V12 -> 0.435 | F12: =BLOQUES!W12+BLOQUES!X12 -> 20.99 | G12: =BLOQUES!Y12+BLOQUES!Z12 -> 52.602 | H12: =E12*INDEX(PAQ_R1,MATCH(B12,PAQ_T,0)) -> 282.75 | I12: =F12*INDEX(PAQ_R2,MATCH(B12,PAQ_T,0)) -> 6821.75 | J12: =H12+I12 -> 7104.5 | K12: =(BLOQUES!U12+BLOQUES!W12)*INDEX(PAQ_MZ,MATCH(B12,PAQ_T,0))/1000 -> 72.874217 | L12: =(BLOQUES!U12+BLOQUES!W12)*INDEX(PAQ_MT,MATCH(B12,PAQ_T,0))/1000 -> 0 | M12: =BLOQUES!F12*INDEX(PAQ_CERCO,MATCH(B12,PAQ_T,0)) -> 4276.5 | N12: =IF(ISNUMBER(BLOQUES!AD12),BLOQUES!AD12/1000,0) -> 0 | O12: =P_JORNAL/(P_CARGA*(P_HORAS*P_EFIC/((BLOQUES!AB12/1000*P_SINUOS)/P_VIDA+(BLOQUES!AB12/1000*P_SINUOS)/P_VVUELTA+P_TCD/60))) -> 0.22528235 | P12: =J12*(1+P_RECALCE)*CU_PLANTON -> 10420.348 | Q12: =J12*CU_PLANTA -> 48743.136 | R12: =(E12+F12)*CU_HA -> 24001.478 | S12: =J12*(1+P_RECALCE)*(P_PESO_PLANTON+P_PESO_INS)*O12 -> 2940.1524 | T12: =J12*(1+P_RECALCE)*P_PESO_INS*P_FT_KG -> 284.81623 | U12: =K12*CU_ZANJA -> 700000.56 | V12: =L12*CU_TERRAZA -> 0 | W12: =M12*CU_CERCO -> 93953.861 | X12: =N12*CU_CARCAVA -> 0 | Y12: =SUM(P12:X12) -> 880344.36 | Z12: =Y12*(P_GG+P_SUP+P_ET) -> 132732.61 | AA12: =Y12+Z12 -> 1013077 | AB12: =IF(D12=0,0,AA12/D12) -> 13685.051 | AC12: =J12*(1+P_RECALCE)*CU_PLANTON_NC+J12*CU_PLANTA_NC+(E12+F12)*CU_HA_NC+S12+K12*CU_ZANJA_NC+L12*CU_TERRAZA_NC+M12*CU_CERCO_NC+N12*CU_CARCAVA_NC -> 652408.79 | AD12: =J12*(1+P_RECALCE)*CU_PLANTON_C+J12*CU_PLANTA_C+(E12+F12)*CU_HA_C+K12*CU_ZANJA_C+L12*CU_TERRAZA_C+M12*CU_CERCO_C+N12*CU_CARCAVA_C -> 53058.166 | AE12: =Y12-AC12-AD12 -> 174877.4 | AF12: =AC12*P_FC_MONC+AD12*P_FC_MOC+(AE12+Z12)*P_FC_BIEN -> 576614.09 | AG12: =(SUM(P12:T12)+W12)*(1+P_GG+P_SUP+P_ET) -> 207534.86 | AH12: =(U12+V12+X12)*(1+P_GG+P_SUP+P_ET) -> 805542.11
A13: =BLOQUES!A13 -> M17B6 | B13: =BLOQUES!AI13 -> T1 | C13: =BLOQUES!AE13 -> No | D13: =BLOQUES!E13 -> 106.538 | E13: =BLOQUES!U13+BLOQUES!V13 -> 13.362 | F13: =BLOQUES!W13+BLOQUES!X13 -> 73.807 | G13: =BLOQUES!Y13+BLOQUES!Z13 -> 19.37 | H13: =E13*INDEX(PAQ_R1,MATCH(B13,PAQ_T,0)) -> 8685.3 | I13: =F13*INDEX(PAQ_R2,MATCH(B13,PAQ_T,0)) -> 23987.275 | J13: =H13+I13 -> 32672.575 | K13: =(BLOQUES!U13+BLOQUES!W13)*INDEX(PAQ_MZ,MATCH(B13,PAQ_T,0))/1000 -> 275.92339 | L13: =(BLOQUES!U13+BLOQUES!W13)*INDEX(PAQ_MT,MATCH(B13,PAQ_T,0))/1000 -> 0 | M13: =BLOQUES!F13*INDEX(PAQ_CERCO,MATCH(B13,PAQ_T,0)) -> 6508.8 | N13: =IF(ISNUMBER(BLOQUES!AD13),BLOQUES!AD13/1000,0) -> 0 | O13: =P_JORNAL/(P_CARGA*(P_HORAS*P_EFIC/((BLOQUES!AB13/1000*P_SINUOS)/P_VIDA+(BLOQUES!AB13/1000*P_SINUOS)/P_VVUELTA+P_TCD/60))) -> 0.10062774 | P13: =J13*(1+P_RECALCE)*CU_PLANTON -> 47921.683 | Q13: =J13*CU_PLANTA -> 224162.68 | R13: =(E13+F13)*CU_HA -> 97651.567 | S13: =J13*(1+P_RECALCE)*(P_PESO_PLANTON+P_PESO_INS)*O13 -> 6039.6288 | T13: =J13*(1+P_RECALCE)*P_PESO_INS*P_FT_KG -> 1309.829 | U13: =K13*CU_ZANJA -> 2650409.7 | V13: =L13*CU_TERRAZA -> 0 | W13: =M13*CU_CERCO -> 142997.05 | X13: =N13*CU_CARCAVA -> 0 | Y13: =SUM(P13:X13) -> 3170492.1 | Z13: =Y13*(P_GG+P_SUP+P_ET) -> 478026.23 | AA13: =Y13+Z13 -> 3648518.4 | AB13: =IF(D13=0,0,AA13/D13) -> 34246.169 | AC13: =J13*(1+P_RECALCE)*CU_PLANTON_NC+J13*CU_PLANTA_NC+(E13+F13)*CU_HA_NC+S13+K13*CU_ZANJA_NC+L13*CU_TERRAZA_NC+M13*CU_CERCO_NC+N13*CU_CARCAVA_NC -> 2497738.1 | AD13: =J13*(1+P_RECALCE)*CU_PLANTON_C+J13*CU_PLANTA_C+(E13+F13)*CU_HA_C+K13*CU_ZANJA_C+L13*CU_TERRAZA_C+M13*CU_CERCO_C+N13*CU_CARCAVA_C -> 203717.79 | AE13: =Y13-AC13-AD13 -> 469036.2 | AF13: =AC13*P_FC_MONC+AD13*P_FC_MOC+(AE13+Z13)*P_FC_BIEN -> 2012582.3 | AG13: =(SUM(P13:T13)+W13)*(1+P_GG+P_SUP+P_ET) -> 598497.1 | AH13: =(U13+V13+X13)*(1+P_GG+P_SUP+P_ET) -> 3050021.3
A14: =BLOQUES!A14 -> M17B7 | B14: =BLOQUES!AI14 -> T6 | C14: =BLOQUES!AE14 -> No | D14: =BLOQUES!E14 -> 258.837 | E14: =BLOQUES!U14+BLOQUES!V14 -> 15.062 | F14: =BLOQUES!W14+BLOQUES!X14 -> 110.204 | G14: =BLOQUES!Y14+BLOQUES!Z14 -> 133.572 | H14: =E14*INDEX(PAQ_R1,MATCH(B14,PAQ_T,0)) -> 9790.3 | I14: =F14*INDEX(PAQ_R2,MATCH(B14,PAQ_T,0)) -> 35816.3 | J14: =H14+I14 -> 45606.6 | K14: =(BLOQUES!U14+BLOQUES!W14)*INDEX(PAQ_MZ,MATCH(B14,PAQ_T,0))/1000 -> 0 | L14: =(BLOQUES!U14+BLOQUES!W14)*INDEX(PAQ_MT,MATCH(B14,PAQ_T,0))/1000 -> 148.06139 | M14: =BLOQUES!F14*INDEX(PAQ_CERCO,MATCH(B14,PAQ_T,0)) -> 12968.1 | N14: =IF(ISNUMBER(BLOQUES!AD14),BLOQUES!AD14/1000,0) -> 0 | O14: =P_JORNAL/(P_CARGA*(P_HORAS*P_EFIC/((BLOQUES!AB14/1000*P_SINUOS)/P_VIDA+(BLOQUES!AB14/1000*P_SINUOS)/P_VVUELTA+P_TCD/60))) -> 0.09560307 | P14: =J14*(1+P_RECALCE)*CU_PLANTON -> 66892.341 | Q14: =J14*CU_PLANTA -> 312901.5 | R14: =(E14+F14)*CU_HA -> 140329.95 | S14: =J14*(1+P_RECALCE)*(P_PESO_PLANTON+P_PESO_INS)*O14 -> 8009.5606 | T14: =J14*(1+P_RECALCE)*P_PESO_INS*P_FT_KG -> 1828.3482 | U14: =K14*CU_ZANJA -> 0 | V14: =L14*CU_TERRAZA -> 13352856 | W14: =M14*CU_CERCO -> 284906.6 | X14: =N14*CU_CARCAVA -> 0 | Y14: =SUM(P14:X14) -> 14167725 | Z14: =Y14*(P_GG+P_SUP+P_ET) -> 2136117.6 | AA14: =Y14+Z14 -> 16303842 | AB14: =IF(D14=0,0,AA14/D14) -> 62988.839 | AC14: =J14*(1+P_RECALCE)*CU_PLANTON_NC+J14*CU_PLANTA_NC+(E14+F14)*CU_HA_NC+S14+K14*CU_ZANJA_NC+L14*CU_TERRAZA_NC+M14*CU_CERCO_NC+N14*CU_CARCAVA_NC -> 8306791.5 | AD14: =J14*(1+P_RECALCE)*CU_PLANTON_C+J14*CU_PLANTA_C+(E14+F14)*CU_HA_C+K14*CU_ZANJA_C+L14*CU_TERRAZA_C+M14*CU_CERCO_C+N14*CU_CARCAVA_C -> 1282029.6 | AE14: =Y14-AC14-AD14 -> 4578903.5 | AF14: =AC14*P_FC_MONC+AD14*P_FC_MOC+(AE14+Z14)*P_FC_BIEN -> 10192352 | AG14: =(SUM(P14:T14)+W14)*(1+P_GG+P_SUP+P_ET) -> 937728.85 | AH14: =(U14+V14+X14)*(1+P_GG+P_SUP+P_ET) -> 15366113
A15: =BLOQUES!A15 -> 39 | B15: =BLOQUES!AI15 -> T4 | C15: =BLOQUES!AE15 -> No | D15: =BLOQUES!E15 -> 68.569 | E15: =BLOQUES!U15+BLOQUES!V15 -> 0 | F15: =BLOQUES!W15+BLOQUES!X15 -> 2.635 | G15: =BLOQUES!Y15+BLOQUES!Z15 -> 65.934 | H15: =E15*INDEX(PAQ_R1,MATCH(B15,PAQ_T,0)) -> 0 | I15: =F15*INDEX(PAQ_R2,MATCH(B15,PAQ_T,0)) -> 951.235 | J15: =H15+I15 -> 951.235 | K15: =(BLOQUES!U15+BLOQUES!W15)*INDEX(PAQ_MZ,MATCH(B15,PAQ_T,0))/1000 -> 9.0755274 | L15: =(BLOQUES!U15+BLOQUES!W15)*INDEX(PAQ_MT,MATCH(B15,PAQ_T,0))/1000 -> 0 | M15: =BLOQUES!F15*INDEX(PAQ_CERCO,MATCH(B15,PAQ_T,0)) -> 3605.6 | N15: =IF(ISNUMBER(BLOQUES!AD15),BLOQUES!AD15/1000,0) -> 0 | O15: =P_JORNAL/(P_CARGA*(P_HORAS*P_EFIC/((BLOQUES!AB15/1000*P_SINUOS)/P_VIDA+(BLOQUES!AB15/1000*P_SINUOS)/P_VVUELTA+P_TCD/60))) -> 0.10800439 | P15: =J15*(1+P_RECALCE)*CU_PLANTON -> 1395.2002 | Q15: =J15*CU_PLANTA -> 6526.3111 | R15: =(E15+F15)*CU_HA -> 2951.8737 | S15: =J15*(1+P_RECALCE)*(P_PESO_PLANTON+P_PESO_INS)*O15 -> 188.72888 | T15: =J15*(1+P_RECALCE)*P_PESO_INS*P_FT_KG -> 38.134587 | U15: =K15*CU_ZANJA -> 87175.884 | V15: =L15*CU_TERRAZA -> 0 | W15: =M15*CU_CERCO -> 79214.32 | X15: =N15*CU_CARCAVA -> 0 | Y15: =SUM(P15:X15) -> 177490.45 | Z15: =Y15*(P_GG+P_SUP+P_ET) -> 26760.859 | AA15: =Y15+Z15 -> 204251.31 | AB15: =IF(D15=0,0,AA15/D15) -> 2978.7705 | AC15: =J15*(1+P_RECALCE)*CU_PLANTON_NC+J15*CU_PLANTA_NC+(E15+F15)*CU_HA_NC+S15+K15*CU_ZANJA_NC+L15*CU_TERRAZA_NC+M15*CU_CERCO_NC+N15*CU_CARCAVA_NC -> 81365.647 | AD15: =J15*(1+P_RECALCE)*CU_PLANTON_C+J15*CU_PLANTA_C+(E15+F15)*CU_HA_C+K15*CU_ZANJA_C+L15*CU_TERRAZA_C+M15*CU_CERCO_C+N15*CU_CARCAVA_C -> 6623.9267 | AE15: =Y15-AC15-AD15 -> 89500.879 | AF15: =AC15*P_FC_MONC+AD15*P_FC_MOC+(AE15+Z15)*P_FC_BIEN -> 137933.37 | AG15: =(SUM(P15:T15)+W15)*(1+P_GG+P_SUP+P_ET) -> 103931.61 | AH15: =(U15+V15+X15)*(1+P_GG+P_SUP+P_ET) -> 100319.7
A16: =BLOQUES!A16 -> 56 | B16: =BLOQUES!AI16 -> T4 | C16: =BLOQUES!AE16 -> No | D16: =BLOQUES!E16 -> 77.666 | E16: =BLOQUES!U16+BLOQUES!V16 -> 0.02 | F16: =BLOQUES!W16+BLOQUES!X16 -> 2.151 | G16: =BLOQUES!Y16+BLOQUES!Z16 -> 75.495 | H16: =E16*INDEX(PAQ_R1,MATCH(B16,PAQ_T,0)) -> 14.44 | I16: =F16*INDEX(PAQ_R2,MATCH(B16,PAQ_T,0)) -> 776.511 | J16: =H16+I16 -> 790.951 | K16: =(BLOQUES!U16+BLOQUES!W16)*INDEX(PAQ_MZ,MATCH(B16,PAQ_T,0))/1000 -> 7.7399381 | L16: =(BLOQUES!U16+BLOQUES!W16)*INDEX(PAQ_MT,MATCH(B16,PAQ_T,0))/1000 -> 0 | M16: =BLOQUES!F16*INDEX(PAQ_CERCO,MATCH(B16,PAQ_T,0)) -> 3472.6 | N16: =IF(ISNUMBER(BLOQUES!AD16),BLOQUES!AD16/1000,0) -> 0 | O16: =P_JORNAL/(P_CARGA*(P_HORAS*P_EFIC/((BLOQUES!AB16/1000*P_SINUOS)/P_VIDA+(BLOQUES!AB16/1000*P_SINUOS)/P_VVUELTA+P_TCD/60))) -> 0.20015899 | P16: =J16*(1+P_RECALCE)*CU_PLANTON -> 1160.1076 | Q16: =J16*CU_PLANTA -> 5426.6215 | R16: =(E16+F16)*CU_HA -> 2432.0751 | S16: =J16*(1+P_RECALCE)*(P_PESO_PLANTON+P_PESO_INS)*O16 -> 290.82641 | T16: =J16*(1+P_RECALCE)*P_PESO_INS*P_FT_KG -> 31.708873 | U16: =K16*CU_ZANJA -> 74346.748 | V16: =L16*CU_TERRAZA -> 0 | W16: =M16*CU_CERCO -> 76292.337 | X16: =N16*CU_CARCAVA -> 0 | Y16: =SUM(P16:X16) -> 159980.42 | Z16: =Y16*(P_GG+P_SUP+P_ET) -> 24120.81 | AA16: =Y16+Z16 -> 184101.23 | AB16: =IF(D16=0,0,AA16/D16) -> 2370.4225 | AC16: =J16*(1+P_RECALCE)*CU_PLANTON_NC+J16*CU_PLANTA_NC+(E16+F16)*CU_HA_NC+S16+K16*CU_ZANJA_NC+L16*CU_TERRAZA_NC+M16*CU_CERCO_NC+N16*CU_CARCAVA_NC -> 69363.249 | AD16: =J16*(1+P_RECALCE)*CU_PLANTON_C+J16*CU_PLANTA_C+(E16+F16)*CU_HA_C+K16*CU_ZANJA_C+L16*CU_TERRAZA_C+M16*CU_CERCO_C+N16*CU_CARCAVA_C -> 5630.4932 | AE16: =Y16-AC16-AD16 -> 84986.682 | AF16: =AC16*P_FC_MONC+AD16*P_FC_MOC+(AE16+Z16)*P_FC_BIEN -> 126044.63 | AG16: =(SUM(P16:T16)+W16)*(1+P_GG+P_SUP+P_ET) -> 98544.966 | AH16: =(U16+V16+X16)*(1+P_GG+P_SUP+P_ET) -> 85556.268
A17: =BLOQUES!A17 -> 81 | B17: =BLOQUES!AI17 -> T1 | C17: =BLOQUES!AE17 -> No | D17: =BLOQUES!E17 -> 8.929 | E17: =BLOQUES!U17+BLOQUES!V17 -> 8.792 | F17: =BLOQUES!W17+BLOQUES!X17 -> 0.137 | G17: =BLOQUES!Y17+BLOQUES!Z17 -> 0 | H17: =E17*INDEX(PAQ_R1,MATCH(B17,PAQ_T,0)) -> 5714.8 | I17: =F17*INDEX(PAQ_R2,MATCH(B17,PAQ_T,0)) -> 44.525 | J17: =H17+I17 -> 5759.325 | K17: =(BLOQUES!U17+BLOQUES!W17)*INDEX(PAQ_MZ,MATCH(B17,PAQ_T,0))/1000 -> 17.240262 | L17: =(BLOQUES!U17+BLOQUES!W17)*INDEX(PAQ_MT,MATCH(B17,PAQ_T,0))/1000 -> 0 | M17: =BLOQUES!F17*INDEX(PAQ_CERCO,MATCH(B17,PAQ_T,0)) -> 1243.6 | N17: =IF(ISNUMBER(BLOQUES!AD17),BLOQUES!AD17/1000,0) -> 0 | O17: =P_JORNAL/(P_CARGA*(P_HORAS*P_EFIC/((BLOQUES!AB17/1000*P_SINUOS)/P_VIDA+(BLOQUES!AB17/1000*P_SINUOS)/P_VVUELTA+P_TCD/60))) -> 0.075076754 | P17: =J17*(1+P_RECALCE)*CU_PLANTON -> 8447.346 | Q17: =J17*CU_PLANTA -> 39514.049 | R17: =(E17+F17)*CU_HA -> 10002.763 | S17: =J17*(1+P_RECALCE)*(P_PESO_PLANTON+P_PESO_INS)*O17 -> 794.30305 | T17: =J17*(1+P_RECALCE)*P_PESO_INS*P_FT_KG -> 230.88877 | U17: =K17*CU_ZANJA -> 165603.06 | V17: =L17*CU_TERRAZA -> 0 | W17: =M17*CU_CERCO -> 27321.647 | X17: =N17*CU_CARCAVA -> 0 | Y17: =SUM(P17:X17) -> 251914.05 | Z17: =Y17*(P_GG+P_SUP+P_ET) -> 37981.966 | AA17: =Y17+Z17 -> 289896.02 | AB17: =IF(D17=0,0,AA17/D17) -> 32466.796 | AC17: =J17*(1+P_RECALCE)*CU_PLANTON_NC+J17*CU_PLANTA_NC+(E17+F17)*CU_HA_NC+S17+K17*CU_ZANJA_NC+L17*CU_TERRAZA_NC+M17*CU_CERCO_NC+N17*CU_CARCAVA_NC -> 177161.08 | AD17: =J17*(1+P_RECALCE)*CU_PLANTON_C+J17*CU_PLANTA_C+(E17+F17)*CU_HA_C+K17*CU_ZANJA_C+L17*CU_TERRAZA_C+M17*CU_CERCO_C+N17*CU_CARCAVA_C -> 14482.051 | AE17: =Y17-AC17-AD17 -> 60270.925 | AF17: =AC17*P_FC_MONC+AD17*P_FC_MOC+(AE17+Z17)*P_FC_BIEN -> 169113.64 | AG17: =(SUM(P17:T17)+W17)*(1+P_GG+P_SUP+P_ET) -> 99324.409 | AH17: =(U17+V17+X17)*(1+P_GG+P_SUP+P_ET) -> 190571.61
A18: =BLOQUES!A18 -> 79 | B18: =BLOQUES!AI18 -> T2 | C18: =BLOQUES!AE18 -> No | D18: =BLOQUES!E18 -> 94.812 | E18: =BLOQUES!U18+BLOQUES!V18 -> 0.324 | F18: =BLOQUES!W18+BLOQUES!X18 -> 27.828 | G18: =BLOQUES!Y18+BLOQUES!Z18 -> 66.66 | H18: =E18*INDEX(PAQ_R1,MATCH(B18,PAQ_T,0)) -> 210.6 | I18: =F18*INDEX(PAQ_R2,MATCH(B18,PAQ_T,0)) -> 9044.1 | J18: =H18+I18 -> 9254.7 | K18: =(BLOQUES!U18+BLOQUES!W18)*INDEX(PAQ_MZ,MATCH(B18,PAQ_T,0))/1000 -> 35.967312 | L18: =(BLOQUES!U18+BLOQUES!W18)*INDEX(PAQ_MT,MATCH(B18,PAQ_T,0))/1000 -> 0 | M18: =BLOQUES!F18*INDEX(PAQ_CERCO,MATCH(B18,PAQ_T,0)) -> 5495.2 | N18: =IF(ISNUMBER(BLOQUES!AD18),BLOQUES!AD18/1000,0) -> 0 | O18: =P_JORNAL/(P_CARGA*(P_HORAS*P_EFIC/((BLOQUES!AB18/1000*P_SINUOS)/P_VIDA+(BLOQUES!AB18/1000*P_SINUOS)/P_VVUELTA+P_TCD/60))) -> 0.14029057 | P18: =J18*(1+P_RECALCE)*CU_PLANTON -> 13574.1 | Q18: =J18*CU_PLANTA -> 63495.405 | R18: =(E18+F18)*CU_HA -> 31537.438 | S18: =J18*(1+P_RECALCE)*(P_PESO_PLANTON+P_PESO_INS)*O18 -> 2385.0637 | T18: =J18*(1+P_RECALCE)*P_PESO_INS*P_FT_KG -> 371.01679 | U18: =K18*CU_ZANJA -> 345487.61 | V18: =L18*CU_TERRAZA -> 0 | W18: =M18*CU_CERCO -> 120728.46 | X18: =N18*CU_CARCAVA -> 0 | Y18: =SUM(P18:X18) -> 577579.09 | Z18: =Y18*(P_GG+P_SUP+P_ET) -> 87083.627 | AA18: =Y18+Z18 -> 664662.72 | AB18: =IF(D18=0,0,AA18/D18) -> 7010.3227 | AC18: =J18*(1+P_RECALCE)*CU_PLANTON_NC+J18*CU_PLANTA_NC+(E18+F18)*CU_HA_NC+S18+K18*CU_ZANJA_NC+L18*CU_TERRAZA_NC+M18*CU_CERCO_NC+N18*CU_CARCAVA_NC -> 364559.57 | AD18: =J18*(1+P_RECALCE)*CU_PLANTON_C+J18*CU_PLANTA_C+(E18+F18)*CU_HA_C+K18*CU_ZANJA_C+L18*CU_TERRAZA_C+M18*CU_CERCO_C+N18*CU_CARCAVA_C -> 30828.658 | AE18: =Y18-AC18-AD18 -> 182190.87 | AF18: =AC18*P_FC_MONC+AD18*P_FC_MOC+(AE18+Z18)*P_FC_BIEN -> 405668.38 | AG18: =(SUM(P18:T18)+W18)*(1+P_GG+P_SUP+P_ET) -> 267084.73 | AH18: =(U18+V18+X18)*(1+P_GG+P_SUP+P_ET) -> 397577.99
... A123: =BLOQUES!A123 -> M28B4 | B123: =BLOQUES!AI123 -> T1 | C123: =BLOQUES!AE123 -> No | D123: =BLOQUES!E123 -> 283.428 | E123: =BLOQUES!U123+BLOQUES!V123 -> 104.426 | F123: =BLOQUES!W123+BLOQUES!X123 -> 107.598 | G123: =BLOQUES!Y123+BLOQUES!Z123 -> 71.405 | H123: =E123*INDEX(PAQ_R1,MATCH(B123,PAQ_T,0)) -> 67876.9 | I123: =F123*INDEX(PAQ_R2,MATCH(B123,PAQ_T,0)) -> 34969.35 | J123: =H123+I123 -> 102846.25 | K123: =(BLOQUES!U123+BLOQUES!W123)*INDEX(PAQ_MZ,MATCH(B123,PAQ_T,0))/1000 -> 209.98632 | L123: =(BLOQUES!U123+BLOQUES!W123)*INDEX(PAQ_MT,MATCH(B123,PAQ_T,0))/1000 -> 0 | M123: =BLOQUES!F123*INDEX(PAQ_CERCO,MATCH(B123,PAQ_T,0)) -> 8181.3 | N123: =IF(ISNUMBER(BLOQUES!AD123),BLOQUES!AD123/1000,0) -> 0 | O123: =P_JORNAL/(P_CARGA*(P_HORAS*P_EFIC/((BLOQUES!AB123/1000*P_SINUOS)/P_VIDA+(BLOQUES!AB123/1000*P_SINUOS)/P_VVUELTA+P_TCD/60))) -> 0.12682018 | P123: =J123*(1+P_RECALCE)*CU_PLANTON -> 150847.17 | Q123: =J123*CU_PLANTA -> 705615.99 | R123: =(E123+F123)*CU_HA -> 237521.09 | S123: =J123*(1+P_RECALCE)*(P_PESO_PLANTON+P_PESO_INS)*O123 -> 23959.953 | T123: =J123*(1+P_RECALCE)*P_PESO_INS*P_FT_KG -> 4123.0603 | U123: =K123*CU_ZANJA -> 2017044.6 | V123: =L123*CU_TERRAZA -> 0 | W123: =M123*CU_CERCO -> 179741.55 | X123: =N123*CU_CARCAVA -> 0 | Y123: =SUM(P123:X123) -> 3318853.4 | Z123: =Y123*(P_GG+P_SUP+P_ET) -> 500395.17 | AA123: =Y123+Z123 -> 3819248.5 | AB123: =IF(D123=0,0,AA123/D123) -> 13475.198 | AC123: =J123*(1+P_RECALCE)*CU_PLANTON_NC+J123*CU_PLANTA_NC+(E123+F123)*CU_HA_NC+S123+K123*CU_ZANJA_NC+L123*CU_TERRAZA_NC+M123*CU_CERCO_NC+N123*CU_CARCAVA_NC -> 2411491.8 | AD123: =J123*(1+P_RECALCE)*CU_PLANTON_C+J123*CU_PLANTA_C+(E123+F123)*CU_HA_C+K123*CU_ZANJA_C+L123*CU_TERRAZA_C+M123*CU_CERCO_C+N123*CU_CARCAVA_C -> 203313.94 | AE123: =Y123-AC123-AD123 -> 704047.57 | AF123: =AC123*P_FC_MONC+AD123*P_FC_MOC+(AE123+Z123)*P_FC_BIEN -> 2194158.8 | AG123: =(SUM(P123:T123)+W123)*(1+P_GG+P_SUP+P_ET) -> 1498087.1 | AH123: =(U123+V123+X123)*(1+P_GG+P_SUP+P_ET) -> 2321161.4
